Workbook
Name solver_eng: 0
Name solver_eng: 0
Name solver_eng: 0
Name solver_eng: 0
Name solver_eng: 0
Name solver_eng: 0
Name solver_eng: 0
Name solver_eng: 0
Name solver_eng: 0
Name solver_eng: 0
Name solver_eng: 0
Name solver_eng: 0
Name solver_eng: 0
Name solver_eng: 0
Name solver_eng: 0
Name solver_eng: 0
Name solver_eng: 0
Name solver_eng: 0
Name solver_eng: 0
Name solver_eng: 0
Name solver_eng: 0
Name solver_eng: 0
Name solver_eng: 0
Name solver_eng: 0

Sheet ScenarioParameters
A1: Scenario input parameters | D1: Data imported from Winter's method | E1: Year | F1: Quarter | G1: =IFERROR(__xludf.DUMMYFUNCTION("IMPORTRANGE(""https://docs.google.com/spreadsheets/d/1Y3ibnN86RzRcOvz_3iryQpOSIamHQku_1S-6YqExw5w/edit?gid=1531545304#gid=1531545304"", ""Winter!H1:H18"")"),"Forecast") -> Forecast
A2: Sales & Product Volume (units/year) | B2: Values imported from forecast
A3: Development Cost (total $) | B3: 60480 | E3: 1 | F3: 1 | G3: =IFERROR(__xludf.DUMMYFUNCTION("""COMPUTED_VALUE"""),3106.96607) -> 3106.9661
A4: Unit price ($/unit) | B4: 299 | E4: 1 | F4: 2 | G4: =IFERROR(__xludf.DUMMYFUNCTION("""COMPUTED_VALUE"""),7938.07622732285) -> 7938.0762
A5: Unit Productions Cost ($/unit) | B5: 115.28 | E5: 1 | F5: 3 | G5: =IFERROR(__xludf.DUMMYFUNCTION("""COMPUTED_VALUE"""),6160.35736753071) -> 6160.3574
A6: Ramp-up cost (total S) | B6: 6048 | E6: 1 | F6: 4 | G6: =IFERROR(__xludf.DUMMYFUNCTION("""COMPUTED_VALUE"""),11872.917093341) -> 11872.917
A7: Marketing & suppost cost ($/year) | B7: 840000 | E7: 2 | F7: 1 | G7: =IFERROR(__xludf.DUMMYFUNCTION("""COMPUTED_VALUE"""),6518.25608721043) -> 6518.2561
A8: Annual Discount Factor (%) | B8: 7 | E8: 2 | F8: 2 | G8: =IFERROR(__xludf.DUMMYFUNCTION("""COMPUTED_VALUE"""),12977.6452429524) -> 12977.645
E9: 2 | F9: 3 | G9: =IFERROR(__xludf.DUMMYFUNCTION("""COMPUTED_VALUE"""),8761.31976315513) -> 8761.3198
E10: 2 | F10: 4 | G10: =IFERROR(__xludf.DUMMYFUNCTION("""COMPUTED_VALUE"""),15586.1371602808) -> 15586.137
E11: 3 | F11: 1 | G11: =IFERROR(__xludf.DUMMYFUNCTION("""COMPUTED_VALUE"""),8260.82892471973) -> 8260.8289
E12: 3 | F12: 2 | G12: =IFERROR(__xludf.DUMMYFUNCTION("""COMPUTED_VALUE"""),16215.6619147742) -> 16215.662
E13: 3 | F13: 3 | G13: =IFERROR(__xludf.DUMMYFUNCTION("""COMPUTED_VALUE"""),10767.2672275139) -> 10767.267
E14: 3 | F14: 4 | G14: =IFERROR(__xludf.DUMMYFUNCTION("""COMPUTED_VALUE"""),18944.3198782037) -> 18944.32
E15: 4 | F15: 1 | G15: =IFERROR(__xludf.DUMMYFUNCTION("""COMPUTED_VALUE"""),10119.1388926823) -> 10119.139
E16: 4 | F16: 2 | G16: =IFERROR(__xludf.DUMMYFUNCTION("""COMPUTED_VALUE"""),19669.2232429464) -> 19669.223
E17: 4 | F17: 3 | G17: =IFERROR(__xludf.DUMMYFUNCTION("""COMPUTED_VALUE"""),12944.5202254938) -> 12944.52
E18: 4 | F18: 4 | G18: =IFERROR(__xludf.DUMMYFUNCTION("""COMPUTED_VALUE"""),22590.7225478699) -> 22590.723

Sheet BaseCase
A1: BaseCase
B2: Year 0, Development | F2: Year 1, Projection | J2: Year 2, Projection | N2: Year 3, Projection | R2: Year 4, Projection
A3: Period | B3: 1 | C3: =B3+1 -> 2 | D3: =C3+1 -> 3 | E3: =D3+1 -> 4 | F3: =E3+1 -> 5 | G3: =F3+1 -> 6 | H3: =G3+1 -> 7 | I3: =H3+1 -> 8 | J3: =I3+1 -> 9 | ... U3: =T3+1 -> 20
A4: ($Value in thousands) | B4: Q1 | C4: Q2 | D4: Q3 | E4: Q4 | F4: Q1 | G4: Q2 | H4: Q3 | I4: Q4 | J4: Q1 | K4: Q2 | L4: Q3 | M4: Q4 | N4: Q1 | O4: Q2 | P4: Q3 | Q4: Q4 | R4: Q1 | S4: Q2 | T4: Q3 | U4: Q4
A6: Development Cost | B6: =(-1)*ScenarioParameters!$B$3/4*(1/1000) -> -15.12 | C6: =(-1)*ScenarioParameters!$B$3/4*(1/1000) -> -15.12 | D6: =(-1)*ScenarioParameters!$B$3/4*(1/1000) -> -15.12 | E6: =(-1)*ScenarioParameters!$B$3/4*(1/1000) -> -15.12
A7: Ramp-up cost | E7: =(-1)*ScenarioParameters!$B$6/2*(1/1000) -> -3.024 | F7: =(-1)*ScenarioParameters!$B$6/2*(1/1000) -> -3.024
A8: Marketing & support cost | F8: =(-1)*ScenarioParameters!$B$7/4*(1/1000) -> -210 | G8: =(-1)*ScenarioParameters!$B$7/4*(1/1000) -> -210 | H8: =(-1)*ScenarioParameters!$B$7/4*(1/1000) -> -210 | I8: =(-1)*ScenarioParameters!$B$7/4*(1/1000) -> -210 | J8: =(-1)*ScenarioParameters!$B$7/4*(1/1000) -> -210 | K8: =(-1)*ScenarioParameters!$B$7/4*(1/1000) -> -210 | L8: =(-1)*ScenarioParameters!$B$7/4*(1/1000) -> -210 | M8: =(-1)*ScenarioParameters!$B$7/4*(1/1000) -> -210 | ... U8: =(-1)*ScenarioParameters!$B$7/4*(1/1000) -> -210
A9: Production Cost | F9: =(-1)*(ScenarioParameters!$B$5)*ScenarioParameters!$G3*(1/1000) -> -358.17105 | G9: =(-1)*(ScenarioParameters!$B$5)*ScenarioParameters!$G4*(1/1000) -> -915.10143 | H9: =(-1)*(ScenarioParameters!$B$5)*ScenarioParameters!$G5*(1/1000) -> -710.166 | I9: =(-1)*(ScenarioParameters!$B$5)*ScenarioParameters!$G6*(1/1000) -> -1368.7099 | J9: =(-1)*(ScenarioParameters!$B$5)*ScenarioParameters!$G7*(1/1000) -> -751.42456 | K9: =(-1)*(ScenarioParameters!$B$5)*ScenarioParameters!$G8*(1/1000) -> -1496.0629 | L9: =(-1)*(ScenarioParameters!$B$5)*ScenarioParameters!$G9*(1/1000) -> -1010.0049 | M9: =(-1)*(ScenarioParameters!$B$5)*ScenarioParameters!$G10*(1/1000) -> -1796.7699 | N9: =(-1)*(ScenarioParameters!$B$5)*ScenarioParameters!$G11*(1/1000) -> -952.30836 | O9: =(-1)*(ScenarioParameters!$B$5)*ScenarioParameters!$G12*(1/1000) -> -1869.3415 | P9: =(-1)*(ScenarioParameters!$B$5)*ScenarioParameters!$G13*(1/1000) -> -1241.2506 | Q9: =(-1)*(ScenarioParameters!$B$5)*ScenarioParameters!$G14*(1/1000) -> -2183.9012 | R9: =(-1)*(ScenarioParameters!$B$5)*ScenarioParameters!$G15*(1/1000) -> -1166.5343 | S9: =(-1)*(ScenarioParameters!$B$5)*ScenarioParameters!$G16*(1/1000) -> -2267.4681 | T9: =(-1)*(ScenarioParameters!$B$5)*ScenarioParameters!$G17*(1/1000) -> -1492.2443 | U9: =(-1)*(ScenarioParameters!$B$5)*ScenarioParameters!$G18*(1/1000) -> -2604.2585
A10: Production volume | F10: =ScenarioParameters!$G3 -> 3106.9661 | G10: =ScenarioParameters!$G4 -> 7938.0762 | H10: =ScenarioParameters!$G5 -> 6160.3574 | I10: =ScenarioParameters!$G6 -> 11872.917 | J10: =ScenarioParameters!$G7 -> 6518.2561 | K10: =ScenarioParameters!$G8 -> 12977.645 | L10: =ScenarioParameters!$G9 -> 8761.3198 | M10: =ScenarioParameters!$G10 -> 15586.137 | N10: =ScenarioParameters!$G11 -> 8260.8289 | O10: =ScenarioParameters!$G12 -> 16215.662 | P10: =ScenarioParameters!$G13 -> 10767.267 | Q10: =ScenarioParameters!$G14 -> 18944.32 | R10: =ScenarioParameters!$G15 -> 10119.139 | S10: =ScenarioParameters!$G16 -> 19669.223 | T10: =ScenarioParameters!$G17 -> 12944.52 | U10: =ScenarioParameters!$G18 -> 22590.723
A11: Unit product cost | F11: =F9/F10 -> -0.11528 | G11: =G9/G10 -> -0.11528 | H11: =H9/H10 -> -0.11528 | I11: =I9/I10 -> -0.11528 | J11: =J9/J10 -> -0.11528 | K11: =K9/K10 -> -0.11528 | L11: =L9/L10 -> -0.11528 | M11: =M9/M10 -> -0.11528 | ... U11: =U9/U10 -> -0.11528
A12: Sales revenue | F12: =(ScenarioParameters!$B$4*F10)*(1/1000) -> 928.98285 | G12: =(ScenarioParameters!$B$4*G10)*(1/1000) -> 2373.4848 | H12: =(ScenarioParameters!$B$4*H10)*(1/1000) -> 1841.9469 | I12: =(ScenarioParameters!$B$4*I10)*(1/1000) -> 3550.0022 | J12: =(ScenarioParameters!$B$4*J10)*(1/1000) -> 1948.9586 | K12: =(ScenarioParameters!$B$4*K10)*(1/1000) -> 3880.3159 | L12: =(ScenarioParameters!$B$4*L10)*(1/1000) -> 2619.6346 | M12: =(ScenarioParameters!$B$4*M10)*(1/1000) -> 4660.255 | ... U12: =(ScenarioParameters!$B$4*U10)*(1/1000) -> 6754.626
A13: Forecasted Sales Volume | F13: =F$10 -> 3106.9661 | G13: =G$10 -> 7938.0762 | H13: =H$10 -> 6160.3574 | I13: =I$10 -> 11872.917 | J13: =J$10 -> 6518.2561 | K13: =K$10 -> 12977.645 | L13: =L$10 -> 8761.3198 | M13: =M$10 -> 15586.137 | ... U13: =U$10 -> 22590.723
A14: Unit price | F14: =F$12/F$13 -> 0.299 | G14: =G$12/G$13 -> 0.299 | H14: =H$12/H$13 -> 0.299 | I14: =I$12/I$13 -> 0.299 | J14: =J$12/J$13 -> 0.299 | K14: =K$12/K$13 -> 0.299 | L14: =L$12/L$13 -> 0.299 | M14: =M$12/M$13 -> 0.299 | ... U14: =U$12/U$13 -> 0.299
A16: Period Cash Flow | B16: =SUM(B6+B7+B8+B9+B12) -> -15.12 | C16: =SUM(C6+C7+C8+C9+C12) -> -15.12 | D16: =SUM(D6+D7+D8+D9+D12) -> -15.12 | E16: =SUM(E6+E7+E8+E9+E12) -> -18.144 | F16: =SUM(F6+F7+F8+F9+F12) -> 357.78781 | G16: =SUM(G6+G7+G8+G9+G12) -> 1248.3834 | H16: =SUM(H6+H7+H8+H9+H12) -> 921.78086 | I16: =SUM(I6+I7+I8+I9+I12) -> 1971.2923 | ... U16: =SUM(U6+U7+U8+U9+U12) -> 3940.3675
A17: Unit Price | B17: =B16 -> -15.12 | C17: =C16/(1+(ScenarioParameters!$B$8/100)/4)^B3 -> -14.859951 | D17: =D16/(1+(ScenarioParameters!$B$8/100)/4)^C3 -> -14.604374 | E17: =E16/(1+(ScenarioParameters!$B$8/100)/4)^D3 -> -17.223832 | F17: =F16/(1+(ScenarioParameters!$B$8/100)/4)^E3 -> 333.80118 | G17: =G16/(1+(ScenarioParameters!$B$8/100)/4)^F3 -> 1144.6584 | H17: =H16/(1+(ScenarioParameters!$B$8/100)/4)^G3 -> 830.65594 | I17: =I16/(1+(ScenarioParameters!$B$8/100)/4)^H3 -> 1745.8628 | J17: =J16/(1+(ScenarioParameters!$B$8/100)/4)^I3 -> 859.56103 | ... U17: =U16/(1+(ScenarioParameters!$B$8/100)/4)^T3 -> 2833.8887
A19: Project NVP | B19: =SUM(B17:U17) -> 25465.99
A21: Forecasted Sales Volume from Winter's forecasting method*

Sheet +10 UnitCost
A1: Unit Cost Analysis: | B1: 0.1
B2: Year 0, Development | F2: Year 1, Projection | J2: Year 2, Projection | N2: Year 3, Projection | R2: Year 4, Projection
A3: Period | B3: 1 | C3: =B3+1 -> 2 | D3: =C3+1 -> 3 | E3: =D3+1 -> 4 | F3: =E3+1 -> 5 | G3: =F3+1 -> 6 | H3: =G3+1 -> 7 | I3: =H3+1 -> 8 | J3: =I3+1 -> 9 | ... U3: =T3+1 -> 20
A4: ($Value in thousands) | B4: Q1 | C4: Q2 | D4: Q3 | E4: Q4 | F4: Q1 | G4: Q2 | H4: Q3 | I4: Q4 | J4: Q1 | K4: Q2 | L4: Q3 | M4: Q4 | N4: Q1 | O4: Q2 | P4: Q3 | Q4: Q4 | R4: Q1 | S4: Q2 | T4: Q3 | U4: Q4
A6: Development Cost | B6: =(-1)*ScenarioParameters!$B$3/4*(1/1000) -> -15.12 | C6: =(-1)*ScenarioParameters!$B$3/4*(1/1000) -> -15.12 | D6: =(-1)*ScenarioParameters!$B$3/4*(1/1000) -> -15.12 | E6: =(-1)*ScenarioParameters!$B$3/4*(1/1000) -> -15.12
A7: Ramp-up cost | E7: =(-1)*ScenarioParameters!$B$6/2*(1/1000) -> -3.024 | F7: =(-1)*ScenarioParameters!$B$6/2*(1/1000) -> -3.024
A8: Marketing & support cost | F8: =(-1)*ScenarioParameters!$B$7/4*(1/1000) -> -210 | G8: =(-1)*ScenarioParameters!$B$7/4*(1/1000) -> -210 | H8: =(-1)*ScenarioParameters!$B$7/4*(1/1000) -> -210 | I8: =(-1)*ScenarioParameters!$B$7/4*(1/1000) -> -210 | J8: =(-1)*ScenarioParameters!$B$7/4*(1/1000) -> -210 | K8: =(-1)*ScenarioParameters!$B$7/4*(1/1000) -> -210 | L8: =(-1)*ScenarioParameters!$B$7/4*(1/1000) -> -210 | M8: =(-1)*ScenarioParameters!$B$7/4*(1/1000) -> -210 | ... U8: =(-1)*ScenarioParameters!$B$7/4*(1/1000) -> -210
A9: Production Cost | F9: =(-1)*(ScenarioParameters!$B$5+(ScenarioParameters!$B$5*$B$1))*ScenarioParameters!$G3*(1/1000) -> -393.98815 | G9: =(-1)*(ScenarioParameters!$B$5+(ScenarioParameters!$B$5*$B$1))*ScenarioParameters!$G4*(1/1000) -> -1006.6116 | H9: =(-1)*(ScenarioParameters!$B$5+(ScenarioParameters!$B$5*$B$1))*ScenarioParameters!$G5*(1/1000) -> -781.1826 | I9: =(-1)*(ScenarioParameters!$B$5+(ScenarioParameters!$B$5*$B$1))*ScenarioParameters!$G6*(1/1000) -> -1505.5809 | J9: =(-1)*(ScenarioParameters!$B$5+(ScenarioParameters!$B$5*$B$1))*ScenarioParameters!$G7*(1/1000) -> -826.56702 | K9: =(-1)*(ScenarioParameters!$B$5+(ScenarioParameters!$B$5*$B$1))*ScenarioParameters!$G8*(1/1000) -> -1645.6692 | L9: =(-1)*(ScenarioParameters!$B$5+(ScenarioParameters!$B$5*$B$1))*ScenarioParameters!$G9*(1/1000) -> -1111.0054 | M9: =(-1)*(ScenarioParameters!$B$5+(ScenarioParameters!$B$5*$B$1))*ScenarioParameters!$G10*(1/1000) -> -1976.4469 | N9: =(-1)*(ScenarioParameters!$B$5+(ScenarioParameters!$B$5*$B$1))*ScenarioParameters!$G11*(1/1000) -> -1047.5392 | O9: =(-1)*(ScenarioParameters!$B$5+(ScenarioParameters!$B$5*$B$1))*ScenarioParameters!$G12*(1/1000) -> -2056.2757 | P9: =(-1)*(ScenarioParameters!$B$5+(ScenarioParameters!$B$5*$B$1))*ScenarioParameters!$G13*(1/1000) -> -1365.3756 | Q9: =(-1)*(ScenarioParameters!$B$5+(ScenarioParameters!$B$5*$B$1))*ScenarioParameters!$G14*(1/1000) -> -2402.2913 | R9: =(-1)*(ScenarioParameters!$B$5+(ScenarioParameters!$B$5*$B$1))*ScenarioParameters!$G15*(1/1000) -> -1283.1878 | S9: =(-1)*(ScenarioParameters!$B$5+(ScenarioParameters!$B$5*$B$1))*ScenarioParameters!$G16*(1/1000) -> -2494.2149 | T9: =(-1)*(ScenarioParameters!$B$5+(ScenarioParameters!$B$5*$B$1))*ScenarioParameters!$G16*(1/1000) -> -2494.2149 | U9: =(-1)*(ScenarioParameters!$B$5+(ScenarioParameters!$B$5*$B$1))*ScenarioParameters!$G18*(1/1000) -> -2864.6843
A10: Production volume | F10: =ScenarioParameters!$G3 -> 3106.9661 | G10: =ScenarioParameters!$G4 -> 7938.0762 | H10: =ScenarioParameters!$G5 -> 6160.3574 | I10: =ScenarioParameters!$G6 -> 11872.917 | J10: =ScenarioParameters!$G7 -> 6518.2561 | K10: =ScenarioParameters!$G8 -> 12977.645 | L10: =ScenarioParameters!$G9 -> 8761.3198 | M10: =ScenarioParameters!$G10 -> 15586.137 | N10: =ScenarioParameters!$G11 -> 8260.8289 | O10: =ScenarioParameters!$G12 -> 16215.662 | P10: =ScenarioParameters!$G13 -> 10767.267 | Q10: =ScenarioParameters!$G14 -> 18944.32 | R10: =ScenarioParameters!$G15 -> 10119.139 | S10: =ScenarioParameters!$G16 -> 19669.223 | T10: =ScenarioParameters!$G17 -> 12944.52 | U10: =ScenarioParameters!$G18 -> 22590.723
A11: Unit product cost | F11: =F9/F10 -> -0.126808 | G11: =G9/G10 -> -0.126808 | H11: =H9/H10 -> -0.126808 | I11: =I9/I10 -> -0.126808 | J11: =J9/J10 -> -0.126808 | K11: =K9/K10 -> -0.126808 | L11: =L9/L10 -> -0.126808 | M11: =M9/M10 -> -0.126808 | ... U11: =U9/U10 -> -0.126808
A12: Sales revenue | F12: =(ScenarioParameters!$B$4*F10)*(1/1000) -> 928.98285 | G12: =(ScenarioParameters!$B$4*G10)*(1/1000) -> 2373.4848 | H12: =(ScenarioParameters!$B$4*H10)*(1/1000) -> 1841.9469 | I12: =(ScenarioParameters!$B$4*I10)*(1/1000) -> 3550.0022 | J12: =(ScenarioParameters!$B$4*J10)*(1/1000) -> 1948.9586 | K12: =(ScenarioParameters!$B$4*K10)*(1/1000) -> 3880.3159 | L12: =(ScenarioParameters!$B$4*L10)*(1/1000) -> 2619.6346 | M12: =(ScenarioParameters!$B$4*M10)*(1/1000) -> 4660.255 | ... U12: =(ScenarioParameters!$B$4*U10)*(1/1000) -> 6754.626
A13: Forecasted Sales Volume | F13: =F$10 -> 3106.9661 | G13: =G$10 -> 7938.0762 | H13: =H$10 -> 6160.3574 | I13: =I$10 -> 11872.917 | J13: =J$10 -> 6518.2561 | K13: =K$10 -> 12977.645 | L13: =L$10 -> 8761.3198 | M13: =M$10 -> 15586.137 | ... U13: =U$10 -> 22590.723
A14: Unit price | F14: =F$12/F$13 -> 0.299 | G14: =G$12/G$13 -> 0.299 | H14: =H$12/H$13 -> 0.299 | I14: =I$12/I$13 -> 0.299 | J14: =J$12/J$13 -> 0.299 | K14: =K$12/K$13 -> 0.299 | L14: =L$12/L$13 -> 0.299 | M14: =M$12/M$13 -> 0.299 | ... U14: =U$12/U$13 -> 0.299
A16: Period Cash Flow | B16: =SUM(B6+B7+B8+B9+B12) -> -15.12 | C16: =SUM(C6+C7+C8+C9+C12) -> -15.12 | D16: =SUM(D6+D7+D8+D9+D12) -> -15.12 | E16: =SUM(E6+E7+E8+E9+E12) -> -18.144 | F16: =SUM(F6+F7+F8+F9+F12) -> 321.9707 | G16: =SUM(G6+G7+G8+G9+G12) -> 1156.8732 | H16: =SUM(H6+H7+H8+H9+H12) -> 850.76426 | I16: =SUM(I6+I7+I8+I9+I12) -> 1834.4213 | ... U16: =SUM(U6+U7+U8+U9+U12) -> 3679.9417
A17: Unit Price | B17: =B16 -> -15.12 | C17: =C16/(1+(ScenarioParameters!$B$8/100)/4)^B3 -> -14.859951 | D17: =D16/(1+(ScenarioParameters!$B$8/100)/4)^C3 -> -14.604374 | E17: =E16/(1+(ScenarioParameters!$B$8/100)/4)^D3 -> -17.223832 | F17: =F16/(1+(ScenarioParameters!$B$8/100)/4)^E3 -> 300.3853 | G17: =G16/(1+(ScenarioParameters!$B$8/100)/4)^F3 -> 1060.7516 | H17: =H16/(1+(ScenarioParameters!$B$8/100)/4)^G3 -> 766.65986 | I17: =I16/(1+(ScenarioParameters!$B$8/100)/4)^H3 -> 1624.6438 | J17: =J16/(1+(ScenarioParameters!$B$8/100)/4)^I3 -> 794.15617 | ... U17: =U16/(1+(ScenarioParameters!$B$8/100)/4)^T3 -> 2646.592
A19: Project NVP | B19: =SUM(B17:U17) -> 23066.729
A21: Forecasted Sales Volume from Winter's forecasting method*

Sheet -10 UnitCost
A1: Unit Cost Analysis: | B1: -0.1
B2: Year 0, Development | F2: Year 1, Projection | J2: Year 2, Projection | N2: Year 3, Projection | R2: Year 4, Projection
A3: Period | B3: 1 | C3: =B3+1 -> 2 | D3: =C3+1 -> 3 | E3: =D3+1 -> 4 | F3: =E3+1 -> 5 | G3: =F3+1 -> 6 | H3: =G3+1 -> 7 | I3: =H3+1 -> 8 | J3: =I3+1 -> 9 | ... U3: =T3+1 -> 20
A4: ($Value in thousands) | B4: Q1 | C4: Q2 | D4: Q3 | E4: Q4 | F4: Q1 | G4: Q2 | H4: Q3 | I4: Q4 | J4: Q1 | K4: Q2 | L4: Q3 | M4: Q4 | N4: Q1 | O4: Q2 | P4: Q3 | Q4: Q4 | R4: Q1 | S4: Q2 | T4: Q3 | U4: Q4
A6: Development Cost | B6: =(-1)*ScenarioParameters!$B$3/4*(1/1000) -> -15.12 | C6: =(-1)*ScenarioParameters!$B$3/4*(1/1000) -> -15.12 | D6: =(-1)*ScenarioParameters!$B$3/4*(1/1000) -> -15.12 | E6: =(-1)*ScenarioParameters!$B$3/4*(1/1000) -> -15.12
A7: Ramp-up cost | E7: =(-1)*ScenarioParameters!$B$6/2*(1/1000) -> -3.024 | F7: =(-1)*ScenarioParameters!$B$6/2*(1/1000) -> -3.024
A8: Marketing & support cost | F8: =(-1)*ScenarioParameters!$B$7/4*(1/1000) -> -210 | G8: =(-1)*ScenarioParameters!$B$7/4*(1/1000) -> -210 | H8: =(-1)*ScenarioParameters!$B$7/4*(1/1000) -> -210 | I8: =(-1)*ScenarioParameters!$B$7/4*(1/1000) -> -210 | J8: =(-1)*ScenarioParameters!$B$7/4*(1/1000) -> -210 | K8: =(-1)*ScenarioParameters!$B$7/4*(1/1000) -> -210 | L8: =(-1)*ScenarioParameters!$B$7/4*(1/1000) -> -210 | M8: =(-1)*ScenarioParameters!$B$7/4*(1/1000) -> -210 | ... U8: =(-1)*ScenarioParameters!$B$7/4*(1/1000) -> -210
A9: Production Cost | F9: =(-1)*(ScenarioParameters!$B$5+(ScenarioParameters!$B$5*$B$1))*ScenarioParameters!$G3*(1/1000) -> -322.35394 | G9: =(-1)*(ScenarioParameters!$B$5+(ScenarioParameters!$B$5*$B$1))*ScenarioParameters!$G4*(1/1000) -> -823.59128 | H9: =(-1)*(ScenarioParameters!$B$5+(ScenarioParameters!$B$5*$B$1))*ScenarioParameters!$G5*(1/1000) -> -639.1494 | I9: =(-1)*(ScenarioParameters!$B$5+(ScenarioParameters!$B$5*$B$1))*ScenarioParameters!$G6*(1/1000) -> -1231.8389 | J9: =(-1)*(ScenarioParameters!$B$5+(ScenarioParameters!$B$5*$B$1))*ScenarioParameters!$G7*(1/1000) -> -676.28211 | K9: =(-1)*(ScenarioParameters!$B$5+(ScenarioParameters!$B$5*$B$1))*ScenarioParameters!$G8*(1/1000) -> -1346.4566 | L9: =(-1)*(ScenarioParameters!$B$5+(ScenarioParameters!$B$5*$B$1))*ScenarioParameters!$G9*(1/1000) -> -909.00445 | M9: =(-1)*(ScenarioParameters!$B$5+(ScenarioParameters!$B$5*$B$1))*ScenarioParameters!$G10*(1/1000) -> -1617.0929 | N9: =(-1)*(ScenarioParameters!$B$5+(ScenarioParameters!$B$5*$B$1))*ScenarioParameters!$G11*(1/1000) -> -857.07752 | O9: =(-1)*(ScenarioParameters!$B$5+(ScenarioParameters!$B$5*$B$1))*ScenarioParameters!$G12*(1/1000) -> -1682.4074 | P9: =(-1)*(ScenarioParameters!$B$5+(ScenarioParameters!$B$5*$B$1))*ScenarioParameters!$G13*(1/1000) -> -1117.1255 | Q9: =(-1)*(ScenarioParameters!$B$5+(ScenarioParameters!$B$5*$B$1))*ScenarioParameters!$G14*(1/1000) -> -1965.5111 | R9: =(-1)*(ScenarioParameters!$B$5+(ScenarioParameters!$B$5*$B$1))*ScenarioParameters!$G15*(1/1000) -> -1049.8809 | S9: =(-1)*(ScenarioParameters!$B$5+(ScenarioParameters!$B$5*$B$1))*ScenarioParameters!$G16*(1/1000) -> -2040.7212 | T9: =(-1)*(ScenarioParameters!$B$5+(ScenarioParameters!$B$5*$B$1))*ScenarioParameters!$G16*(1/1000) -> -2040.7212 | U9: =(-1)*(ScenarioParameters!$B$5+(ScenarioParameters!$B$5*$B$1))*ScenarioParameters!$G18*(1/1000) -> -2343.8326
A10: Production volume | F10: =ScenarioParameters!$G3 -> 3106.9661 | G10: =ScenarioParameters!$G4 -> 7938.0762 | H10: =ScenarioParameters!$G5 -> 6160.3574 | I10: =ScenarioParameters!$G6 -> 11872.917 | J10: =ScenarioParameters!$G7 -> 6518.2561 | K10: =ScenarioParameters!$G8 -> 12977.645 | L10: =ScenarioParameters!$G9 -> 8761.3198 | M10: =ScenarioParameters!$G10 -> 15586.137 | N10: =ScenarioParameters!$G11 -> 8260.8289 | O10: =ScenarioParameters!$G12 -> 16215.662 | P10: =ScenarioParameters!$G13 -> 10767.267 | Q10: =ScenarioParameters!$G14 -> 18944.32 | R10: =ScenarioParameters!$G15 -> 10119.139 | S10: =ScenarioParameters!$G16 -> 19669.223 | T10: =ScenarioParameters!$G17 -> 12944.52 | U10: =ScenarioParameters!$G18 -> 22590.723
A11: Unit product cost | F11: =F9/F10 -> -0.103752 | G11: =G9/G10 -> -0.103752 | H11: =H9/H10 -> -0.103752 | I11: =I9/I10 -> -0.103752 | J11: =J9/J10 -> -0.103752 | K11: =K9/K10 -> -0.103752 | L11: =L9/L10 -> -0.103752 | M11: =M9/M10 -> -0.103752 | ... U11: =U9/U10 -> -0.103752
A12: Sales revenue | F12: =(ScenarioParameters!$B$4*F10)*(1/1000) -> 928.98285 | G12: =(ScenarioParameters!$B$4*G10)*(1/1000) -> 2373.4848 | H12: =(ScenarioParameters!$B$4*H10)*(1/1000) -> 1841.9469 | I12: =(ScenarioParameters!$B$4*I10)*(1/1000) -> 3550.0022 | J12: =(ScenarioParameters!$B$4*J10)*(1/1000) -> 1948.9586 | K12: =(ScenarioParameters!$B$4*K10)*(1/1000) -> 3880.3159 | L12: =(ScenarioParameters!$B$4*L10)*(1/1000) -> 2619.6346 | M12: =(ScenarioParameters!$B$4*M10)*(1/1000) -> 4660.255 | ... U12: =(ScenarioParameters!$B$4*U10)*(1/1000) -> 6754.626
A13: Forecasted Sales Volume | F13: =F$10 -> 3106.9661 | G13: =G$10 -> 7938.0762 | H13: =H$10 -> 6160.3574 | I13: =I$10 -> 11872.917 | J13: =J$10 -> 6518.2561 | K13: =K$10 -> 12977.645 | L13: =L$10 -> 8761.3198 | M13: =M$10 -> 15586.137 | ... U13: =U$10 -> 22590.723
A14: Unit price | F14: =F$12/F$13 -> 0.299 | G14: =G$12/G$13 -> 0.299 | H14: =H$12/H$13 -> 0.299 | I14: =I$12/I$13 -> 0.299 | J14: =J$12/J$13 -> 0.299 | K14: =K$12/K$13 -> 0.299 | L14: =L$12/L$13 -> 0.299 | M14: =M$12/M$13 -> 0.299 | ... U14: =U$12/U$13 -> 0.299
A16: Period Cash Flow | B16: =SUM(B6+B7+B8+B9+B12) -> -15.12 | C16: =SUM(C6+C7+C8+C9+C12) -> -15.12 | D16: =SUM(D6+D7+D8+D9+D12) -> -15.12 | E16: =SUM(E6+E7+E8+E9+E12) -> -18.144 | F16: =SUM(F6+F7+F8+F9+F12) -> 393.60491 | G16: =SUM(G6+G7+G8+G9+G12) -> 1339.8935 | H16: =SUM(H6+H7+H8+H9+H12) -> 992.79746 | I16: =SUM(I6+I7+I8+I9+I12) -> 2108.1633 | ... U16: =SUM(U6+U7+U8+U9+U12) -> 4200.7934
A17: Unit Price | B17: =B16 -> -15.12 | C17: =C16/(1+(ScenarioParameters!$B$8/100)/4)^B3 -> -14.859951 | D17: =D16/(1+(ScenarioParameters!$B$8/100)/4)^C3 -> -14.604374 | E17: =E16/(1+(ScenarioParameters!$B$8/100)/4)^D3 -> -17.223832 | F17: =F16/(1+(ScenarioParameters!$B$8/100)/4)^E3 -> 367.21705 | G17: =G16/(1+(ScenarioParameters!$B$8/100)/4)^F3 -> 1228.5652 | H17: =H16/(1+(ScenarioParameters!$B$8/100)/4)^G3 -> 894.65202 | I17: =I16/(1+(ScenarioParameters!$B$8/100)/4)^H3 -> 1867.0817 | J17: =J16/(1+(ScenarioParameters!$B$8/100)/4)^I3 -> 924.96589 | ... U17: =U16/(1+(ScenarioParameters!$B$8/100)/4)^T3 -> 3021.1854
A19: Project NVP | B19: =SUM(B17:U17) -> 26730.665
A21: Forecasted Sales Volume from Winter's forecasting method*

Sheet +20 UnitCost
A1: Unit Cost Analysis: | B1: 0.2
B2: Year 0, Development | F2: Year 1, Projection | J2: Year 2, Projection | N2: Year 3, Projection | R2: Year 4, Projection
A3: Period | B3: 1 | C3: =B3+1 -> 2 | D3: =C3+1 -> 3 | E3: =D3+1 -> 4 | F3: =E3+1 -> 5 | G3: =F3+1 -> 6 | H3: =G3+1 -> 7 | I3: =H3+1 -> 8 | J3: =I3+1 -> 9 | ... U3: =T3+1 -> 20
A4: ($Value in thousands) | B4: Q1 | C4: Q2 | D4: Q3 | E4: Q4 | F4: Q1 | G4: Q2 | H4: Q3 | I4: Q4 | J4: Q1 | K4: Q2 | L4: Q3 | M4: Q4 | N4: Q1 | O4: Q2 | P4: Q3 | Q4: Q4 | R4: Q1 | S4: Q2 | T4: Q3 | U4: Q4
A6: Development Cost | B6: =(-1)*ScenarioParameters!$B$3/4*(1/1000) -> -15.12 | C6: =(-1)*ScenarioParameters!$B$3/4*(1/1000) -> -15.12 | D6: =(-1)*ScenarioParameters!$B$3/4*(1/1000) -> -15.12 | E6: =(-1)*ScenarioParameters!$B$3/4*(1/1000) -> -15.12
A7: Ramp-up cost | E7: =(-1)*ScenarioParameters!$B$6/2*(1/1000) -> -3.024 | F7: =(-1)*ScenarioParameters!$B$6/2*(1/1000) -> -3.024
A8: Marketing & support cost | F8: =(-1)*ScenarioParameters!$B$7/4*(1/1000) -> -210 | G8: =(-1)*ScenarioParameters!$B$7/4*(1/1000) -> -210 | H8: =(-1)*ScenarioParameters!$B$7/4*(1/1000) -> -210 | I8: =(-1)*ScenarioParameters!$B$7/4*(1/1000) -> -210 | J8: =(-1)*ScenarioParameters!$B$7/4*(1/1000) -> -210 | K8: =(-1)*ScenarioParameters!$B$7/4*(1/1000) -> -210 | L8: =(-1)*ScenarioParameters!$B$7/4*(1/1000) -> -210 | M8: =(-1)*ScenarioParameters!$B$7/4*(1/1000) -> -210 | ... U8: =(-1)*ScenarioParameters!$B$7/4*(1/1000) -> -210
A9: Production Cost | F9: =(-1)*(ScenarioParameters!$B$5+(ScenarioParameters!$B$5*$B$1))*ScenarioParameters!$G3*(1/1000) -> -429.80526 | G9: =(-1)*(ScenarioParameters!$B$5+(ScenarioParameters!$B$5*$B$1))*ScenarioParameters!$G4*(1/1000) -> -1098.1217 | H9: =(-1)*(ScenarioParameters!$B$5+(ScenarioParameters!$B$5*$B$1))*ScenarioParameters!$G5*(1/1000) -> -852.1992 | I9: =(-1)*(ScenarioParameters!$B$5+(ScenarioParameters!$B$5*$B$1))*ScenarioParameters!$G6*(1/1000) -> -1642.4519 | J9: =(-1)*(ScenarioParameters!$B$5+(ScenarioParameters!$B$5*$B$1))*ScenarioParameters!$G7*(1/1000) -> -901.70947 | K9: =(-1)*(ScenarioParameters!$B$5+(ScenarioParameters!$B$5*$B$1))*ScenarioParameters!$G8*(1/1000) -> -1795.2755 | L9: =(-1)*(ScenarioParameters!$B$5+(ScenarioParameters!$B$5*$B$1))*ScenarioParameters!$G9*(1/1000) -> -1212.0059 | M9: =(-1)*(ScenarioParameters!$B$5+(ScenarioParameters!$B$5*$B$1))*ScenarioParameters!$G10*(1/1000) -> -2156.1239 | N9: =(-1)*(ScenarioParameters!$B$5+(ScenarioParameters!$B$5*$B$1))*ScenarioParameters!$G11*(1/1000) -> -1142.77 | O9: =(-1)*(ScenarioParameters!$B$5+(ScenarioParameters!$B$5*$B$1))*ScenarioParameters!$G12*(1/1000) -> -2243.2098 | P9: =(-1)*(ScenarioParameters!$B$5+(ScenarioParameters!$B$5*$B$1))*ScenarioParameters!$G13*(1/1000) -> -1489.5007 | Q9: =(-1)*(ScenarioParameters!$B$5+(ScenarioParameters!$B$5*$B$1))*ScenarioParameters!$G14*(1/1000) -> -2620.6814 | R9: =(-1)*(ScenarioParameters!$B$5+(ScenarioParameters!$B$5*$B$1))*ScenarioParameters!$G15*(1/1000) -> -1399.8412 | S9: =(-1)*(ScenarioParameters!$B$5+(ScenarioParameters!$B$5*$B$1))*ScenarioParameters!$G16*(1/1000) -> -2720.9617 | T9: =(-1)*(ScenarioParameters!$B$5+(ScenarioParameters!$B$5*$B$1))*ScenarioParameters!$G16*(1/1000) -> -2720.9617 | U9: =(-1)*(ScenarioParameters!$B$5+(ScenarioParameters!$B$5*$B$1))*ScenarioParameters!$G18*(1/1000) -> -3125.1102
A10: Production volume | F10: =ScenarioParameters!$G3 -> 3106.9661 | G10: =ScenarioParameters!$G4 -> 7938.0762 | H10: =ScenarioParameters!$G5 -> 6160.3574 | I10: =ScenarioParameters!$G6 -> 11872.917 | J10: =ScenarioParameters!$G7 -> 6518.2561 | K10: =ScenarioParameters!$G8 -> 12977.645 | L10: =ScenarioParameters!$G9 -> 8761.3198 | M10: =ScenarioParameters!$G10 -> 15586.137 | N10: =ScenarioParameters!$G11 -> 8260.8289 | O10: =ScenarioParameters!$G12 -> 16215.662 | P10: =ScenarioParameters!$G13 -> 10767.267 | Q10: =ScenarioParameters!$G14 -> 18944.32 | R10: =ScenarioParameters!$G15 -> 10119.139 | S10: =ScenarioParameters!$G16 -> 19669.223 | T10: =ScenarioParameters!$G17 -> 12944.52 | U10: =ScenarioParameters!$G18 -> 22590.723
A11: Unit product cost | F11: =F9/F10 -> -0.138336 | G11: =G9/G10 -> -0.138336 | H11: =H9/H10 -> -0.138336 | I11: =I9/I10 -> -0.138336 | J11: =J9/J10 -> -0.138336 | K11: =K9/K10 -> -0.138336 | L11: =L9/L10 -> -0.138336 | M11: =M9/M10 -> -0.138336 | ... U11: =U9/U10 -> -0.138336
A12: Sales revenue | F12: =(ScenarioParameters!$B$4*F10)*(1/1000) -> 928.98285 | G12: =(ScenarioParameters!$B$4*G10)*(1/1000) -> 2373.4848 | H12: =(ScenarioParameters!$B$4*H10)*(1/1000) -> 1841.9469 | I12: =(ScenarioParameters!$B$4*I10)*(1/1000) -> 3550.0022 | J12: =(ScenarioParameters!$B$4*J10)*(1/1000) -> 1948.9586 | K12: =(ScenarioParameters!$B$4*K10)*(1/1000) -> 3880.3159 | L12: =(ScenarioParameters!$B$4*L10)*(1/1000) -> 2619.6346 | M12: =(ScenarioParameters!$B$4*M10)*(1/1000) -> 4660.255 | ... U12: =(ScenarioParameters!$B$4*U10)*(1/1000) -> 6754.626
A13: Forecasted Sales Volume | F13: =F$10 -> 3106.9661 | G13: =G$10 -> 7938.0762 | H13: =H$10 -> 6160.3574 | I13: =I$10 -> 11872.917 | J13: =J$10 -> 6518.2561 | K13: =K$10 -> 12977.645 | L13: =L$10 -> 8761.3198 | M13: =M$10 -> 15586.137 | ... U13: =U$10 -> 22590.723
A14: Unit price | F14: =F$12/F$13 -> 0.299 | G14: =G$12/G$13 -> 0.299 | H14: =H$12/H$13 -> 0.299 | I14: =I$12/I$13 -> 0.299 | J14: =J$12/J$13 -> 0.299 | K14: =K$12/K$13 -> 0.299 | L14: =L$12/L$13 -> 0.299 | M14: =M$12/M$13 -> 0.299 | ... U14: =U$12/U$13 -> 0.299
A16: Period Cash Flow | B16: =SUM(B6+B7+B8+B9+B12) -> -15.12 | C16: =SUM(C6+C7+C8+C9+C12) -> -15.12 | D16: =SUM(D6+D7+D8+D9+D12) -> -15.12 | E16: =SUM(E6+E7+E8+E9+E12) -> -18.144 | F16: =SUM(F6+F7+F8+F9+F12) -> 286.1536 | G16: =SUM(G6+G7+G8+G9+G12) -> 1065.3631 | H16: =SUM(H6+H7+H8+H9+H12) -> 779.74766 | I16: =SUM(I6+I7+I8+I9+I12) -> 1697.5504 | ... U16: =SUM(U6+U7+U8+U9+U12) -> 3419.5158
A17: Unit Price | B17: =B16 -> -15.12 | C17: =C16/(1+(ScenarioParameters!$B$8/100)/4)^B3 -> -14.859951 | D17: =D16/(1+(ScenarioParameters!$B$8/100)/4)^C3 -> -14.604374 | E17: =E16/(1+(ScenarioParameters!$B$8/100)/4)^D3 -> -17.223832 | F17: =F16/(1+(ScenarioParameters!$B$8/100)/4)^E3 -> 266.96943 | G17: =G16/(1+(ScenarioParameters!$B$8/100)/4)^F3 -> 976.84476 | H17: =H16/(1+(ScenarioParameters!$B$8/100)/4)^G3 -> 702.66378 | I17: =I16/(1+(ScenarioParameters!$B$8/100)/4)^H3 -> 1503.4249 | J17: =J16/(1+(ScenarioParameters!$B$8/100)/4)^I3 -> 728.7513 | ... U17: =U16/(1+(ScenarioParameters!$B$8/100)/4)^T3 -> 2459.2953
A19: Project NVP | B19: =SUM(B17:U17) -> 21234.76
A21: Forecasted Sales Volume from Winter's forecasting method*

Sheet -20 UnitCost
A1: Unit Cost Analysis: | B1: -0.2
B2: Year 0, Development | F2: Year 1, Projection | J2: Year 2, Projection | N2: Year 3, Projection | R2: Year 4, Projection
A3: Period | B3: 1 | C3: =B3+1 -> 2 | D3: =C3+1 -> 3 | E3: =D3+1 -> 4 | F3: =E3+1 -> 5 | G3: =F3+1 -> 6 | H3: =G3+1 -> 7 | I3: =H3+1 -> 8 | J3: =I3+1 -> 9 | ... U3: =T3+1 -> 20
A4: ($Value in thousands) | B4: Q1 | C4: Q2 | D4: Q3 | E4: Q4 | F4: Q1 | G4: Q2 | H4: Q3 | I4: Q4 | J4: Q1 | K4: Q2 | L4: Q3 | M4: Q4 | N4: Q1 | O4: Q2 | P4: Q3 | Q4: Q4 | R4: Q1 | S4: Q2 | T4: Q3 | U4: Q4
A6: Development Cost | B6: =(-1)*ScenarioParameters!$B$3/4*(1/1000) -> -15.12 | C6: =(-1)*ScenarioParameters!$B$3/4*(1/1000) -> -15.12 | D6: =(-1)*ScenarioParameters!$B$3/4*(1/1000) -> -15.12 | E6: =(-1)*ScenarioParameters!$B$3/4*(1/1000) -> -15.12
A7: Ramp-up cost | E7: =(-1)*ScenarioParameters!$B$6/2*(1/1000) -> -3.024 | F7: =(-1)*ScenarioParameters!$B$6/2*(1/1000) -> -3.024
A8: Marketing & support cost | F8: =(-1)*ScenarioParameters!$B$7/4*(1/1000) -> -210 | G8: =(-1)*ScenarioParameters!$B$7/4*(1/1000) -> -210 | H8: =(-1)*ScenarioParameters!$B$7/4*(1/1000) -> -210 | I8: =(-1)*ScenarioParameters!$B$7/4*(1/1000) -> -210 | J8: =(-1)*ScenarioParameters!$B$7/4*(1/1000) -> -210 | K8: =(-1)*ScenarioParameters!$B$7/4*(1/1000) -> -210 | L8: =(-1)*ScenarioParameters!$B$7/4*(1/1000) -> -210 | M8: =(-1)*ScenarioParameters!$B$7/4*(1/1000) -> -210 | ... U8: =(-1)*ScenarioParameters!$B$7/4*(1/1000) -> -210
A9: Production Cost | F9: =(-1)*(ScenarioParameters!$B$5+(ScenarioParameters!$B$5*$B$1))*ScenarioParameters!$G3*(1/1000) -> -286.53684 | G9: =(-1)*(ScenarioParameters!$B$5+(ScenarioParameters!$B$5*$B$1))*ScenarioParameters!$G4*(1/1000) -> -732.08114 | H9: =(-1)*(ScenarioParameters!$B$5+(ScenarioParameters!$B$5*$B$1))*ScenarioParameters!$G5*(1/1000) -> -568.1328 | I9: =(-1)*(ScenarioParameters!$B$5+(ScenarioParameters!$B$5*$B$1))*ScenarioParameters!$G6*(1/1000) -> -1094.9679 | J9: =(-1)*(ScenarioParameters!$B$5+(ScenarioParameters!$B$5*$B$1))*ScenarioParameters!$G7*(1/1000) -> -601.13965 | K9: =(-1)*(ScenarioParameters!$B$5+(ScenarioParameters!$B$5*$B$1))*ScenarioParameters!$G8*(1/1000) -> -1196.8504 | L9: =(-1)*(ScenarioParameters!$B$5+(ScenarioParameters!$B$5*$B$1))*ScenarioParameters!$G9*(1/1000) -> -808.00395 | M9: =(-1)*(ScenarioParameters!$B$5+(ScenarioParameters!$B$5*$B$1))*ScenarioParameters!$G10*(1/1000) -> -1437.4159 | N9: =(-1)*(ScenarioParameters!$B$5+(ScenarioParameters!$B$5*$B$1))*ScenarioParameters!$G11*(1/1000) -> -761.84669 | O9: =(-1)*(ScenarioParameters!$B$5+(ScenarioParameters!$B$5*$B$1))*ScenarioParameters!$G12*(1/1000) -> -1495.4732 | P9: =(-1)*(ScenarioParameters!$B$5+(ScenarioParameters!$B$5*$B$1))*ScenarioParameters!$G13*(1/1000) -> -993.00045 | Q9: =(-1)*(ScenarioParameters!$B$5+(ScenarioParameters!$B$5*$B$1))*ScenarioParameters!$G14*(1/1000) -> -1747.121 | R9: =(-1)*(ScenarioParameters!$B$5+(ScenarioParameters!$B$5*$B$1))*ScenarioParameters!$G15*(1/1000) -> -933.22747 | S9: =(-1)*(ScenarioParameters!$B$5+(ScenarioParameters!$B$5*$B$1))*ScenarioParameters!$G16*(1/1000) -> -1813.9744 | T9: =(-1)*(ScenarioParameters!$B$5+(ScenarioParameters!$B$5*$B$1))*ScenarioParameters!$G16*(1/1000) -> -1813.9744 | U9: =(-1)*(ScenarioParameters!$B$5+(ScenarioParameters!$B$5*$B$1))*ScenarioParameters!$G18*(1/1000) -> -2083.4068
A10: Production volume | F10: =ScenarioParameters!$G3 -> 3106.9661 | G10: =ScenarioParameters!$G4 -> 7938.0762 | H10: =ScenarioParameters!$G5 -> 6160.3574 | I10: =ScenarioParameters!$G6 -> 11872.917 | J10: =ScenarioParameters!$G7 -> 6518.2561 | K10: =ScenarioParameters!$G8 -> 12977.645 | L10: =ScenarioParameters!$G9 -> 8761.3198 | M10: =ScenarioParameters!$G10 -> 15586.137 | N10: =ScenarioParameters!$G11 -> 8260.8289 | O10: =ScenarioParameters!$G12 -> 16215.662 | P10: =ScenarioParameters!$G13 -> 10767.267 | Q10: =ScenarioParameters!$G14 -> 18944.32 | R10: =ScenarioParameters!$G15 -> 10119.139 | S10: =ScenarioParameters!$G16 -> 19669.223 | T10: =ScenarioParameters!$G17 -> 12944.52 | U10: =ScenarioParameters!$G18 -> 22590.723
A11: Unit product cost | F11: =F9/F10 -> -0.092224 | G11: =G9/G10 -> -0.092224 | H11: =H9/H10 -> -0.092224 | I11: =I9/I10 -> -0.092224 | J11: =J9/J10 -> -0.092224 | K11: =K9/K10 -> -0.092224 | L11: =L9/L10 -> -0.092224 | M11: =M9/M10 -> -0.092224 | ... U11: =U9/U10 -> -0.092224
A12: Sales revenue | F12: =(ScenarioParameters!$B$4*F10)*(1/1000) -> 928.98285 | G12: =(ScenarioParameters!$B$4*G10)*(1/1000) -> 2373.4848 | H12: =(ScenarioParameters!$B$4*H10)*(1/1000) -> 1841.9469 | I12: =(ScenarioParameters!$B$4*I10)*(1/1000) -> 3550.0022 | J12: =(ScenarioParameters!$B$4*J10)*(1/1000) -> 1948.9586 | K12: =(ScenarioParameters!$B$4*K10)*(1/1000) -> 3880.3159 | L12: =(ScenarioParameters!$B$4*L10)*(1/1000) -> 2619.6346 | M12: =(ScenarioParameters!$B$4*M10)*(1/1000) -> 4660.255 | ... U12: =(ScenarioParameters!$B$4*U10)*(1/1000) -> 6754.626
A13: Forecasted Sales Volume | F13: =F$10 -> 3106.9661 | G13: =G$10 -> 7938.0762 | H13: =H$10 -> 6160.3574 | I13: =I$10 -> 11872.917 | J13: =J$10 -> 6518.2561 | K13: =K$10 -> 12977.645 | L13: =L$10 -> 8761.3198 | M13: =M$10 -> 15586.137 | ... U13: =U$10 -> 22590.723
A14: Unit price | F14: =F$12/F$13 -> 0.299 | G14: =G$12/G$13 -> 0.299 | H14: =H$12/H$13 -> 0.299 | I14: =I$12/I$13 -> 0.299 | J14: =J$12/J$13 -> 0.299 | K14: =K$12/K$13 -> 0.299 | L14: =L$12/L$13 -> 0.299 | M14: =M$12/M$13 -> 0.299 | ... U14: =U$12/U$13 -> 0.299
A16: Period Cash Flow | B16: =SUM(B6+B7+B8+B9+B12) -> -15.12 | C16: =SUM(C6+C7+C8+C9+C12) -> -15.12 | D16: =SUM(D6+D7+D8+D9+D12) -> -15.12 | E16: =SUM(E6+E7+E8+E9+E12) -> -18.144 | F16: =SUM(F6+F7+F8+F9+F12) -> 429.42202 | G16: =SUM(G6+G7+G8+G9+G12) -> 1431.4036 | H16: =SUM(H6+H7+H8+H9+H12) -> 1063.8141 | I16: =SUM(I6+I7+I8+I9+I12) -> 2245.0343 | ... U16: =SUM(U6+U7+U8+U9+U12) -> 4461.2192
A17: Unit Price | B17: =B16 -> -15.12 | C17: =C16/(1+(ScenarioParameters!$B$8/100)/4)^B3 -> -14.859951 | D17: =D16/(1+(ScenarioParameters!$B$8/100)/4)^C3 -> -14.604374 | E17: =E16/(1+(ScenarioParameters!$B$8/100)/4)^D3 -> -17.223832 | F17: =F16/(1+(ScenarioParameters!$B$8/100)/4)^E3 -> 400.63292 | G17: =G16/(1+(ScenarioParameters!$B$8/100)/4)^F3 -> 1312.472 | H17: =H16/(1+(ScenarioParameters!$B$8/100)/4)^G3 -> 958.6481 | I17: =I16/(1+(ScenarioParameters!$B$8/100)/4)^H3 -> 1988.3007 | J17: =J16/(1+(ScenarioParameters!$B$8/100)/4)^I3 -> 990.37076 | ... U17: =U16/(1+(ScenarioParameters!$B$8/100)/4)^T3 -> 3208.4821
A19: Project NVP | B19: =SUM(B17:U17) -> 28562.633
A21: Forecasted Sales Volume from Winter's forecasting method*

Sheet +30 UnitCost
A1: Unit Cost Analysis: | B1: 0.3
B2: Year 0, Development | F2: Year 1, Projection | J2: Year 2, Projection | N2: Year 3, Projection | R2: Year 4, Projection
A3: Period | B3: 1 | C3: =B3+1 -> 2 | D3: =C3+1 -> 3 | E3: =D3+1 -> 4 | F3: =E3+1 -> 5 | G3: =F3+1 -> 6 | H3: =G3+1 -> 7 | I3: =H3+1 -> 8 | J3: =I3+1 -> 9 | ... U3: =T3+1 -> 20
A4: ($Value in thousands) | B4: Q1 | C4: Q2 | D4: Q3 | E4: Q4 | F4: Q1 | G4: Q2 | H4: Q3 | I4: Q4 | J4: Q1 | K4: Q2 | L4: Q3 | M4: Q4 | N4: Q1 | O4: Q2 | P4: Q3 | Q4: Q4 | R4: Q1 | S4: Q2 | T4: Q3 | U4: Q4
A6: Development Cost | B6: =(-1)*ScenarioParameters!$B$3/4*(1/1000) -> -15.12 | C6: =(-1)*ScenarioParameters!$B$3/4*(1/1000) -> -15.12 | D6: =(-1)*ScenarioParameters!$B$3/4*(1/1000) -> -15.12 | E6: =(-1)*ScenarioParameters!$B$3/4*(1/1000) -> -15.12
A7: Ramp-up cost | E7: =(-1)*ScenarioParameters!$B$6/2*(1/1000) -> -3.024 | F7: =(-1)*ScenarioParameters!$B$6/2*(1/1000) -> -3.024
A8: Marketing & support cost | F8: =(-1)*ScenarioParameters!$B$7/4*(1/1000) -> -210 | G8: =(-1)*ScenarioParameters!$B$7/4*(1/1000) -> -210 | H8: =(-1)*ScenarioParameters!$B$7/4*(1/1000) -> -210 | I8: =(-1)*ScenarioParameters!$B$7/4*(1/1000) -> -210 | J8: =(-1)*ScenarioParameters!$B$7/4*(1/1000) -> -210 | K8: =(-1)*ScenarioParameters!$B$7/4*(1/1000) -> -210 | L8: =(-1)*ScenarioParameters!$B$7/4*(1/1000) -> -210 | M8: =(-1)*ScenarioParameters!$B$7/4*(1/1000) -> -210 | ... U8: =(-1)*ScenarioParameters!$B$7/4*(1/1000) -> -210
A9: Production Cost | F9: =(-1)*(ScenarioParameters!$B$5+(ScenarioParameters!$B$5*$B$1))*ScenarioParameters!$G3*(1/1000) -> -465.62236 | G9: =(-1)*(ScenarioParameters!$B$5+(ScenarioParameters!$B$5*$B$1))*ScenarioParameters!$G4*(1/1000) -> -1189.6319 | H9: =(-1)*(ScenarioParameters!$B$5+(ScenarioParameters!$B$5*$B$1))*ScenarioParameters!$G5*(1/1000) -> -923.2158 | I9: =(-1)*(ScenarioParameters!$B$5+(ScenarioParameters!$B$5*$B$1))*ScenarioParameters!$G6*(1/1000) -> -1779.3228 | J9: =(-1)*(ScenarioParameters!$B$5+(ScenarioParameters!$B$5*$B$1))*ScenarioParameters!$G7*(1/1000) -> -976.85193 | K9: =(-1)*(ScenarioParameters!$B$5+(ScenarioParameters!$B$5*$B$1))*ScenarioParameters!$G8*(1/1000) -> -1944.8818 | L9: =(-1)*(ScenarioParameters!$B$5+(ScenarioParameters!$B$5*$B$1))*ScenarioParameters!$G9*(1/1000) -> -1313.0064 | M9: =(-1)*(ScenarioParameters!$B$5+(ScenarioParameters!$B$5*$B$1))*ScenarioParameters!$G10*(1/1000) -> -2335.8009 | N9: =(-1)*(ScenarioParameters!$B$5+(ScenarioParameters!$B$5*$B$1))*ScenarioParameters!$G11*(1/1000) -> -1238.0009 | O9: =(-1)*(ScenarioParameters!$B$5+(ScenarioParameters!$B$5*$B$1))*ScenarioParameters!$G12*(1/1000) -> -2430.144 | P9: =(-1)*(ScenarioParameters!$B$5+(ScenarioParameters!$B$5*$B$1))*ScenarioParameters!$G13*(1/1000) -> -1613.6257 | Q9: =(-1)*(ScenarioParameters!$B$5+(ScenarioParameters!$B$5*$B$1))*ScenarioParameters!$G14*(1/1000) -> -2839.0716 | R9: =(-1)*(ScenarioParameters!$B$5+(ScenarioParameters!$B$5*$B$1))*ScenarioParameters!$G15*(1/1000) -> -1516.4946 | S9: =(-1)*(ScenarioParameters!$B$5+(ScenarioParameters!$B$5*$B$1))*ScenarioParameters!$G16*(1/1000) -> -2947.7085 | T9: =(-1)*(ScenarioParameters!$B$5+(ScenarioParameters!$B$5*$B$1))*ScenarioParameters!$G16*(1/1000) -> -2947.7085 | U9: =(-1)*(ScenarioParameters!$B$5+(ScenarioParameters!$B$5*$B$1))*ScenarioParameters!$G18*(1/1000) -> -3385.536
A10: Production volume | F10: =ScenarioParameters!$G3 -> 3106.9661 | G10: =ScenarioParameters!$G4 -> 7938.0762 | H10: =ScenarioParameters!$G5 -> 6160.3574 | I10: =ScenarioParameters!$G6 -> 11872.917 | J10: =ScenarioParameters!$G7 -> 6518.2561 | K10: =ScenarioParameters!$G8 -> 12977.645 | L10: =ScenarioParameters!$G9 -> 8761.3198 | M10: =ScenarioParameters!$G10 -> 15586.137 | N10: =ScenarioParameters!$G11 -> 8260.8289 | O10: =ScenarioParameters!$G12 -> 16215.662 | P10: =ScenarioParameters!$G13 -> 10767.267 | Q10: =ScenarioParameters!$G14 -> 18944.32 | R10: =ScenarioParameters!$G15 -> 10119.139 | S10: =ScenarioParameters!$G16 -> 19669.223 | T10: =ScenarioParameters!$G17 -> 12944.52 | U10: =ScenarioParameters!$G18 -> 22590.723
A11: Unit product cost | F11: =F9/F10 -> -0.149864 | G11: =G9/G10 -> -0.149864 | H11: =H9/H10 -> -0.149864 | I11: =I9/I10 -> -0.149864 | J11: =J9/J10 -> -0.149864 | K11: =K9/K10 -> -0.149864 | L11: =L9/L10 -> -0.149864 | M11: =M9/M10 -> -0.149864 | ... U11: =U9/U10 -> -0.149864
A12: Sales revenue | F12: =(ScenarioParameters!$B$4*F10)*(1/1000) -> 928.98285 | G12: =(ScenarioParameters!$B$4*G10)*(1/1000) -> 2373.4848 | H12: =(ScenarioParameters!$B$4*H10)*(1/1000) -> 1841.9469 | I12: =(ScenarioParameters!$B$4*I10)*(1/1000) -> 3550.0022 | J12: =(ScenarioParameters!$B$4*J10)*(1/1000) -> 1948.9586 | K12: =(ScenarioParameters!$B$4*K10)*(1/1000) -> 3880.3159 | L12: =(ScenarioParameters!$B$4*L10)*(1/1000) -> 2619.6346 | M12: =(ScenarioParameters!$B$4*M10)*(1/1000) -> 4660.255 | ... U12: =(ScenarioParameters!$B$4*U10)*(1/1000) -> 6754.626
A13: Forecasted Sales Volume | F13: =F$10 -> 3106.9661 | G13: =G$10 -> 7938.0762 | H13: =H$10 -> 6160.3574 | I13: =I$10 -> 11872.917 | J13: =J$10 -> 6518.2561 | K13: =K$10 -> 12977.645 | L13: =L$10 -> 8761.3198 | M13: =M$10 -> 15586.137 | ... U13: =U$10 -> 22590.723
A14: Unit price | F14: =F$12/F$13 -> 0.299 | G14: =G$12/G$13 -> 0.299 | H14: =H$12/H$13 -> 0.299 | I14: =I$12/I$13 -> 0.299 | J14: =J$12/J$13 -> 0.299 | K14: =K$12/K$13 -> 0.299 | L14: =L$12/L$13 -> 0.299 | M14: =M$12/M$13 -> 0.299 | ... U14: =U$12/U$13 -> 0.299
A16: Period Cash Flow | B16: =SUM(B6+B7+B8+B9+B12) -> -15.12 | C16: =SUM(C6+C7+C8+C9+C12) -> -15.12 | D16: =SUM(D6+D7+D8+D9+D12) -> -15.12 | E16: =SUM(E6+E7+E8+E9+E12) -> -18.144 | F16: =SUM(F6+F7+F8+F9+F12) -> 250.33649 | G16: =SUM(G6+G7+G8+G9+G12) -> 973.85294 | H16: =SUM(H6+H7+H8+H9+H12) -> 708.73106 | I16: =SUM(I6+I7+I8+I9+I12) -> 1560.6794 | ... U16: =SUM(U6+U7+U8+U9+U12) -> 3159.09
A17: Unit Price | B17: =B16 -> -15.12 | C17: =C16/(1+(ScenarioParameters!$B$8/100)/4)^B3 -> -14.859951 | D17: =D16/(1+(ScenarioParameters!$B$8/100)/4)^C3 -> -14.604374 | E17: =E16/(1+(ScenarioParameters!$B$8/100)/4)^D3 -> -17.223832 | F17: =F16/(1+(ScenarioParameters!$B$8/100)/4)^E3 -> 233.55356 | G17: =G16/(1+(ScenarioParameters!$B$8/100)/4)^F3 -> 892.93797 | H17: =H16/(1+(ScenarioParameters!$B$8/100)/4)^G3 -> 638.66771 | I17: =I16/(1+(ScenarioParameters!$B$8/100)/4)^H3 -> 1382.206 | J17: =J16/(1+(ScenarioParameters!$B$8/100)/4)^I3 -> 663.34644 | ... U17: =U16/(1+(ScenarioParameters!$B$8/100)/4)^T3 -> 2271.9986
A19: Project NVP | B19: =SUM(B17:U17) -> 19402.792
A21: Forecasted Sales Volume from Winter's forecasting method*

Sheet -30 UnitCost
A1: Unit Cost Analysis: | B1: -0.3
B2: Year 0, Development | F2: Year 1, Projection | J2: Year 2, Projection | N2: Year 3, Projection | R2: Year 4, Projection
A3: Period | B3: 1 | C3: =B3+1 -> 2 | D3: =C3+1 -> 3 | E3: =D3+1 -> 4 | F3: =E3+1 -> 5 | G3: =F3+1 -> 6 | H3: =G3+1 -> 7 | I3: =H3+1 -> 8 | J3: =I3+1 -> 9 | ... U3: =T3+1 -> 20
A4: ($Value in thousands) | B4: Q1 | C4: Q2 | D4: Q3 | E4: Q4 | F4: Q1 | G4: Q2 | H4: Q3 | I4: Q4 | J4: Q1 | K4: Q2 | L4: Q3 | M4: Q4 | N4: Q1 | O4: Q2 | P4: Q3 | Q4: Q4 | R4: Q1 | S4: Q2 | T4: Q3 | U4: Q4
A6: Development Cost | B6: =(-1)*ScenarioParameters!$B$3/4*(1/1000) -> -15.12 | C6: =(-1)*ScenarioParameters!$B$3/4*(1/1000) -> -15.12 | D6: =(-1)*ScenarioParameters!$B$3/4*(1/1000) -> -15.12 | E6: =(-1)*ScenarioParameters!$B$3/4*(1/1000) -> -15.12
A7: Ramp-up cost | E7: =(-1)*ScenarioParameters!$B$6/2*(1/1000) -> -3.024 | F7: =(-1)*ScenarioParameters!$B$6/2*(1/1000) -> -3.024
A8: Marketing & support cost | F8: =(-1)*ScenarioParameters!$B$7/4*(1/1000) -> -210 | G8: =(-1)*ScenarioParameters!$B$7/4*(1/1000) -> -210 | H8: =(-1)*ScenarioParameters!$B$7/4*(1/1000) -> -210 | I8: =(-1)*ScenarioParameters!$B$7/4*(1/1000) -> -210 | J8: =(-1)*ScenarioParameters!$B$7/4*(1/1000) -> -210 | K8: =(-1)*ScenarioParameters!$B$7/4*(1/1000) -> -210 | L8: =(-1)*ScenarioParameters!$B$7/4*(1/1000) -> -210 | M8: =(-1)*ScenarioParameters!$B$7/4*(1/1000) -> -210 | ... U8: =(-1)*ScenarioParameters!$B$7/4*(1/1000) -> -210
A9: Production Cost | F9: =(-1)*(ScenarioParameters!$B$5+(ScenarioParameters!$B$5*$B$1))*ScenarioParameters!$G3*(1/1000) -> -250.71973 | G9: =(-1)*(ScenarioParameters!$B$5+(ScenarioParameters!$B$5*$B$1))*ScenarioParameters!$G4*(1/1000) -> -640.571 | H9: =(-1)*(ScenarioParameters!$B$5+(ScenarioParameters!$B$5*$B$1))*ScenarioParameters!$G5*(1/1000) -> -497.1162 | I9: =(-1)*(ScenarioParameters!$B$5+(ScenarioParameters!$B$5*$B$1))*ScenarioParameters!$G6*(1/1000) -> -958.09692 | J9: =(-1)*(ScenarioParameters!$B$5+(ScenarioParameters!$B$5*$B$1))*ScenarioParameters!$G7*(1/1000) -> -525.99719 | K9: =(-1)*(ScenarioParameters!$B$5+(ScenarioParameters!$B$5*$B$1))*ScenarioParameters!$G8*(1/1000) -> -1047.2441 | L9: =(-1)*(ScenarioParameters!$B$5+(ScenarioParameters!$B$5*$B$1))*ScenarioParameters!$G9*(1/1000) -> -707.00346 | M9: =(-1)*(ScenarioParameters!$B$5+(ScenarioParameters!$B$5*$B$1))*ScenarioParameters!$G10*(1/1000) -> -1257.7389 | N9: =(-1)*(ScenarioParameters!$B$5+(ScenarioParameters!$B$5*$B$1))*ScenarioParameters!$G11*(1/1000) -> -666.61585 | O9: =(-1)*(ScenarioParameters!$B$5+(ScenarioParameters!$B$5*$B$1))*ScenarioParameters!$G12*(1/1000) -> -1308.5391 | P9: =(-1)*(ScenarioParameters!$B$5+(ScenarioParameters!$B$5*$B$1))*ScenarioParameters!$G13*(1/1000) -> -868.8754 | Q9: =(-1)*(ScenarioParameters!$B$5+(ScenarioParameters!$B$5*$B$1))*ScenarioParameters!$G14*(1/1000) -> -1528.7308 | R9: =(-1)*(ScenarioParameters!$B$5+(ScenarioParameters!$B$5*$B$1))*ScenarioParameters!$G15*(1/1000) -> -816.57403 | S9: =(-1)*(ScenarioParameters!$B$5+(ScenarioParameters!$B$5*$B$1))*ScenarioParameters!$G16*(1/1000) -> -1587.2276 | T9: =(-1)*(ScenarioParameters!$B$5+(ScenarioParameters!$B$5*$B$1))*ScenarioParameters!$G16*(1/1000) -> -1587.2276 | U9: =(-1)*(ScenarioParameters!$B$5+(ScenarioParameters!$B$5*$B$1))*ScenarioParameters!$G18*(1/1000) -> -1822.9809
A10: Production volume | F10: =ScenarioParameters!$G3 -> 3106.9661 | G10: =ScenarioParameters!$G4 -> 7938.0762 | H10: =ScenarioParameters!$G5 -> 6160.3574 | I10: =ScenarioParameters!$G6 -> 11872.917 | J10: =ScenarioParameters!$G7 -> 6518.2561 | K10: =ScenarioParameters!$G8 -> 12977.645 | L10: =ScenarioParameters!$G9 -> 8761.3198 | M10: =ScenarioParameters!$G10 -> 15586.137 | N10: =ScenarioParameters!$G11 -> 8260.8289 | O10: =ScenarioParameters!$G12 -> 16215.662 | P10: =ScenarioParameters!$G13 -> 10767.267 | Q10: =ScenarioParameters!$G14 -> 18944.32 | R10: =ScenarioParameters!$G15 -> 10119.139 | S10: =ScenarioParameters!$G16 -> 19669.223 | T10: =ScenarioParameters!$G17 -> 12944.52 | U10: =ScenarioParameters!$G18 -> 22590.723
A11: Unit product cost | F11: =F9/F10 -> -0.080696 | G11: =G9/G10 -> -0.080696 | H11: =H9/H10 -> -0.080696 | I11: =I9/I10 -> -0.080696 | J11: =J9/J10 -> -0.080696 | K11: =K9/K10 -> -0.080696 | L11: =L9/L10 -> -0.080696 | M11: =M9/M10 -> -0.080696 | ... U11: =U9/U10 -> -0.080696
A12: Sales revenue | F12: =(ScenarioParameters!$B$4*F10)*(1/1000) -> 928.98285 | G12: =(ScenarioParameters!$B$4*G10)*(1/1000) -> 2373.4848 | H12: =(ScenarioParameters!$B$4*H10)*(1/1000) -> 1841.9469 | I12: =(ScenarioParameters!$B$4*I10)*(1/1000) -> 3550.0022 | J12: =(ScenarioParameters!$B$4*J10)*(1/1000) -> 1948.9586 | K12: =(ScenarioParameters!$B$4*K10)*(1/1000) -> 3880.3159 | L12: =(ScenarioParameters!$B$4*L10)*(1/1000) -> 2619.6346 | M12: =(ScenarioParameters!$B$4*M10)*(1/1000) -> 4660.255 | ... U12: =(ScenarioParameters!$B$4*U10)*(1/1000) -> 6754.626
A13: Forecasted Sales Volume | F13: =F$10 -> 3106.9661 | G13: =G$10 -> 7938.0762 | H13: =H$10 -> 6160.3574 | I13: =I$10 -> 11872.917 | J13: =J$10 -> 6518.2561 | K13: =K$10 -> 12977.645 | L13: =L$10 -> 8761.3198 | M13: =M$10 -> 15586.137 | ... U13: =U$10 -> 22590.723
A14: Unit price | F14: =F$12/F$13 -> 0.299 | G14: =G$12/G$13 -> 0.299 | H14: =H$12/H$13 -> 0.299 | I14: =I$12/I$13 -> 0.299 | J14: =J$12/J$13 -> 0.299 | K14: =K$12/K$13 -> 0.299 | L14: =L$12/L$13 -> 0.299 | M14: =M$12/M$13 -> 0.299 | ... U14: =U$12/U$13 -> 0.299
A16: Period Cash Flow | B16: =SUM(B6+B7+B8+B9+B12) -> -15.12 | C16: =SUM(C6+C7+C8+C9+C12) -> -15.12 | D16: =SUM(D6+D7+D8+D9+D12) -> -15.12 | E16: =SUM(E6+E7+E8+E9+E12) -> -18.144 | F16: =SUM(F6+F7+F8+F9+F12) -> 465.23912 | G16: =SUM(G6+G7+G8+G9+G12) -> 1522.9138 | H16: =SUM(H6+H7+H8+H9+H12) -> 1134.8307 | I16: =SUM(I6+I7+I8+I9+I12) -> 2381.9053 | ... U16: =SUM(U6+U7+U8+U9+U12) -> 4721.6451
A17: Unit Price | B17: =B16 -> -15.12 | C17: =C16/(1+(ScenarioParameters!$B$8/100)/4)^B3 -> -14.859951 | D17: =D16/(1+(ScenarioParameters!$B$8/100)/4)^C3 -> -14.604374 | E17: =E16/(1+(ScenarioParameters!$B$8/100)/4)^D3 -> -17.223832 | F17: =F16/(1+(ScenarioParameters!$B$8/100)/4)^E3 -> 434.0488 | G17: =G16/(1+(ScenarioParameters!$B$8/100)/4)^F3 -> 1396.3787 | H17: =H16/(1+(ScenarioParameters!$B$8/100)/4)^G3 -> 1022.6442 | I17: =I16/(1+(ScenarioParameters!$B$8/100)/4)^H3 -> 2109.5196 | J17: =J16/(1+(ScenarioParameters!$B$8/100)/4)^I3 -> 1055.7756 | ... U17: =U16/(1+(ScenarioParameters!$B$8/100)/4)^T3 -> 3395.7789
A19: Project NVP | B19: =SUM(B17:U17) -> 30394.601
A21: Forecasted Sales Volume from Winter's forecasting method*

Sheet +10% SalesVol
A1: Sales Volume Analysis: | B1: 0.1
B2: Year 0, Development | F2: Year 1, Projection | J2: Year 2, Projection | N2: Year 3, Projection | R2: Year 4, Projection
A3: Period | B3: 1 | C3: =B3+1 -> 2 | D3: =C3+1 -> 3 | E3: =D3+1 -> 4 | F3: =E3+1 -> 5 | G3: =F3+1 -> 6 | H3: =G3+1 -> 7 | I3: =H3+1 -> 8 | J3: =I3+1 -> 9 | ... U3: =T3+1 -> 20
A4: ($Value in thousands) | B4: Q1 | C4: Q2 | D4: Q3 | E4: Q4 | F4: Q1 | G4: Q2 | H4: Q3 | I4: Q4 | J4: Q1 | K4: Q2 | L4: Q3 | M4: Q4 | N4: Q1 | O4: Q2 | P4: Q3 | Q4: Q4 | R4: Q1 | S4: Q2 | T4: Q3 | U4: Q4
A6: Development Cost | B6: =(-1)*ScenarioParameters!$B$3/4*(1/1000) -> -15.12 | C6: =(-1)*ScenarioParameters!$B$3/4*(1/1000) -> -15.12 | D6: =(-1)*ScenarioParameters!$B$3/4*(1/1000) -> -15.12 | E6: =(-1)*ScenarioParameters!$B$3/4*(1/1000) -> -15.12
A7: Ramp-up cost | E7: =(-1)*ScenarioParameters!$B$6/2*(1/1000) -> -3.024 | F7: =(-1)*ScenarioParameters!$B$6/2*(1/1000) -> -3.024
A8: Marketing & support cost | F8: =(-1)*ScenarioParameters!$B$7/4*(1/1000) -> -210 | G8: =(-1)*ScenarioParameters!$B$7/4*(1/1000) -> -210 | H8: =(-1)*ScenarioParameters!$B$7/4*(1/1000) -> -210 | I8: =(-1)*ScenarioParameters!$B$7/4*(1/1000) -> -210 | J8: =(-1)*ScenarioParameters!$B$7/4*(1/1000) -> -210 | K8: =(-1)*ScenarioParameters!$B$7/4*(1/1000) -> -210 | L8: =(-1)*ScenarioParameters!$B$7/4*(1/1000) -> -210 | M8: =(-1)*ScenarioParameters!$B$7/4*(1/1000) -> -210 | ... U8: =(-1)*ScenarioParameters!$B$7/4*(1/1000) -> -210
A9: Production Cost | F9: =(-1)*(ScenarioParameters!$B$5)*ScenarioParameters!$G3*(1/1000) -> -358.17105 | G9: =(-1)*(ScenarioParameters!$B$5)*ScenarioParameters!$G4*(1/1000) -> -915.10143 | H9: =(-1)*(ScenarioParameters!$B$5)*ScenarioParameters!$G5*(1/1000) -> -710.166 | I9: =(-1)*(ScenarioParameters!$B$5)*ScenarioParameters!$G6*(1/1000) -> -1368.7099 | J9: =(-1)*(ScenarioParameters!$B$5)*ScenarioParameters!$G7*(1/1000) -> -751.42456 | K9: =(-1)*(ScenarioParameters!$B$5)*ScenarioParameters!$G8*(1/1000) -> -1496.0629 | L9: =(-1)*(ScenarioParameters!$B$5)*ScenarioParameters!$G9*(1/1000) -> -1010.0049 | M9: =(-1)*(ScenarioParameters!$B$5)*ScenarioParameters!$G10*(1/1000) -> -1796.7699 | N9: =(-1)*(ScenarioParameters!$B$5)*ScenarioParameters!$G11*(1/1000) -> -952.30836 | O9: =(-1)*(ScenarioParameters!$B$5)*ScenarioParameters!$G12*(1/1000) -> -1869.3415 | P9: =(-1)*(ScenarioParameters!$B$5)*ScenarioParameters!$G13*(1/1000) -> -1241.2506 | Q9: =(-1)*(ScenarioParameters!$B$5)*ScenarioParameters!$G14*(1/1000) -> -2183.9012 | R9: =(-1)*(ScenarioParameters!$B$5)*ScenarioParameters!$G15*(1/1000) -> -1166.5343 | S9: =(-1)*(ScenarioParameters!$B$5)*ScenarioParameters!$G16*(1/1000) -> -2267.4681 | T9: =(-1)*(ScenarioParameters!$B$5)*ScenarioParameters!$G17*(1/1000) -> -1492.2443 | U9: =(-1)*(ScenarioParameters!$B$5)*ScenarioParameters!$G18*(1/1000) -> -2604.2585
A10: Production volume | F10: =ScenarioParameters!$G3+ScenarioParameters!$G3*$B$1 -> 3417.6627 | G10: =ScenarioParameters!$G4+ScenarioParameters!$G4*$B$1 -> 8731.8839 | H10: =ScenarioParameters!$G5+ScenarioParameters!$G5*$B$1 -> 6776.3931 | I10: =ScenarioParameters!$G6+ScenarioParameters!$G6*$B$1 -> 13060.209 | J10: =ScenarioParameters!$G7+ScenarioParameters!$G7*$B$1 -> 7170.0817 | K10: =ScenarioParameters!$G8+ScenarioParameters!$G8*$B$1 -> 14275.41 | L10: =ScenarioParameters!$G9+ScenarioParameters!$G9*$B$1 -> 9637.4517 | M10: =ScenarioParameters!$G10+ScenarioParameters!$G10*$B$1 -> 17144.751 | N10: =ScenarioParameters!$G11+ScenarioParameters!$G11*$B$1 -> 9086.9118 | O10: =ScenarioParameters!$G12+ScenarioParameters!$G12*$B$1 -> 17837.228 | P10: =ScenarioParameters!$G13+ScenarioParameters!$G13*$B$1 -> 11843.994 | Q10: =ScenarioParameters!$G14+ScenarioParameters!$G14*$B$1 -> 20838.752 | R10: =ScenarioParameters!$G15+ScenarioParameters!$G15*$B$1 -> 11131.053 | S10: =ScenarioParameters!$G16+ScenarioParameters!$G16*$B$1 -> 21636.146 | T10: =ScenarioParameters!$G17+ScenarioParameters!$G17*$B$1 -> 14238.972 | U10: =ScenarioParameters!$G18+ScenarioParameters!$G18*$B$1 -> 24849.795
A11: Unit product cost | F11: =F9/F10 -> -0.1048 | G11: =G9/G10 -> -0.1048 | H11: =H9/H10 -> -0.1048 | I11: =I9/I10 -> -0.1048 | J11: =J9/J10 -> -0.1048 | K11: =K9/K10 -> -0.1048 | L11: =L9/L10 -> -0.1048 | M11: =M9/M10 -> -0.1048 | ... U11: =U9/U10 -> -0.1048
A12: Sales revenue | F12: =(ScenarioParameters!$B$4*F10)*(1/1000) -> 1021.8811 | G12: =(ScenarioParameters!$B$4*G10)*(1/1000) -> 2610.8333 | H12: =(ScenarioParameters!$B$4*H10)*(1/1000) -> 2026.1415 | I12: =(ScenarioParameters!$B$4*I10)*(1/1000) -> 3905.0024 | J12: =(ScenarioParameters!$B$4*J10)*(1/1000) -> 2143.8544 | K12: =(ScenarioParameters!$B$4*K10)*(1/1000) -> 4268.3475 | L12: =(ScenarioParameters!$B$4*L10)*(1/1000) -> 2881.5981 | M12: =(ScenarioParameters!$B$4*M10)*(1/1000) -> 5126.2805 | ... U12: =(ScenarioParameters!$B$4*U10)*(1/1000) -> 7430.0886
A13: Forecasted Sales Volume | F13: =F$10 -> 3417.6627 | G13: =G$10 -> 8731.8839 | H13: =H$10 -> 6776.3931 | I13: =I$10 -> 13060.209 | J13: =J$10 -> 7170.0817 | K13: =K$10 -> 14275.41 | L13: =L$10 -> 9637.4517 | M13: =M$10 -> 17144.751 | ... U13: =U$10 -> 24849.795
A14: Unit price | F14: =F$12/F$13 -> 0.299 | G14: =G$12/G$13 -> 0.299 | H14: =H$12/H$13 -> 0.299 | I14: =I$12/I$13 -> 0.299 | J14: =J$12/J$13 -> 0.299 | K14: =K$12/K$13 -> 0.299 | L14: =L$12/L$13 -> 0.299 | M14: =M$12/M$13 -> 0.299 | ... U14: =U$12/U$13 -> 0.299
A16: Period Cash Flow | B16: =SUM(B6+B7+B8+B9+B12) -> -15.12 | C16: =SUM(C6+C7+C8+C9+C12) -> -15.12 | D16: =SUM(D6+D7+D8+D9+D12) -> -15.12 | E16: =SUM(E6+E7+E8+E9+E12) -> -18.144 | F16: =SUM(F6+F7+F8+F9+F12) -> 450.68609 | G16: =SUM(G6+G7+G8+G9+G12) -> 1485.7318 | H16: =SUM(H6+H7+H8+H9+H12) -> 1105.9755 | I16: =SUM(I6+I7+I8+I9+I12) -> 2326.2925 | ... U16: =SUM(U6+U7+U8+U9+U12) -> 4615.8302
A17: Unit Price | B17: =B16 -> -15.12 | C17: =C16/(1+(ScenarioParameters!$B$8/100)/4)^B3 -> -14.859951 | D17: =D16/(1+(ScenarioParameters!$B$8/100)/4)^C3 -> -14.604374 | E17: =E16/(1+(ScenarioParameters!$B$8/100)/4)^D3 -> -17.223832 | F17: =F16/(1+(ScenarioParameters!$B$8/100)/4)^E3 -> 420.47142 | G17: =G16/(1+(ScenarioParameters!$B$8/100)/4)^F3 -> 1362.2862 | H17: =H16/(1+(ScenarioParameters!$B$8/100)/4)^G3 -> 996.64161 | I17: =I16/(1+(ScenarioParameters!$B$8/100)/4)^H3 -> 2060.2665 | J17: =J16/(1+(ScenarioParameters!$B$8/100)/4)^I3 -> 1029.2006 | ... U17: =U16/(1+(ScenarioParameters!$B$8/100)/4)^T3 -> 3319.6774
A19: Project NVP | B19: =SUM(B17:U17) -> 30070.4
A21: Forecasted Sales Volume from Winter's forecasting method*

Sheet -10% SalesVol
A1: Sales Volume Analysis: | B1: -0.1
B2: Year 0, Development | F2: Year 1, Projection | J2: Year 2, Projection | N2: Year 3, Projection | R2: Year 4, Projection
A3: Period | B3: 1 | C3: =B3+1 -> 2 | D3: =C3+1 -> 3 | E3: =D3+1 -> 4 | F3: =E3+1 -> 5 | G3: =F3+1 -> 6 | H3: =G3+1 -> 7 | I3: =H3+1 -> 8 | J3: =I3+1 -> 9 | ... U3: =T3+1 -> 20
A4: ($Value in thousands) | B4: Q1 | C4: Q2 | D4: Q3 | E4: Q4 | F4: Q1 | G4: Q2 | H4: Q3 | I4: Q4 | J4: Q1 | K4: Q2 | L4: Q3 | M4: Q4 | N4: Q1 | O4: Q2 | P4: Q3 | Q4: Q4 | R4: Q1 | S4: Q2 | T4: Q3 | U4: Q4
A6: Development Cost | B6: =(-1)*ScenarioParameters!$B$3/4*(1/1000) -> -15.12 | C6: =(-1)*ScenarioParameters!$B$3/4*(1/1000) -> -15.12 | D6: =(-1)*ScenarioParameters!$B$3/4*(1/1000) -> -15.12 | E6: =(-1)*ScenarioParameters!$B$3/4*(1/1000) -> -15.12
A7: Ramp-up cost | E7: =(-1)*ScenarioParameters!$B$6/2*(1/1000) -> -3.024 | F7: =(-1)*ScenarioParameters!$B$6/2*(1/1000) -> -3.024
A8: Marketing & support cost | F8: =(-1)*ScenarioParameters!$B$7/4*(1/1000) -> -210 | G8: =(-1)*ScenarioParameters!$B$7/4*(1/1000) -> -210 | H8: =(-1)*ScenarioParameters!$B$7/4*(1/1000) -> -210 | I8: =(-1)*ScenarioParameters!$B$7/4*(1/1000) -> -210 | J8: =(-1)*ScenarioParameters!$B$7/4*(1/1000) -> -210 | K8: =(-1)*ScenarioParameters!$B$7/4*(1/1000) -> -210 | L8: =(-1)*ScenarioParameters!$B$7/4*(1/1000) -> -210 | M8: =(-1)*ScenarioParameters!$B$7/4*(1/1000) -> -210 | ... U8: =(-1)*ScenarioParameters!$B$7/4*(1/1000) -> -210
A9: Production Cost | F9: =(-1)*(ScenarioParameters!$B$5)*ScenarioParameters!$G3*(1/1000) -> -358.17105 | G9: =(-1)*(ScenarioParameters!$B$5)*ScenarioParameters!$G4*(1/1000) -> -915.10143 | H9: =(-1)*(ScenarioParameters!$B$5)*ScenarioParameters!$G5*(1/1000) -> -710.166 | I9: =(-1)*(ScenarioParameters!$B$5)*ScenarioParameters!$G6*(1/1000) -> -1368.7099 | J9: =(-1)*(ScenarioParameters!$B$5)*ScenarioParameters!$G7*(1/1000) -> -751.42456 | K9: =(-1)*(ScenarioParameters!$B$5)*ScenarioParameters!$G8*(1/1000) -> -1496.0629 | L9: =(-1)*(ScenarioParameters!$B$5)*ScenarioParameters!$G9*(1/1000) -> -1010.0049 | M9: =(-1)*(ScenarioParameters!$B$5)*ScenarioParameters!$G10*(1/1000) -> -1796.7699 | N9: =(-1)*(ScenarioParameters!$B$5)*ScenarioParameters!$G11*(1/1000) -> -952.30836 | O9: =(-1)*(ScenarioParameters!$B$5)*ScenarioParameters!$G12*(1/1000) -> -1869.3415 | P9: =(-1)*(ScenarioParameters!$B$5)*ScenarioParameters!$G13*(1/1000) -> -1241.2506 | Q9: =(-1)*(ScenarioParameters!$B$5)*ScenarioParameters!$G14*(1/1000) -> -2183.9012 | R9: =(-1)*(ScenarioParameters!$B$5)*ScenarioParameters!$G15*(1/1000) -> -1166.5343 | S9: =(-1)*(ScenarioParameters!$B$5)*ScenarioParameters!$G16*(1/1000) -> -2267.4681 | T9: =(-1)*(ScenarioParameters!$B$5)*ScenarioParameters!$G17*(1/1000) -> -1492.2443 | U9: =(-1)*(ScenarioParameters!$B$5)*ScenarioParameters!$G18*(1/1000) -> -2604.2585
A10: Production volume | F10: =ScenarioParameters!$G3+ScenarioParameters!$G3*$B$1 -> 2796.2695 | G10: =ScenarioParameters!$G4+ScenarioParameters!$G4*$B$1 -> 7144.2686 | H10: =ScenarioParameters!$G5+ScenarioParameters!$G5*$B$1 -> 5544.3216 | I10: =ScenarioParameters!$G6+ScenarioParameters!$G6*$B$1 -> 10685.625 | J10: =ScenarioParameters!$G7+ScenarioParameters!$G7*$B$1 -> 5866.4305 | K10: =ScenarioParameters!$G8+ScenarioParameters!$G8*$B$1 -> 11679.881 | L10: =ScenarioParameters!$G9+ScenarioParameters!$G9*$B$1 -> 7885.1878 | M10: =ScenarioParameters!$G10+ScenarioParameters!$G10*$B$1 -> 14027.523 | N10: =ScenarioParameters!$G11+ScenarioParameters!$G11*$B$1 -> 7434.746 | O10: =ScenarioParameters!$G12+ScenarioParameters!$G12*$B$1 -> 14594.096 | P10: =ScenarioParameters!$G13+ScenarioParameters!$G13*$B$1 -> 9690.5405 | Q10: =ScenarioParameters!$G14+ScenarioParameters!$G14*$B$1 -> 17049.888 | R10: =ScenarioParameters!$G15+ScenarioParameters!$G15*$B$1 -> 9107.225 | S10: =ScenarioParameters!$G16+ScenarioParameters!$G16*$B$1 -> 17702.301 | T10: =ScenarioParameters!$G17+ScenarioParameters!$G17*$B$1 -> 11650.068 | U10: =ScenarioParameters!$G18+ScenarioParameters!$G18*$B$1 -> 20331.65
A11: Unit product cost | F11: =F9/F10 -> -0.12808889 | G11: =G9/G10 -> -0.12808889 | H11: =H9/H10 -> -0.12808889 | I11: =I9/I10 -> -0.12808889 | J11: =J9/J10 -> -0.12808889 | K11: =K9/K10 -> -0.12808889 | L11: =L9/L10 -> -0.12808889 | M11: =M9/M10 -> -0.12808889 | ... U11: =U9/U10 -> -0.12808889
A12: Sales revenue | F12: =(ScenarioParameters!$B$4*F10)*(1/1000) -> 836.08457 | G12: =(ScenarioParameters!$B$4*G10)*(1/1000) -> 2136.1363 | H12: =(ScenarioParameters!$B$4*H10)*(1/1000) -> 1657.7522 | I12: =(ScenarioParameters!$B$4*I10)*(1/1000) -> 3195.002 | J12: =(ScenarioParameters!$B$4*J10)*(1/1000) -> 1754.0627 | K12: =(ScenarioParameters!$B$4*K10)*(1/1000) -> 3492.2843 | L12: =(ScenarioParameters!$B$4*L10)*(1/1000) -> 2357.6711 | M12: =(ScenarioParameters!$B$4*M10)*(1/1000) -> 4194.2295 | ... U12: =(ScenarioParameters!$B$4*U10)*(1/1000) -> 6079.1634
A13: Forecasted Sales Volume | F13: =F$10 -> 2796.2695 | G13: =G$10 -> 7144.2686 | H13: =H$10 -> 5544.3216 | I13: =I$10 -> 10685.625 | J13: =J$10 -> 5866.4305 | K13: =K$10 -> 11679.881 | L13: =L$10 -> 7885.1878 | M13: =M$10 -> 14027.523 | ... U13: =U$10 -> 20331.65
A14: Unit price | F14: =F$12/F$13 -> 0.299 | G14: =G$12/G$13 -> 0.299 | H14: =H$12/H$13 -> 0.299 | I14: =I$12/I$13 -> 0.299 | J14: =J$12/J$13 -> 0.299 | K14: =K$12/K$13 -> 0.299 | L14: =L$12/L$13 -> 0.299 | M14: =M$12/M$13 -> 0.299 | ... U14: =U$12/U$13 -> 0.299
A16: Period Cash Flow | B16: =SUM(B6+B7+B8+B9+B12) -> -15.12 | C16: =SUM(C6+C7+C8+C9+C12) -> -15.12 | D16: =SUM(D6+D7+D8+D9+D12) -> -15.12 | E16: =SUM(E6+E7+E8+E9+E12) -> -18.144 | F16: =SUM(F6+F7+F8+F9+F12) -> 264.88952 | G16: =SUM(G6+G7+G8+G9+G12) -> 1011.0349 | H16: =SUM(H6+H7+H8+H9+H12) -> 737.58617 | I16: =SUM(I6+I7+I8+I9+I12) -> 1616.2921 | ... U16: =SUM(U6+U7+U8+U9+U12) -> 3264.9049
A17: Unit Price | B17: =B16 -> -15.12 | C17: =C16/(1+(ScenarioParameters!$B$8/100)/4)^B3 -> -14.859951 | D17: =D16/(1+(ScenarioParameters!$B$8/100)/4)^C3 -> -14.604374 | E17: =E16/(1+(ScenarioParameters!$B$8/100)/4)^D3 -> -17.223832 | F17: =F16/(1+(ScenarioParameters!$B$8/100)/4)^E3 -> 247.13093 | G17: =G16/(1+(ScenarioParameters!$B$8/100)/4)^F3 -> 927.03056 | H17: =H16/(1+(ScenarioParameters!$B$8/100)/4)^G3 -> 664.67028 | I17: =I16/(1+(ScenarioParameters!$B$8/100)/4)^H3 -> 1431.459 | J17: =J16/(1+(ScenarioParameters!$B$8/100)/4)^I3 -> 689.92142 | ... U17: =U16/(1+(ScenarioParameters!$B$8/100)/4)^T3 -> 2348.1001
A19: Project NVP | B19: =SUM(B17:U17) -> 20861.58
A21: Forecasted Sales Volume from Winter's forecasting method*

Sheet +20% SalesVol
A1: Sales Volume Analysis: | B1: 0.2
B2: Year 0, Development | F2: Year 1, Projection | J2: Year 2, Projection | N2: Year 3, Projection | R2: Year 4, Projection
A3: Period | B3: 1 | C3: =B3+1 -> 2 | D3: =C3+1 -> 3 | E3: =D3+1 -> 4 | F3: =E3+1 -> 5 | G3: =F3+1 -> 6 | H3: =G3+1 -> 7 | I3: =H3+1 -> 8 | J3: =I3+1 -> 9 | ... U3: =T3+1 -> 20
A4: ($Value in thousands) | B4: Q1 | C4: Q2 | D4: Q3 | E4: Q4 | F4: Q1 | G4: Q2 | H4: Q3 | I4: Q4 | J4: Q1 | K4: Q2 | L4: Q3 | M4: Q4 | N4: Q1 | O4: Q2 | P4: Q3 | Q4: Q4 | R4: Q1 | S4: Q2 | T4: Q3 | U4: Q4
A6: Development Cost | B6: =(-1)*ScenarioParameters!$B$3/4*(1/1000) -> -15.12 | C6: =(-1)*ScenarioParameters!$B$3/4*(1/1000) -> -15.12 | D6: =(-1)*ScenarioParameters!$B$3/4*(1/1000) -> -15.12 | E6: =(-1)*ScenarioParameters!$B$3/4*(1/1000) -> -15.12
A7: Ramp-up cost | E7: =(-1)*ScenarioParameters!$B$6/2*(1/1000) -> -3.024 | F7: =(-1)*ScenarioParameters!$B$6/2*(1/1000) -> -3.024
A8: Marketing & support cost | F8: =(-1)*ScenarioParameters!$B$7/4*(1/1000) -> -210 | G8: =(-1)*ScenarioParameters!$B$7/4*(1/1000) -> -210 | H8: =(-1)*ScenarioParameters!$B$7/4*(1/1000) -> -210 | I8: =(-1)*ScenarioParameters!$B$7/4*(1/1000) -> -210 | J8: =(-1)*ScenarioParameters!$B$7/4*(1/1000) -> -210 | K8: =(-1)*ScenarioParameters!$B$7/4*(1/1000) -> -210 | L8: =(-1)*ScenarioParameters!$B$7/4*(1/1000) -> -210 | M8: =(-1)*ScenarioParameters!$B$7/4*(1/1000) -> -210 | ... U8: =(-1)*ScenarioParameters!$B$7/4*(1/1000) -> -210
A9: Production Cost | F9: =(-1)*(ScenarioParameters!$B$5)*ScenarioParameters!$G3*(1/1000) -> -358.17105 | G9: =(-1)*(ScenarioParameters!$B$5)*ScenarioParameters!$G4*(1/1000) -> -915.10143 | H9: =(-1)*(ScenarioParameters!$B$5)*ScenarioParameters!$G5*(1/1000) -> -710.166 | I9: =(-1)*(ScenarioParameters!$B$5)*ScenarioParameters!$G6*(1/1000) -> -1368.7099 | J9: =(-1)*(ScenarioParameters!$B$5)*ScenarioParameters!$G7*(1/1000) -> -751.42456 | K9: =(-1)*(ScenarioParameters!$B$5)*ScenarioParameters!$G8*(1/1000) -> -1496.0629 | L9: =(-1)*(ScenarioParameters!$B$5)*ScenarioParameters!$G9*(1/1000) -> -1010.0049 | M9: =(-1)*(ScenarioParameters!$B$5)*ScenarioParameters!$G10*(1/1000) -> -1796.7699 | N9: =(-1)*(ScenarioParameters!$B$5)*ScenarioParameters!$G11*(1/1000) -> -952.30836 | O9: =(-1)*(ScenarioParameters!$B$5)*ScenarioParameters!$G12*(1/1000) -> -1869.3415 | P9: =(-1)*(ScenarioParameters!$B$5)*ScenarioParameters!$G13*(1/1000) -> -1241.2506 | Q9: =(-1)*(ScenarioParameters!$B$5)*ScenarioParameters!$G14*(1/1000) -> -2183.9012 | R9: =(-1)*(ScenarioParameters!$B$5)*ScenarioParameters!$G15*(1/1000) -> -1166.5343 | S9: =(-1)*(ScenarioParameters!$B$5)*ScenarioParameters!$G16*(1/1000) -> -2267.4681 | T9: =(-1)*(ScenarioParameters!$B$5)*ScenarioParameters!$G17*(1/1000) -> -1492.2443 | U9: =(-1)*(ScenarioParameters!$B$5)*ScenarioParameters!$G18*(1/1000) -> -2604.2585
A10: Production volume | F10: =ScenarioParameters!$G3+ScenarioParameters!$G3*$B$1 -> 3728.3593 | G10: =ScenarioParameters!$G4+ScenarioParameters!$G4*$B$1 -> 9525.6915 | H10: =ScenarioParameters!$G5+ScenarioParameters!$G5*$B$1 -> 7392.4288 | I10: =ScenarioParameters!$G6+ScenarioParameters!$G6*$B$1 -> 14247.501 | J10: =ScenarioParameters!$G7+ScenarioParameters!$G7*$B$1 -> 7821.9073 | K10: =ScenarioParameters!$G8+ScenarioParameters!$G8*$B$1 -> 15573.174 | L10: =ScenarioParameters!$G9+ScenarioParameters!$G9*$B$1 -> 10513.584 | M10: =ScenarioParameters!$G10+ScenarioParameters!$G10*$B$1 -> 18703.365 | N10: =ScenarioParameters!$G11+ScenarioParameters!$G11*$B$1 -> 9912.9947 | O10: =ScenarioParameters!$G12+ScenarioParameters!$G12*$B$1 -> 19458.794 | P10: =ScenarioParameters!$G13+ScenarioParameters!$G13*$B$1 -> 12920.721 | Q10: =ScenarioParameters!$G14+ScenarioParameters!$G14*$B$1 -> 22733.184 | R10: =ScenarioParameters!$G15+ScenarioParameters!$G15*$B$1 -> 12142.967 | S10: =ScenarioParameters!$G16+ScenarioParameters!$G16*$B$1 -> 23603.068 | T10: =ScenarioParameters!$G17+ScenarioParameters!$G17*$B$1 -> 15533.424 | U10: =ScenarioParameters!$G18+ScenarioParameters!$G18*$B$1 -> 27108.867
A11: Unit product cost | F11: =F9/F10 -> -0.096066667 | G11: =G9/G10 -> -0.096066667 | H11: =H9/H10 -> -0.096066667 | I11: =I9/I10 -> -0.096066667 | J11: =J9/J10 -> -0.096066667 | K11: =K9/K10 -> -0.096066667 | L11: =L9/L10 -> -0.096066667 | M11: =M9/M10 -> -0.096066667 | ... U11: =U9/U10 -> -0.096066667
A12: Sales revenue | F12: =(ScenarioParameters!$B$4*F10)*(1/1000) -> 1114.7794 | G12: =(ScenarioParameters!$B$4*G10)*(1/1000) -> 2848.1818 | H12: =(ScenarioParameters!$B$4*H10)*(1/1000) -> 2210.3362 | I12: =(ScenarioParameters!$B$4*I10)*(1/1000) -> 4260.0027 | J12: =(ScenarioParameters!$B$4*J10)*(1/1000) -> 2338.7503 | K12: =(ScenarioParameters!$B$4*K10)*(1/1000) -> 4656.3791 | L12: =(ScenarioParameters!$B$4*L10)*(1/1000) -> 3143.5615 | M12: =(ScenarioParameters!$B$4*M10)*(1/1000) -> 5592.306 | ... U12: =(ScenarioParameters!$B$4*U10)*(1/1000) -> 8105.5513
A13: Forecasted Sales Volume | F13: =F$10 -> 3728.3593 | G13: =G$10 -> 9525.6915 | H13: =H$10 -> 7392.4288 | I13: =I$10 -> 14247.501 | J13: =J$10 -> 7821.9073 | K13: =K$10 -> 15573.174 | L13: =L$10 -> 10513.584 | M13: =M$10 -> 18703.365 | ... U13: =U$10 -> 27108.867
A14: Unit price | F14: =F$12/F$13 -> 0.299 | G14: =G$12/G$13 -> 0.299 | H14: =H$12/H$13 -> 0.299 | I14: =I$12/I$13 -> 0.299 | J14: =J$12/J$13 -> 0.299 | K14: =K$12/K$13 -> 0.299 | L14: =L$12/L$13 -> 0.299 | M14: =M$12/M$13 -> 0.299 | ... U14: =U$12/U$13 -> 0.299
A16: Period Cash Flow | B16: =SUM(B6+B7+B8+B9+B12) -> -15.12 | C16: =SUM(C6+C7+C8+C9+C12) -> -15.12 | D16: =SUM(D6+D7+D8+D9+D12) -> -15.12 | E16: =SUM(E6+E7+E8+E9+E12) -> -18.144 | F16: =SUM(F6+F7+F8+F9+F12) -> 543.58438 | G16: =SUM(G6+G7+G8+G9+G12) -> 1723.0803 | H16: =SUM(H6+H7+H8+H9+H12) -> 1290.1702 | I16: =SUM(I6+I7+I8+I9+I12) -> 2681.2928 | ... U16: =SUM(U6+U7+U8+U9+U12) -> 5291.2928
A17: Unit Price | B17: =B16 -> -15.12 | C17: =C16/(1+(ScenarioParameters!$B$8/100)/4)^B3 -> -14.859951 | D17: =D16/(1+(ScenarioParameters!$B$8/100)/4)^C3 -> -14.604374 | E17: =E16/(1+(ScenarioParameters!$B$8/100)/4)^D3 -> -17.223832 | F17: =F16/(1+(ScenarioParameters!$B$8/100)/4)^E3 -> 507.14167 | G17: =G16/(1+(ScenarioParameters!$B$8/100)/4)^F3 -> 1579.9139 | H17: =H16/(1+(ScenarioParameters!$B$8/100)/4)^G3 -> 1162.6273 | I17: =I16/(1+(ScenarioParameters!$B$8/100)/4)^H3 -> 2374.6703 | J17: =J16/(1+(ScenarioParameters!$B$8/100)/4)^I3 -> 1198.8402 | ... U17: =U16/(1+(ScenarioParameters!$B$8/100)/4)^T3 -> 3805.466
A19: Project NVP | B19: =SUM(B17:U17) -> 34674.811
A21: Forecasted Sales Volume from Winter's forecasting method*

Sheet -20% SalesVol
A1: Sales Volume Analysis: | B1: -0.2
B2: Year 0, Development | F2: Year 1, Projection | J2: Year 2, Projection | N2: Year 3, Projection | R2: Year 4, Projection
A3: Period | B3: 1 | C3: =B3+1 -> 2 | D3: =C3+1 -> 3 | E3: =D3+1 -> 4 | F3: =E3+1 -> 5 | G3: =F3+1 -> 6 | H3: =G3+1 -> 7 | I3: =H3+1 -> 8 | J3: =I3+1 -> 9 | ... U3: =T3+1 -> 20
A4: ($Value in thousands) | B4: Q1 | C4: Q2 | D4: Q3 | E4: Q4 | F4: Q1 | G4: Q2 | H4: Q3 | I4: Q4 | J4: Q1 | K4: Q2 | L4: Q3 | M4: Q4 | N4: Q1 | O4: Q2 | P4: Q3 | Q4: Q4 | R4: Q1 | S4: Q2 | T4: Q3 | U4: Q4
A6: Development Cost | B6: =(-1)*ScenarioParameters!$B$3/4*(1/1000) -> -15.12 | C6: =(-1)*ScenarioParameters!$B$3/4*(1/1000) -> -15.12 | D6: =(-1)*ScenarioParameters!$B$3/4*(1/1000) -> -15.12 | E6: =(-1)*ScenarioParameters!$B$3/4*(1/1000) -> -15.12
A7: Ramp-up cost | E7: =(-1)*ScenarioParameters!$B$6/2*(1/1000) -> -3.024 | F7: =(-1)*ScenarioParameters!$B$6/2*(1/1000) -> -3.024
A8: Marketing & support cost | F8: =(-1)*ScenarioParameters!$B$7/4*(1/1000) -> -210 | G8: =(-1)*ScenarioParameters!$B$7/4*(1/1000) -> -210 | H8: =(-1)*ScenarioParameters!$B$7/4*(1/1000) -> -210 | I8: =(-1)*ScenarioParameters!$B$7/4*(1/1000) -> -210 | J8: =(-1)*ScenarioParameters!$B$7/4*(1/1000) -> -210 | K8: =(-1)*ScenarioParameters!$B$7/4*(1/1000) -> -210 | L8: =(-1)*ScenarioParameters!$B$7/4*(1/1000) -> -210 | M8: =(-1)*ScenarioParameters!$B$7/4*(1/1000) -> -210 | ... U8: =(-1)*ScenarioParameters!$B$7/4*(1/1000) -> -210
A9: Production Cost | F9: =(-1)*(ScenarioParameters!$B$5)*ScenarioParameters!$G3*(1/1000) -> -358.17105 | G9: =(-1)*(ScenarioParameters!$B$5)*ScenarioParameters!$G4*(1/1000) -> -915.10143 | H9: =(-1)*(ScenarioParameters!$B$5)*ScenarioParameters!$G5*(1/1000) -> -710.166 | I9: =(-1)*(ScenarioParameters!$B$5)*ScenarioParameters!$G6*(1/1000) -> -1368.7099 | J9: =(-1)*(ScenarioParameters!$B$5)*ScenarioParameters!$G7*(1/1000) -> -751.42456 | K9: =(-1)*(ScenarioParameters!$B$5)*ScenarioParameters!$G8*(1/1000) -> -1496.0629 | L9: =(-1)*(ScenarioParameters!$B$5)*ScenarioParameters!$G9*(1/1000) -> -1010.0049 | M9: =(-1)*(ScenarioParameters!$B$5)*ScenarioParameters!$G10*(1/1000) -> -1796.7699 | N9: =(-1)*(ScenarioParameters!$B$5)*ScenarioParameters!$G11*(1/1000) -> -952.30836 | O9: =(-1)*(ScenarioParameters!$B$5)*ScenarioParameters!$G12*(1/1000) -> -1869.3415 | P9: =(-1)*(ScenarioParameters!$B$5)*ScenarioParameters!$G13*(1/1000) -> -1241.2506 | Q9: =(-1)*(ScenarioParameters!$B$5)*ScenarioParameters!$G14*(1/1000) -> -2183.9012 | R9: =(-1)*(ScenarioParameters!$B$5)*ScenarioParameters!$G15*(1/1000) -> -1166.5343 | S9: =(-1)*(ScenarioParameters!$B$5)*ScenarioParameters!$G16*(1/1000) -> -2267.4681 | T9: =(-1)*(ScenarioParameters!$B$5)*ScenarioParameters!$G17*(1/1000) -> -1492.2443 | U9: =(-1)*(ScenarioParameters!$B$5)*ScenarioParameters!$G18*(1/1000) -> -2604.2585
A10: Production volume | F10: =ScenarioParameters!$G3+ScenarioParameters!$G3*$B$1 -> 2485.5729 | G10: =ScenarioParameters!$G4+ScenarioParameters!$G4*$B$1 -> 6350.461 | H10: =ScenarioParameters!$G5+ScenarioParameters!$G5*$B$1 -> 4928.2859 | I10: =ScenarioParameters!$G6+ScenarioParameters!$G6*$B$1 -> 9498.3337 | J10: =ScenarioParameters!$G7+ScenarioParameters!$G7*$B$1 -> 5214.6049 | K10: =ScenarioParameters!$G8+ScenarioParameters!$G8*$B$1 -> 10382.116 | L10: =ScenarioParameters!$G9+ScenarioParameters!$G9*$B$1 -> 7009.0558 | M10: =ScenarioParameters!$G10+ScenarioParameters!$G10*$B$1 -> 12468.91 | N10: =ScenarioParameters!$G11+ScenarioParameters!$G11*$B$1 -> 6608.6631 | O10: =ScenarioParameters!$G12+ScenarioParameters!$G12*$B$1 -> 12972.53 | P10: =ScenarioParameters!$G13+ScenarioParameters!$G13*$B$1 -> 8613.8138 | Q10: =ScenarioParameters!$G14+ScenarioParameters!$G14*$B$1 -> 15155.456 | R10: =ScenarioParameters!$G15+ScenarioParameters!$G15*$B$1 -> 8095.3111 | S10: =ScenarioParameters!$G16+ScenarioParameters!$G16*$B$1 -> 15735.379 | T10: =ScenarioParameters!$G17+ScenarioParameters!$G17*$B$1 -> 10355.616 | U10: =ScenarioParameters!$G18+ScenarioParameters!$G18*$B$1 -> 18072.578
A11: Unit product cost | F11: =F9/F10 -> -0.1441 | G11: =G9/G10 -> -0.1441 | H11: =H9/H10 -> -0.1441 | I11: =I9/I10 -> -0.1441 | J11: =J9/J10 -> -0.1441 | K11: =K9/K10 -> -0.1441 | L11: =L9/L10 -> -0.1441 | M11: =M9/M10 -> -0.1441 | ... U11: =U9/U10 -> -0.1441
A12: Sales revenue | F12: =(ScenarioParameters!$B$4*F10)*(1/1000) -> 743.18628 | G12: =(ScenarioParameters!$B$4*G10)*(1/1000) -> 1898.7878 | H12: =(ScenarioParameters!$B$4*H10)*(1/1000) -> 1473.5575 | I12: =(ScenarioParameters!$B$4*I10)*(1/1000) -> 2840.0018 | J12: =(ScenarioParameters!$B$4*J10)*(1/1000) -> 1559.1669 | K12: =(ScenarioParameters!$B$4*K10)*(1/1000) -> 3104.2527 | L12: =(ScenarioParameters!$B$4*L10)*(1/1000) -> 2095.7077 | M12: =(ScenarioParameters!$B$4*M10)*(1/1000) -> 3728.204 | ... U12: =(ScenarioParameters!$B$4*U10)*(1/1000) -> 5403.7008
A13: Forecasted Sales Volume | F13: =F$10 -> 2485.5729 | G13: =G$10 -> 6350.461 | H13: =H$10 -> 4928.2859 | I13: =I$10 -> 9498.3337 | J13: =J$10 -> 5214.6049 | K13: =K$10 -> 10382.116 | L13: =L$10 -> 7009.0558 | M13: =M$10 -> 12468.91 | ... U13: =U$10 -> 18072.578
A14: Unit price | F14: =F$12/F$13 -> 0.299 | G14: =G$12/G$13 -> 0.299 | H14: =H$12/H$13 -> 0.299 | I14: =I$12/I$13 -> 0.299 | J14: =J$12/J$13 -> 0.299 | K14: =K$12/K$13 -> 0.299 | L14: =L$12/L$13 -> 0.299 | M14: =M$12/M$13 -> 0.299 | ... U14: =U$12/U$13 -> 0.299
A16: Period Cash Flow | B16: =SUM(B6+B7+B8+B9+B12) -> -15.12 | C16: =SUM(C6+C7+C8+C9+C12) -> -15.12 | D16: =SUM(D6+D7+D8+D9+D12) -> -15.12 | E16: =SUM(E6+E7+E8+E9+E12) -> -18.144 | F16: =SUM(F6+F7+F8+F9+F12) -> 171.99124 | G16: =SUM(G6+G7+G8+G9+G12) -> 773.68641 | H16: =SUM(H6+H7+H8+H9+H12) -> 553.39148 | I16: =SUM(I6+I7+I8+I9+I12) -> 1261.2919 | ... U16: =SUM(U6+U7+U8+U9+U12) -> 2589.4423
A17: Unit Price | B17: =B16 -> -15.12 | C17: =C16/(1+(ScenarioParameters!$B$8/100)/4)^B3 -> -14.859951 | D17: =D16/(1+(ScenarioParameters!$B$8/100)/4)^C3 -> -14.604374 | E17: =E16/(1+(ScenarioParameters!$B$8/100)/4)^D3 -> -17.223832 | F17: =F16/(1+(ScenarioParameters!$B$8/100)/4)^E3 -> 160.46069 | G17: =G16/(1+(ScenarioParameters!$B$8/100)/4)^F3 -> 709.40276 | H17: =H16/(1+(ScenarioParameters!$B$8/100)/4)^G3 -> 498.68461 | I17: =I16/(1+(ScenarioParameters!$B$8/100)/4)^H3 -> 1117.0553 | J17: =J16/(1+(ScenarioParameters!$B$8/100)/4)^I3 -> 520.28181 | ... U17: =U16/(1+(ScenarioParameters!$B$8/100)/4)^T3 -> 1862.3114
A19: Project NVP | B19: =SUM(B17:U17) -> 16257.169
A21: Forecasted Sales Volume from Winter's forecasting method*

Sheet +30% SalesVol
A1: Sales Volume Analysis: | B1: 0.3
B2: Year 0, Development | F2: Year 1, Projection | J2: Year 2, Projection | N2: Year 3, Projection | R2: Year 4, Projection
A3: Period | B3: 1 | C3: =B3+1 -> 2 | D3: =C3+1 -> 3 | E3: =D3+1 -> 4 | F3: =E3+1 -> 5 | G3: =F3+1 -> 6 | H3: =G3+1 -> 7 | I3: =H3+1 -> 8 | J3: =I3+1 -> 9 | ... U3: =T3+1 -> 20
A4: ($Value in thousands) | B4: Q1 | C4: Q2 | D4: Q3 | E4: Q4 | F4: Q1 | G4: Q2 | H4: Q3 | I4: Q4 | J4: Q1 | K4: Q2 | L4: Q3 | M4: Q4 | N4: Q1 | O4: Q2 | P4: Q3 | Q4: Q4 | R4: Q1 | S4: Q2 | T4: Q3 | U4: Q4
A6: Development Cost | B6: =(-1)*ScenarioParameters!$B$3/4*(1/1000) -> -15.12 | C6: =(-1)*ScenarioParameters!$B$3/4*(1/1000) -> -15.12 | D6: =(-1)*ScenarioParameters!$B$3/4*(1/1000) -> -15.12 | E6: =(-1)*ScenarioParameters!$B$3/4*(1/1000) -> -15.12
A7: Ramp-up cost | E7: =(-1)*ScenarioParameters!$B$6/2*(1/1000) -> -3.024 | F7: =(-1)*ScenarioParameters!$B$6/2*(1/1000) -> -3.024
A8: Marketing & support cost | F8: =(-1)*ScenarioParameters!$B$7/4*(1/1000) -> -210 | G8: =(-1)*ScenarioParameters!$B$7/4*(1/1000) -> -210 | H8: =(-1)*ScenarioParameters!$B$7/4*(1/1000) -> -210 | I8: =(-1)*ScenarioParameters!$B$7/4*(1/1000) -> -210 | J8: =(-1)*ScenarioParameters!$B$7/4*(1/1000) -> -210 | K8: =(-1)*ScenarioParameters!$B$7/4*(1/1000) -> -210 | L8: =(-1)*ScenarioParameters!$B$7/4*(1/1000) -> -210 | M8: =(-1)*ScenarioParameters!$B$7/4*(1/1000) -> -210 | ... U8: =(-1)*ScenarioParameters!$B$7/4*(1/1000) -> -210
A9: Production Cost | F9: =(-1)*(ScenarioParameters!$B$5)*ScenarioParameters!$G3*(1/1000) -> -358.17105 | G9: =(-1)*(ScenarioParameters!$B$5)*ScenarioParameters!$G4*(1/1000) -> -915.10143 | H9: =(-1)*(ScenarioParameters!$B$5)*ScenarioParameters!$G5*(1/1000) -> -710.166 | I9: =(-1)*(ScenarioParameters!$B$5)*ScenarioParameters!$G6*(1/1000) -> -1368.7099 | J9: =(-1)*(ScenarioParameters!$B$5)*ScenarioParameters!$G7*(1/1000) -> -751.42456 | K9: =(-1)*(ScenarioParameters!$B$5)*ScenarioParameters!$G8*(1/1000) -> -1496.0629 | L9: =(-1)*(ScenarioParameters!$B$5)*ScenarioParameters!$G9*(1/1000) -> -1010.0049 | M9: =(-1)*(ScenarioParameters!$B$5)*ScenarioParameters!$G10*(1/1000) -> -1796.7699 | N9: =(-1)*(ScenarioParameters!$B$5)*ScenarioParameters!$G11*(1/1000) -> -952.30836 | O9: =(-1)*(ScenarioParameters!$B$5)*ScenarioParameters!$G12*(1/1000) -> -1869.3415 | P9: =(-1)*(ScenarioParameters!$B$5)*ScenarioParameters!$G13*(1/1000) -> -1241.2506 | Q9: =(-1)*(ScenarioParameters!$B$5)*ScenarioParameters!$G14*(1/1000) -> -2183.9012 | R9: =(-1)*(ScenarioParameters!$B$5)*ScenarioParameters!$G15*(1/1000) -> -1166.5343 | S9: =(-1)*(ScenarioParameters!$B$5)*ScenarioParameters!$G16*(1/1000) -> -2267.4681 | T9: =(-1)*(ScenarioParameters!$B$5)*ScenarioParameters!$G17*(1/1000) -> -1492.2443 | U9: =(-1)*(ScenarioParameters!$B$5)*ScenarioParameters!$G18*(1/1000) -> -2604.2585
A10: Production volume | F10: =ScenarioParameters!$G3+ScenarioParameters!$G3*$B$1 -> 4039.0559 | G10: =ScenarioParameters!$G4+ScenarioParameters!$G4*$B$1 -> 10319.499 | H10: =ScenarioParameters!$G5+ScenarioParameters!$G5*$B$1 -> 8008.4646 | I10: =ScenarioParameters!$G6+ScenarioParameters!$G6*$B$1 -> 15434.792 | J10: =ScenarioParameters!$G7+ScenarioParameters!$G7*$B$1 -> 8473.7329 | K10: =ScenarioParameters!$G8+ScenarioParameters!$G8*$B$1 -> 16870.939 | L10: =ScenarioParameters!$G9+ScenarioParameters!$G9*$B$1 -> 11389.716 | M10: =ScenarioParameters!$G10+ScenarioParameters!$G10*$B$1 -> 20261.978 | N10: =ScenarioParameters!$G11+ScenarioParameters!$G11*$B$1 -> 10739.078 | O10: =ScenarioParameters!$G12+ScenarioParameters!$G12*$B$1 -> 21080.36 | P10: =ScenarioParameters!$G13+ScenarioParameters!$G13*$B$1 -> 13997.447 | Q10: =ScenarioParameters!$G14+ScenarioParameters!$G14*$B$1 -> 24627.616 | R10: =ScenarioParameters!$G15+ScenarioParameters!$G15*$B$1 -> 13154.881 | S10: =ScenarioParameters!$G16+ScenarioParameters!$G16*$B$1 -> 25569.99 | T10: =ScenarioParameters!$G17+ScenarioParameters!$G17*$B$1 -> 16827.876 | U10: =ScenarioParameters!$G18+ScenarioParameters!$G18*$B$1 -> 29367.939
A11: Unit product cost | F11: =F9/F10 -> -0.088676923 | G11: =G9/G10 -> -0.088676923 | H11: =H9/H10 -> -0.088676923 | I11: =I9/I10 -> -0.088676923 | J11: =J9/J10 -> -0.088676923 | K11: =K9/K10 -> -0.088676923 | L11: =L9/L10 -> -0.088676923 | M11: =M9/M10 -> -0.088676923 | ... U11: =U9/U10 -> -0.088676923
A12: Sales revenue | F12: =(ScenarioParameters!$B$4*F10)*(1/1000) -> 1207.6777 | G12: =(ScenarioParameters!$B$4*G10)*(1/1000) -> 3085.5302 | H12: =(ScenarioParameters!$B$4*H10)*(1/1000) -> 2394.5309 | I12: =(ScenarioParameters!$B$4*I10)*(1/1000) -> 4615.0029 | J12: =(ScenarioParameters!$B$4*J10)*(1/1000) -> 2533.6461 | K12: =(ScenarioParameters!$B$4*K10)*(1/1000) -> 5044.4107 | L12: =(ScenarioParameters!$B$4*L10)*(1/1000) -> 3405.525 | M12: =(ScenarioParameters!$B$4*M10)*(1/1000) -> 6058.3315 | ... U12: =(ScenarioParameters!$B$4*U10)*(1/1000) -> 8781.0139
A13: Forecasted Sales Volume | F13: =F$10 -> 4039.0559 | G13: =G$10 -> 10319.499 | H13: =H$10 -> 8008.4646 | I13: =I$10 -> 15434.792 | J13: =J$10 -> 8473.7329 | K13: =K$10 -> 16870.939 | L13: =L$10 -> 11389.716 | M13: =M$10 -> 20261.978 | ... U13: =U$10 -> 29367.939
A14: Unit price | F14: =F$12/F$13 -> 0.299 | G14: =G$12/G$13 -> 0.299 | H14: =H$12/H$13 -> 0.299 | I14: =I$12/I$13 -> 0.299 | J14: =J$12/J$13 -> 0.299 | K14: =K$12/K$13 -> 0.299 | L14: =L$12/L$13 -> 0.299 | M14: =M$12/M$13 -> 0.299 | ... U14: =U$12/U$13 -> 0.299
A16: Period Cash Flow | B16: =SUM(B6+B7+B8+B9+B12) -> -15.12 | C16: =SUM(C6+C7+C8+C9+C12) -> -15.12 | D16: =SUM(D6+D7+D8+D9+D12) -> -15.12 | E16: =SUM(E6+E7+E8+E9+E12) -> -18.144 | F16: =SUM(F6+F7+F8+F9+F12) -> 636.48266 | G16: =SUM(G6+G7+G8+G9+G12) -> 1960.4288 | H16: =SUM(H6+H7+H8+H9+H12) -> 1474.3649 | I16: =SUM(I6+I7+I8+I9+I12) -> 3036.293 | ... U16: =SUM(U6+U7+U8+U9+U12) -> 5966.7554
A17: Unit Price | B17: =B16 -> -15.12 | C17: =C16/(1+(ScenarioParameters!$B$8/100)/4)^B3 -> -14.859951 | D17: =D16/(1+(ScenarioParameters!$B$8/100)/4)^C3 -> -14.604374 | E17: =E16/(1+(ScenarioParameters!$B$8/100)/4)^D3 -> -17.223832 | F17: =F16/(1+(ScenarioParameters!$B$8/100)/4)^E3 -> 593.81191 | G17: =G16/(1+(ScenarioParameters!$B$8/100)/4)^F3 -> 1797.5417 | H17: =H16/(1+(ScenarioParameters!$B$8/100)/4)^G3 -> 1328.6129 | I17: =I16/(1+(ScenarioParameters!$B$8/100)/4)^H3 -> 2689.074 | J17: =J16/(1+(ScenarioParameters!$B$8/100)/4)^I3 -> 1368.4799 | ... U17: =U16/(1+(ScenarioParameters!$B$8/100)/4)^T3 -> 4291.2547
A19: Project NVP | B19: =SUM(B17:U17) -> 39279.221
A21: Forecasted Sales Volume from Winter's forecasting method*

Sheet -30% SalesVol
A1: Sales Volume Analysis: | B1: -0.3
B2: Year 0, Development | F2: Year 1, Projection | J2: Year 2, Projection | N2: Year 3, Projection | R2: Year 4, Projection
A3: Period | B3: 1 | C3: =B3+1 -> 2 | D3: =C3+1 -> 3 | E3: =D3+1 -> 4 | F3: =E3+1 -> 5 | G3: =F3+1 -> 6 | H3: =G3+1 -> 7 | I3: =H3+1 -> 8 | J3: =I3+1 -> 9 | ... U3: =T3+1 -> 20
A4: ($Value in thousands) | B4: Q1 | C4: Q2 | D4: Q3 | E4: Q4 | F4: Q1 | G4: Q2 | H4: Q3 | I4: Q4 | J4: Q1 | K4: Q2 | L4: Q3 | M4: Q4 | N4: Q1 | O4: Q2 | P4: Q3 | Q4: Q4 | R4: Q1 | S4: Q2 | T4: Q3 | U4: Q4
A6: Development Cost | B6: =(-1)*ScenarioParameters!$B$3/4*(1/1000) -> -15.12 | C6: =(-1)*ScenarioParameters!$B$3/4*(1/1000) -> -15.12 | D6: =(-1)*ScenarioParameters!$B$3/4*(1/1000) -> -15.12 | E6: =(-1)*ScenarioParameters!$B$3/4*(1/1000) -> -15.12
A7: Ramp-up cost | E7: =(-1)*ScenarioParameters!$B$6/2*(1/1000) -> -3.024 | F7: =(-1)*ScenarioParameters!$B$6/2*(1/1000) -> -3.024
A8: Marketing & support cost | F8: =(-1)*ScenarioParameters!$B$7/4*(1/1000) -> -210 | G8: =(-1)*ScenarioParameters!$B$7/4*(1/1000) -> -210 | H8: =(-1)*ScenarioParameters!$B$7/4*(1/1000) -> -210 | I8: =(-1)*ScenarioParameters!$B$7/4*(1/1000) -> -210 | J8: =(-1)*ScenarioParameters!$B$7/4*(1/1000) -> -210 | K8: =(-1)*ScenarioParameters!$B$7/4*(1/1000) -> -210 | L8: =(-1)*ScenarioParameters!$B$7/4*(1/1000) -> -210 | M8: =(-1)*ScenarioParameters!$B$7/4*(1/1000) -> -210 | ... U8: =(-1)*ScenarioParameters!$B$7/4*(1/1000) -> -210
A9: Production Cost | F9: =(-1)*(ScenarioParameters!$B$5)*ScenarioParameters!$G3*(1/1000) -> -358.17105 | G9: =(-1)*(ScenarioParameters!$B$5)*ScenarioParameters!$G4*(1/1000) -> -915.10143 | H9: =(-1)*(ScenarioParameters!$B$5)*ScenarioParameters!$G5*(1/1000) -> -710.166 | I9: =(-1)*(ScenarioParameters!$B$5)*ScenarioParameters!$G6*(1/1000) -> -1368.7099 | J9: =(-1)*(ScenarioParameters!$B$5)*ScenarioParameters!$G7*(1/1000) -> -751.42456 | K9: =(-1)*(ScenarioParameters!$B$5)*ScenarioParameters!$G8*(1/1000) -> -1496.0629 | L9: =(-1)*(ScenarioParameters!$B$5)*ScenarioParameters!$G9*(1/1000) -> -1010.0049 | M9: =(-1)*(ScenarioParameters!$B$5)*ScenarioParameters!$G10*(1/1000) -> -1796.7699 | N9: =(-1)*(ScenarioParameters!$B$5)*ScenarioParameters!$G11*(1/1000) -> -952.30836 | O9: =(-1)*(ScenarioParameters!$B$5)*ScenarioParameters!$G12*(1/1000) -> -1869.3415 | P9: =(-1)*(ScenarioParameters!$B$5)*ScenarioParameters!$G13*(1/1000) -> -1241.2506 | Q9: =(-1)*(ScenarioParameters!$B$5)*ScenarioParameters!$G14*(1/1000) -> -2183.9012 | R9: =(-1)*(ScenarioParameters!$B$5)*ScenarioParameters!$G15*(1/1000) -> -1166.5343 | S9: =(-1)*(ScenarioParameters!$B$5)*ScenarioParameters!$G16*(1/1000) -> -2267.4681 | T9: =(-1)*(ScenarioParameters!$B$5)*ScenarioParameters!$G17*(1/1000) -> -1492.2443 | U9: =(-1)*(ScenarioParameters!$B$5)*ScenarioParameters!$G18*(1/1000) -> -2604.2585
A10: Production volume | F10: =ScenarioParameters!$G3+ScenarioParameters!$G3*$B$1 -> 2174.8762 | G10: =ScenarioParameters!$G4+ScenarioParameters!$G4*$B$1 -> 5556.6534 | H10: =ScenarioParameters!$G5+ScenarioParameters!$G5*$B$1 -> 4312.2502 | I10: =ScenarioParameters!$G6+ScenarioParameters!$G6*$B$1 -> 8311.042 | J10: =ScenarioParameters!$G7+ScenarioParameters!$G7*$B$1 -> 4562.7793 | K10: =ScenarioParameters!$G8+ScenarioParameters!$G8*$B$1 -> 9084.3517 | L10: =ScenarioParameters!$G9+ScenarioParameters!$G9*$B$1 -> 6132.9238 | M10: =ScenarioParameters!$G10+ScenarioParameters!$G10*$B$1 -> 10910.296 | N10: =ScenarioParameters!$G11+ScenarioParameters!$G11*$B$1 -> 5782.5802 | O10: =ScenarioParameters!$G12+ScenarioParameters!$G12*$B$1 -> 11350.963 | P10: =ScenarioParameters!$G13+ScenarioParameters!$G13*$B$1 -> 7537.0871 | Q10: =ScenarioParameters!$G14+ScenarioParameters!$G14*$B$1 -> 13261.024 | R10: =ScenarioParameters!$G15+ScenarioParameters!$G15*$B$1 -> 7083.3972 | S10: =ScenarioParameters!$G16+ScenarioParameters!$G16*$B$1 -> 13768.456 | T10: =ScenarioParameters!$G17+ScenarioParameters!$G17*$B$1 -> 9061.1642 | U10: =ScenarioParameters!$G18+ScenarioParameters!$G18*$B$1 -> 15813.506
A11: Unit product cost | F11: =F9/F10 -> -0.16468571 | G11: =G9/G10 -> -0.16468571 | H11: =H9/H10 -> -0.16468571 | I11: =I9/I10 -> -0.16468571 | J11: =J9/J10 -> -0.16468571 | K11: =K9/K10 -> -0.16468571 | L11: =L9/L10 -> -0.16468571 | M11: =M9/M10 -> -0.16468571 | ... U11: =U9/U10 -> -0.16468571
A12: Sales revenue | F12: =(ScenarioParameters!$B$4*F10)*(1/1000) -> 650.288 | G12: =(ScenarioParameters!$B$4*G10)*(1/1000) -> 1661.4394 | H12: =(ScenarioParameters!$B$4*H10)*(1/1000) -> 1289.3628 | I12: =(ScenarioParameters!$B$4*I10)*(1/1000) -> 2485.0015 | J12: =(ScenarioParameters!$B$4*J10)*(1/1000) -> 1364.271 | K12: =(ScenarioParameters!$B$4*K10)*(1/1000) -> 2716.2211 | L12: =(ScenarioParameters!$B$4*L10)*(1/1000) -> 1833.7442 | M12: =(ScenarioParameters!$B$4*M10)*(1/1000) -> 3262.1785 | ... U12: =(ScenarioParameters!$B$4*U10)*(1/1000) -> 4728.2382
A13: Forecasted Sales Volume | F13: =F$10 -> 2174.8762 | G13: =G$10 -> 5556.6534 | H13: =H$10 -> 4312.2502 | I13: =I$10 -> 8311.042 | J13: =J$10 -> 4562.7793 | K13: =K$10 -> 9084.3517 | L13: =L$10 -> 6132.9238 | M13: =M$10 -> 10910.296 | ... U13: =U$10 -> 15813.506
A14: Unit price | F14: =F$12/F$13 -> 0.299 | G14: =G$12/G$13 -> 0.299 | H14: =H$12/H$13 -> 0.299 | I14: =I$12/I$13 -> 0.299 | J14: =J$12/J$13 -> 0.299 | K14: =K$12/K$13 -> 0.299 | L14: =L$12/L$13 -> 0.299 | M14: =M$12/M$13 -> 0.299 | ... U14: =U$12/U$13 -> 0.299
A16: Period Cash Flow | B16: =SUM(B6+B7+B8+B9+B12) -> -15.12 | C16: =SUM(C6+C7+C8+C9+C12) -> -15.12 | D16: =SUM(D6+D7+D8+D9+D12) -> -15.12 | E16: =SUM(E6+E7+E8+E9+E12) -> -18.144 | F16: =SUM(F6+F7+F8+F9+F12) -> 79.09295 | G16: =SUM(G6+G7+G8+G9+G12) -> 536.33793 | H16: =SUM(H6+H7+H8+H9+H12) -> 369.1968 | I16: =SUM(I6+I7+I8+I9+I12) -> 906.29167 | ... U16: =SUM(U6+U7+U8+U9+U12) -> 1913.9797
A17: Unit Price | B17: =B16 -> -15.12 | C17: =C16/(1+(ScenarioParameters!$B$8/100)/4)^B3 -> -14.859951 | D17: =D16/(1+(ScenarioParameters!$B$8/100)/4)^C3 -> -14.604374 | E17: =E16/(1+(ScenarioParameters!$B$8/100)/4)^D3 -> -17.223832 | F17: =F16/(1+(ScenarioParameters!$B$8/100)/4)^E3 -> 73.79044 | G17: =G16/(1+(ScenarioParameters!$B$8/100)/4)^F3 -> 491.77497 | H17: =H16/(1+(ScenarioParameters!$B$8/100)/4)^G3 -> 332.69894 | I17: =I16/(1+(ScenarioParameters!$B$8/100)/4)^H3 -> 802.65157 | J17: =J16/(1+(ScenarioParameters!$B$8/100)/4)^I3 -> 350.6422 | ... U17: =U16/(1+(ScenarioParameters!$B$8/100)/4)^T3 -> 1376.5228
A19: Project NVP | B19: =SUM(B17:U17) -> 11652.759
A21: Forecasted Sales Volume from Winter's forecasting method*

Sheet SalesVolume_Sensitivity
A1: Base Sales, Qty | B1: Change in Sales Volume (%) | C1: Sales Volume (Qty) | D1: Change in Sales Volume (Qty) | E1: Change in NPV, % | F1: NPV, $ Thousands | G1: Change in NPV, $ Thousands
A2: =BaseCase!B19 -> 25465.99 | B2: 0.3 | C2: =SUM('+30% SalesVol'!$F$10:Z$10) -> 250163.37 | D2: =C2-$C$5 -> 57730.007 | E2: =(F2-$F$5)/$F$5 -> 0.54241877 | F2: ='+30% SalesVol'!$B$19 -> 39279.221 | G2: =F2-$F$5 -> 13813.231
A3: =A2 -> 25465.99 | B3: 0.2 | C3: =SUM('+20% SalesVol'!$F$10:Z$10) -> 230920.03 | D3: =C3-$C$5 -> 38486.672 | E3: =(F3-$F$5)/$F$5 -> 0.36161252 | F3: ='+20% SalesVol'!$B$19 -> 34674.811 | G3: =F3-$F$5 -> 9208.8207
A4: =A3 -> 25465.99 | B4: 0.1 | C4: =SUM('+10% SalesVol'!$F$10:Z$10) -> 211676.69 | D4: =C4-$C$5 -> 19243.336 | E4: =(F4-$F$5)/$F$5 -> 0.18080626 | F4: ='+10% SalesVol'!$B$19 -> 30070.4 | G4: =F4-$F$5 -> 4604.4103
A5: =A4 -> 25465.99 | B5: 0 | C5: =SUM(BaseCase!$F$10:Z$10) -> 192433.36 | D5: =C5-$C$5 -> 0 | E5: =(F5-$F$5)/$F$5 -> 0 | F5: =BaseCase!B19 -> 25465.99 | G5: =F5-$F$5 -> 0
A6: =A5 -> 25465.99 | B6: -0.1 | C6: =SUM('-10% SalesVol'!$F$10:Z$10) -> 173190.02 | D6: =C6-$C$5 -> -19243.336 | E6: =(F6-$F$5)/$F$5 -> -0.18080626 | F6: ='-10% SalesVol'!$B$19 -> 20861.58 | G6: =F6-$F$5 -> -4604.4103
A7: =A6 -> 25465.99 | B7: -0.2 | C7: =SUM('-20% SalesVol'!$F$10:Z$10) -> 153946.69 | D7: =C7-$C$5 -> -38486.672 | E7: =(F7-$F$5)/$F$5 -> -0.36161252 | F7: ='-20% SalesVol'!$B$19 -> 16257.169 | G7: =F7-$F$5 -> -9208.8207
A8: =A7 -> 25465.99 | B8: -0.3 | C8: =SUM('-30% SalesVol'!$F$10:Z$10) -> 134703.35 | D8: =C8-$C$5 -> -57730.007 | E8: =(F8-$F$5)/$F$5 -> -0.54241877 | F8: ='-30% SalesVol'!$B$19 -> 11652.759 | G8: =F8-$F$5 -> -13813.231

Sheet DevelopmentCost_Sensitivity
A1: Base Dev Cost, $ | B1: Change in Development Cost, % | C1: Development Cost, $ | D1: Change in Development Cost, $ | E1: NPV, $ Thousands | F1: Change in NPV, % | G1: Change in NPV, $ Thousands
A2: =ScenarioParameters!$B$3 -> 60480 | B2: 0.3 | C2: =A2*(1+B2) -> 78624 | D2: =C2-A2 -> 18144 | E2: ='+30% DevCost'!$B$19 -> 25448.309 | F2: =(E2-$E$5)/$E$5 -> -0.00069430859 | G2: =E2-$E$5*1 -> -17.681256
A3: =ScenarioParameters!$B$3 -> 60480 | B3: 0.2 | C3: =A3*(1+B3) -> 72576 | D3: =C3-A3 -> 12096 | E3: ='+20% DevCost'!$B$19 -> 25454.202 | F3: =(E3-$E$5)/$E$5 -> -0.00046287239 | G3: =E3-$E$5 -> -11.787504
A4: =ScenarioParameters!$B$3 -> 60480 | B4: 0.1 | C4: =A4*(1+B4) -> 66528 | D4: =C4-A4 -> 6048 | E4: ='+10% DevCost'!$B$19 -> 25460.096 | F4: =(E4-$E$5)/$E$5 -> -0.0002314362 | G4: =E4-$E$5 -> -5.8937519
A5: =ScenarioParameters!$B$3 -> 60480 | B5: 0 | C5: =A5*(1+B5) -> 60480 | D5: =C5-A5 -> 0 | E5: =BaseCase!B19 -> 25465.99 | F5: =(E5-$E$5)/$E$5 -> 0 | G5: =E5-$E$5 -> 0
A6: =ScenarioParameters!$B$3 -> 60480 | B6: -0.1 | C6: =A6*(1+B6) -> 54432 | D6: =C6-A6 -> -6048 | E6: ='-10% DevCost'!$B$19 -> 25471.884 | F6: =(E6-$E$5)/$E$5 -> 0.0002314362 | G6: =E6-$E$5 -> 5.8937519
A7: =ScenarioParameters!$B$3 -> 60480 | B7: -0.2 | C7: =A7*(1+B7) -> 48384 | D7: =C7-A7 -> -12096 | E7: ='-20% DevCost'!$B$19 -> 25477.777 | F7: =(E7-$E$5)/$E$5 -> 0.00046287239 | G7: =E7-$E$5 -> 11.787504
A8: =ScenarioParameters!$B$3 -> 60480 | B8: -0.3 | C8: =A8*(1+B8) -> 42336 | D8: =C8-A8 -> -18144 | E8: ='-30% DevCost'!$B$19 -> 25483.671 | F8: =(E8-$E$5)/$E$5 -> 0.00069430859 | G8: =E8-$E$5 -> 17.681256

Sheet +10% DevCost
A1: Development Cost Analysis: | B1: 0.1
B2: Year 0, Development | F2: Year 1, Projection | J2: Year 2, Projection | N2: Year 3, Projection | R2: Year 4, Projection
A3: Period | B3: 1 | C3: =B3+1 -> 2 | D3: =C3+1 -> 3 | E3: =D3+1 -> 4 | F3: =E3+1 -> 5 | G3: =F3+1 -> 6 | H3: =G3+1 -> 7 | I3: =H3+1 -> 8 | J3: =I3+1 -> 9 | ... U3: =T3+1 -> 20
A4: ($Value in thousands) | B4: Q1 | C4: Q2 | D4: Q3 | E4: Q4 | F4: Q1 | G4: Q2 | H4: Q3 | I4: Q4 | J4: Q1 | K4: Q2 | L4: Q3 | M4: Q4 | N4: Q1 | O4: Q2 | P4: Q3 | Q4: Q4 | R4: Q1 | S4: Q2 | T4: Q3 | U4: Q4
A6: Development Cost | B6: =(-1)*ScenarioParameters!$B$3/4*(1/1000)*(1+$B$1) -> -16.632 | C6: =(-1)*ScenarioParameters!$B$3/4*(1/1000)*(1+$B$1) -> -16.632 | D6: =(-1)*ScenarioParameters!$B$3/4*(1/1000)*(1+$B$1) -> -16.632 | E6: =(-1)*ScenarioParameters!$B$3/4*(1/1000)*(1+$B$1) -> -16.632
A7: Ramp-up cost | E7: =(-1)*ScenarioParameters!$B$6/2*(1/1000) -> -3.024 | F7: =(-1)*ScenarioParameters!$B$6/2*(1/1000) -> -3.024
A8: Marketing & support cost | F8: =(-1)*ScenarioParameters!$B$7/4*(1/1000) -> -210 | G8: =(-1)*ScenarioParameters!$B$7/4*(1/1000) -> -210 | H8: =(-1)*ScenarioParameters!$B$7/4*(1/1000) -> -210 | I8: =(-1)*ScenarioParameters!$B$7/4*(1/1000) -> -210 | J8: =(-1)*ScenarioParameters!$B$7/4*(1/1000) -> -210 | K8: =(-1)*ScenarioParameters!$B$7/4*(1/1000) -> -210 | L8: =(-1)*ScenarioParameters!$B$7/4*(1/1000) -> -210 | M8: =(-1)*ScenarioParameters!$B$7/4*(1/1000) -> -210 | ... U8: =(-1)*ScenarioParameters!$B$7/4*(1/1000) -> -210
A9: Production Cost | F9: =(-1)*(ScenarioParameters!$B$5)*ScenarioParameters!$G3*(1/1000) -> -358.17105 | G9: =(-1)*(ScenarioParameters!$B$5)*ScenarioParameters!$G4*(1/1000) -> -915.10143 | H9: =(-1)*(ScenarioParameters!$B$5)*ScenarioParameters!$G5*(1/1000) -> -710.166 | I9: =(-1)*(ScenarioParameters!$B$5)*ScenarioParameters!$G6*(1/1000) -> -1368.7099 | J9: =(-1)*(ScenarioParameters!$B$5)*ScenarioParameters!$G7*(1/1000) -> -751.42456 | K9: =(-1)*(ScenarioParameters!$B$5)*ScenarioParameters!$G8*(1/1000) -> -1496.0629 | L9: =(-1)*(ScenarioParameters!$B$5)*ScenarioParameters!$G9*(1/1000) -> -1010.0049 | M9: =(-1)*(ScenarioParameters!$B$5)*ScenarioParameters!$G10*(1/1000) -> -1796.7699 | N9: =(-1)*(ScenarioParameters!$B$5)*ScenarioParameters!$G11*(1/1000) -> -952.30836 | O9: =(-1)*(ScenarioParameters!$B$5)*ScenarioParameters!$G12*(1/1000) -> -1869.3415 | P9: =(-1)*(ScenarioParameters!$B$5)*ScenarioParameters!$G13*(1/1000) -> -1241.2506 | Q9: =(-1)*(ScenarioParameters!$B$5)*ScenarioParameters!$G14*(1/1000) -> -2183.9012 | R9: =(-1)*(ScenarioParameters!$B$5)*ScenarioParameters!$G15*(1/1000) -> -1166.5343 | S9: =(-1)*(ScenarioParameters!$B$5)*ScenarioParameters!$G16*(1/1000) -> -2267.4681 | T9: =(-1)*(ScenarioParameters!$B$5)*ScenarioParameters!$G17*(1/1000) -> -1492.2443 | U9: =(-1)*(ScenarioParameters!$B$5)*ScenarioParameters!$G18*(1/1000) -> -2604.2585
A10: Production volume | F10: =ScenarioParameters!$G3 -> 3106.9661 | G10: =ScenarioParameters!$G4 -> 7938.0762 | H10: =ScenarioParameters!$G5 -> 6160.3574 | I10: =ScenarioParameters!$G6 -> 11872.917 | J10: =ScenarioParameters!$G7 -> 6518.2561 | K10: =ScenarioParameters!$G8 -> 12977.645 | L10: =ScenarioParameters!$G9 -> 8761.3198 | M10: =ScenarioParameters!$G10 -> 15586.137 | N10: =ScenarioParameters!$G11 -> 8260.8289 | O10: =ScenarioParameters!$G12 -> 16215.662 | P10: =ScenarioParameters!$G13 -> 10767.267 | Q10: =ScenarioParameters!$G14 -> 18944.32 | R10: =ScenarioParameters!$G15 -> 10119.139 | S10: =ScenarioParameters!$G16 -> 19669.223 | T10: =ScenarioParameters!$G17 -> 12944.52 | U10: =ScenarioParameters!$G18 -> 22590.723
A11: Unit product cost | F11: =F9/F10 -> -0.11528 | G11: =G9/G10 -> -0.11528 | H11: =H9/H10 -> -0.11528 | I11: =I9/I10 -> -0.11528 | J11: =J9/J10 -> -0.11528 | K11: =K9/K10 -> -0.11528 | L11: =L9/L10 -> -0.11528 | M11: =M9/M10 -> -0.11528 | ... U11: =U9/U10 -> -0.11528
A12: Sales revenue | F12: =(ScenarioParameters!$B$4*F10)*(1/1000) -> 928.98285 | G12: =(ScenarioParameters!$B$4*G10)*(1/1000) -> 2373.4848 | H12: =(ScenarioParameters!$B$4*H10)*(1/1000) -> 1841.9469 | I12: =(ScenarioParameters!$B$4*I10)*(1/1000) -> 3550.0022 | J12: =(ScenarioParameters!$B$4*J10)*(1/1000) -> 1948.9586 | K12: =(ScenarioParameters!$B$4*K10)*(1/1000) -> 3880.3159 | L12: =(ScenarioParameters!$B$4*L10)*(1/1000) -> 2619.6346 | M12: =(ScenarioParameters!$B$4*M10)*(1/1000) -> 4660.255 | ... U12: =(ScenarioParameters!$B$4*U10)*(1/1000) -> 6754.626
A13: Forecasted Sales Volume | F13: =F$10 -> 3106.9661 | G13: =G$10 -> 7938.0762 | H13: =H$10 -> 6160.3574 | I13: =I$10 -> 11872.917 | J13: =J$10 -> 6518.2561 | K13: =K$10 -> 12977.645 | L13: =L$10 -> 8761.3198 | M13: =M$10 -> 15586.137 | ... U13: =U$10 -> 22590.723
A14: Unit price | F14: =F$12/F$13 -> 0.299 | G14: =G$12/G$13 -> 0.299 | H14: =H$12/H$13 -> 0.299 | I14: =I$12/I$13 -> 0.299 | J14: =J$12/J$13 -> 0.299 | K14: =K$12/K$13 -> 0.299 | L14: =L$12/L$13 -> 0.299 | M14: =M$12/M$13 -> 0.299 | ... U14: =U$12/U$13 -> 0.299
A16: Period Cash Flow | B16: =SUM(B6+B7+B8+B9+B12) -> -16.632 | C16: =SUM(C6+C7+C8+C9+C12) -> -16.632 | D16: =SUM(D6+D7+D8+D9+D12) -> -16.632 | E16: =SUM(E6+E7+E8+E9+E12) -> -19.656 | F16: =SUM(F6+F7+F8+F9+F12) -> 357.78781 | G16: =SUM(G6+G7+G8+G9+G12) -> 1248.3834 | H16: =SUM(H6+H7+H8+H9+H12) -> 921.78086 | I16: =SUM(I6+I7+I8+I9+I12) -> 1971.2923 | ... U16: =SUM(U6+U7+U8+U9+U12) -> 3940.3675
A17: Unit Price | B17: =B16 -> -16.632 | C17: =C16/(1+(ScenarioParameters!$B$8/100)/4)^B3 -> -16.345946 | D17: =D16/(1+(ScenarioParameters!$B$8/100)/4)^C3 -> -16.064812 | E17: =E16/(1+(ScenarioParameters!$B$8/100)/4)^D3 -> -18.659151 | F17: =F16/(1+(ScenarioParameters!$B$8/100)/4)^E3 -> 333.80118 | G17: =G16/(1+(ScenarioParameters!$B$8/100)/4)^F3 -> 1144.6584 | H17: =H16/(1+(ScenarioParameters!$B$8/100)/4)^G3 -> 830.65594 | I17: =I16/(1+(ScenarioParameters!$B$8/100)/4)^H3 -> 1745.8628 | J17: =J16/(1+(ScenarioParameters!$B$8/100)/4)^I3 -> 859.56103 | ... U17: =U16/(1+(ScenarioParameters!$B$8/100)/4)^T3 -> 2833.8887
A19: Project NVP | B19: =SUM(B17:U17) -> 25460.096
A21: Forecasted Sales Volume from Winter's forecasting method*

Sheet -10% DevCost
A1: Development Cost Analysis: | B1: -0.1
B2: Year 0, Development | F2: Year 1, Projection | J2: Year 2, Projection | N2: Year 3, Projection | R2: Year 4, Projection
A3: Period | B3: 1 | C3: =B3+1 -> 2 | D3: =C3+1 -> 3 | E3: =D3+1 -> 4 | F3: =E3+1 -> 5 | G3: =F3+1 -> 6 | H3: =G3+1 -> 7 | I3: =H3+1 -> 8 | J3: =I3+1 -> 9 | ... U3: =T3+1 -> 20
A4: ($Value in thousands) | B4: Q1 | C4: Q2 | D4: Q3 | E4: Q4 | F4: Q1 | G4: Q2 | H4: Q3 | I4: Q4 | J4: Q1 | K4: Q2 | L4: Q3 | M4: Q4 | N4: Q1 | O4: Q2 | P4: Q3 | Q4: Q4 | R4: Q1 | S4: Q2 | T4: Q3 | U4: Q4
A6: Development Cost | B6: =(-1)*ScenarioParameters!$B$3/4*(1/1000)*(1+$B$1) -> -13.608 | C6: =(-1)*ScenarioParameters!$B$3/4*(1/1000)*(1+$B$1) -> -13.608 | D6: =(-1)*ScenarioParameters!$B$3/4*(1/1000)*(1+$B$1) -> -13.608 | E6: =(-1)*ScenarioParameters!$B$3/4*(1/1000)*(1+$B$1) -> -13.608
A7: Ramp-up cost | E7: =(-1)*ScenarioParameters!$B$6/2*(1/1000) -> -3.024 | F7: =(-1)*ScenarioParameters!$B$6/2*(1/1000) -> -3.024
A8: Marketing & support cost | F8: =(-1)*ScenarioParameters!$B$7/4*(1/1000) -> -210 | G8: =(-1)*ScenarioParameters!$B$7/4*(1/1000) -> -210 | H8: =(-1)*ScenarioParameters!$B$7/4*(1/1000) -> -210 | I8: =(-1)*ScenarioParameters!$B$7/4*(1/1000) -> -210 | J8: =(-1)*ScenarioParameters!$B$7/4*(1/1000) -> -210 | K8: =(-1)*ScenarioParameters!$B$7/4*(1/1000) -> -210 | L8: =(-1)*ScenarioParameters!$B$7/4*(1/1000) -> -210 | M8: =(-1)*ScenarioParameters!$B$7/4*(1/1000) -> -210 | ... U8: =(-1)*ScenarioParameters!$B$7/4*(1/1000) -> -210
A9: Production Cost | F9: =(-1)*(ScenarioParameters!$B$5)*ScenarioParameters!$G3*(1/1000) -> -358.17105 | G9: =(-1)*(ScenarioParameters!$B$5)*ScenarioParameters!$G4*(1/1000) -> -915.10143 | H9: =(-1)*(ScenarioParameters!$B$5)*ScenarioParameters!$G5*(1/1000) -> -710.166 | I9: =(-1)*(ScenarioParameters!$B$5)*ScenarioParameters!$G6*(1/1000) -> -1368.7099 | J9: =(-1)*(ScenarioParameters!$B$5)*ScenarioParameters!$G7*(1/1000) -> -751.42456 | K9: =(-1)*(ScenarioParameters!$B$5)*ScenarioParameters!$G8*(1/1000) -> -1496.0629 | L9: =(-1)*(ScenarioParameters!$B$5)*ScenarioParameters!$G9*(1/1000) -> -1010.0049 | M9: =(-1)*(ScenarioParameters!$B$5)*ScenarioParameters!$G10*(1/1000) -> -1796.7699 | N9: =(-1)*(ScenarioParameters!$B$5)*ScenarioParameters!$G11*(1/1000) -> -952.30836 | O9: =(-1)*(ScenarioParameters!$B$5)*ScenarioParameters!$G12*(1/1000) -> -1869.3415 | P9: =(-1)*(ScenarioParameters!$B$5)*ScenarioParameters!$G13*(1/1000) -> -1241.2506 | Q9: =(-1)*(ScenarioParameters!$B$5)*ScenarioParameters!$G14*(1/1000) -> -2183.9012 | R9: =(-1)*(ScenarioParameters!$B$5)*ScenarioParameters!$G15*(1/1000) -> -1166.5343 | S9: =(-1)*(ScenarioParameters!$B$5)*ScenarioParameters!$G16*(1/1000) -> -2267.4681 | T9: =(-1)*(ScenarioParameters!$B$5)*ScenarioParameters!$G17*(1/1000) -> -1492.2443 | U9: =(-1)*(ScenarioParameters!$B$5)*ScenarioParameters!$G18*(1/1000) -> -2604.2585
A10: Production volume | F10: =ScenarioParameters!$G3 -> 3106.9661 | G10: =ScenarioParameters!$G4 -> 7938.0762 | H10: =ScenarioParameters!$G5 -> 6160.3574 | I10: =ScenarioParameters!$G6 -> 11872.917 | J10: =ScenarioParameters!$G7 -> 6518.2561 | K10: =ScenarioParameters!$G8 -> 12977.645 | L10: =ScenarioParameters!$G9 -> 8761.3198 | M10: =ScenarioParameters!$G10 -> 15586.137 | N10: =ScenarioParameters!$G11 -> 8260.8289 | O10: =ScenarioParameters!$G12 -> 16215.662 | P10: =ScenarioParameters!$G13 -> 10767.267 | Q10: =ScenarioParameters!$G14 -> 18944.32 | R10: =ScenarioParameters!$G15 -> 10119.139 | S10: =ScenarioParameters!$G16 -> 19669.223 | T10: =ScenarioParameters!$G17 -> 12944.52 | U10: =ScenarioParameters!$G18 -> 22590.723
A11: Unit product cost | F11: =F9/F10 -> -0.11528 | G11: =G9/G10 -> -0.11528 | H11: =H9/H10 -> -0.11528 | I11: =I9/I10 -> -0.11528 | J11: =J9/J10 -> -0.11528 | K11: =K9/K10 -> -0.11528 | L11: =L9/L10 -> -0.11528 | M11: =M9/M10 -> -0.11528 | ... U11: =U9/U10 -> -0.11528
A12: Sales revenue | F12: =(ScenarioParameters!$B$4*F10)*(1/1000) -> 928.98285 | G12: =(ScenarioParameters!$B$4*G10)*(1/1000) -> 2373.4848 | H12: =(ScenarioParameters!$B$4*H10)*(1/1000) -> 1841.9469 | I12: =(ScenarioParameters!$B$4*I10)*(1/1000) -> 3550.0022 | J12: =(ScenarioParameters!$B$4*J10)*(1/1000) -> 1948.9586 | K12: =(ScenarioParameters!$B$4*K10)*(1/1000) -> 3880.3159 | L12: =(ScenarioParameters!$B$4*L10)*(1/1000) -> 2619.6346 | M12: =(ScenarioParameters!$B$4*M10)*(1/1000) -> 4660.255 | ... U12: =(ScenarioParameters!$B$4*U10)*(1/1000) -> 6754.626
A13: Forecasted Sales Volume | F13: =F$10 -> 3106.9661 | G13: =G$10 -> 7938.0762 | H13: =H$10 -> 6160.3574 | I13: =I$10 -> 11872.917 | J13: =J$10 -> 6518.2561 | K13: =K$10 -> 12977.645 | L13: =L$10 -> 8761.3198 | M13: =M$10 -> 15586.137 | ... U13: =U$10 -> 22590.723
A14: Unit price | F14: =F$12/F$13 -> 0.299 | G14: =G$12/G$13 -> 0.299 | H14: =H$12/H$13 -> 0.299 | I14: =I$12/I$13 -> 0.299 | J14: =J$12/J$13 -> 0.299 | K14: =K$12/K$13 -> 0.299 | L14: =L$12/L$13 -> 0.299 | M14: =M$12/M$13 -> 0.299 | ... U14: =U$12/U$13 -> 0.299
A16: Period Cash Flow | B16: =SUM(B6+B7+B8+B9+B12) -> -13.608 | C16: =SUM(C6+C7+C8+C9+C12) -> -13.608 | D16: =SUM(D6+D7+D8+D9+D12) -> -13.608 | E16: =SUM(E6+E7+E8+E9+E12) -> -16.632 | F16: =SUM(F6+F7+F8+F9+F12) -> 357.78781 | G16: =SUM(G6+G7+G8+G9+G12) -> 1248.3834 | H16: =SUM(H6+H7+H8+H9+H12) -> 921.78086 | I16: =SUM(I6+I7+I8+I9+I12) -> 1971.2923 | ... U16: =SUM(U6+U7+U8+U9+U12) -> 3940.3675
A17: Unit Price | B17: =B16 -> -13.608 | C17: =C16/(1+(ScenarioParameters!$B$8/100)/4)^B3 -> -13.373956 | D17: =D16/(1+(ScenarioParameters!$B$8/100)/4)^C3 -> -13.143937 | E17: =E16/(1+(ScenarioParameters!$B$8/100)/4)^D3 -> -15.788513 | F17: =F16/(1+(ScenarioParameters!$B$8/100)/4)^E3 -> 333.80118 | G17: =G16/(1+(ScenarioParameters!$B$8/100)/4)^F3 -> 1144.6584 | H17: =H16/(1+(ScenarioParameters!$B$8/100)/4)^G3 -> 830.65594 | I17: =I16/(1+(ScenarioParameters!$B$8/100)/4)^H3 -> 1745.8628 | J17: =J16/(1+(ScenarioParameters!$B$8/100)/4)^I3 -> 859.56103 | ... U17: =U16/(1+(ScenarioParameters!$B$8/100)/4)^T3 -> 2833.8887
A19: Project NVP | B19: =SUM(B17:U17) -> 25471.884
A21: Forecasted Sales Volume from Winter's forecasting method*

Sheet -20% DevCost
A1: Development Cost Analysis: | B1: -0.2
B2: Year 0, Development | F2: Year 1, Projection | J2: Year 2, Projection | N2: Year 3, Projection | R2: Year 4, Projection
A3: Period | B3: 1 | C3: =B3+1 -> 2 | D3: =C3+1 -> 3 | E3: =D3+1 -> 4 | F3: =E3+1 -> 5 | G3: =F3+1 -> 6 | H3: =G3+1 -> 7 | I3: =H3+1 -> 8 | J3: =I3+1 -> 9 | ... U3: =T3+1 -> 20
A4: ($Value in thousands) | B4: Q1 | C4: Q2 | D4: Q3 | E4: Q4 | F4: Q1 | G4: Q2 | H4: Q3 | I4: Q4 | J4: Q1 | K4: Q2 | L4: Q3 | M4: Q4 | N4: Q1 | O4: Q2 | P4: Q3 | Q4: Q4 | R4: Q1 | S4: Q2 | T4: Q3 | U4: Q4
A6: Development Cost | B6: =(-1)*ScenarioParameters!$B$3/4*(1/1000)*(1+$B$1) -> -12.096 | C6: =(-1)*ScenarioParameters!$B$3/4*(1/1000)*(1+$B$1) -> -12.096 | D6: =(-1)*ScenarioParameters!$B$3/4*(1/1000)*(1+$B$1) -> -12.096 | E6: =(-1)*ScenarioParameters!$B$3/4*(1/1000)*(1+$B$1) -> -12.096
A7: Ramp-up cost | E7: =(-1)*ScenarioParameters!$B$6/2*(1/1000) -> -3.024 | F7: =(-1)*ScenarioParameters!$B$6/2*(1/1000) -> -3.024
A8: Marketing & support cost | F8: =(-1)*ScenarioParameters!$B$7/4*(1/1000) -> -210 | G8: =(-1)*ScenarioParameters!$B$7/4*(1/1000) -> -210 | H8: =(-1)*ScenarioParameters!$B$7/4*(1/1000) -> -210 | I8: =(-1)*ScenarioParameters!$B$7/4*(1/1000) -> -210 | J8: =(-1)*ScenarioParameters!$B$7/4*(1/1000) -> -210 | K8: =(-1)*ScenarioParameters!$B$7/4*(1/1000) -> -210 | L8: =(-1)*ScenarioParameters!$B$7/4*(1/1000) -> -210 | M8: =(-1)*ScenarioParameters!$B$7/4*(1/1000) -> -210 | ... U8: =(-1)*ScenarioParameters!$B$7/4*(1/1000) -> -210
A9: Production Cost | F9: =(-1)*(ScenarioParameters!$B$5)*ScenarioParameters!$G3*(1/1000) -> -358.17105 | G9: =(-1)*(ScenarioParameters!$B$5)*ScenarioParameters!$G4*(1/1000) -> -915.10143 | H9: =(-1)*(ScenarioParameters!$B$5)*ScenarioParameters!$G5*(1/1000) -> -710.166 | I9: =(-1)*(ScenarioParameters!$B$5)*ScenarioParameters!$G6*(1/1000) -> -1368.7099 | J9: =(-1)*(ScenarioParameters!$B$5)*ScenarioParameters!$G7*(1/1000) -> -751.42456 | K9: =(-1)*(ScenarioParameters!$B$5)*ScenarioParameters!$G8*(1/1000) -> -1496.0629 | L9: =(-1)*(ScenarioParameters!$B$5)*ScenarioParameters!$G9*(1/1000) -> -1010.0049 | M9: =(-1)*(ScenarioParameters!$B$5)*ScenarioParameters!$G10*(1/1000) -> -1796.7699 | N9: =(-1)*(ScenarioParameters!$B$5)*ScenarioParameters!$G11*(1/1000) -> -952.30836 | O9: =(-1)*(ScenarioParameters!$B$5)*ScenarioParameters!$G12*(1/1000) -> -1869.3415 | P9: =(-1)*(ScenarioParameters!$B$5)*ScenarioParameters!$G13*(1/1000) -> -1241.2506 | Q9: =(-1)*(ScenarioParameters!$B$5)*ScenarioParameters!$G14*(1/1000) -> -2183.9012 | R9: =(-1)*(ScenarioParameters!$B$5)*ScenarioParameters!$G15*(1/1000) -> -1166.5343 | S9: =(-1)*(ScenarioParameters!$B$5)*ScenarioParameters!$G16*(1/1000) -> -2267.4681 | T9: =(-1)*(ScenarioParameters!$B$5)*ScenarioParameters!$G17*(1/1000) -> -1492.2443 | U9: =(-1)*(ScenarioParameters!$B$5)*ScenarioParameters!$G18*(1/1000) -> -2604.2585
A10: Production volume | F10: =ScenarioParameters!$G3 -> 3106.9661 | G10: =ScenarioParameters!$G4 -> 7938.0762 | H10: =ScenarioParameters!$G5 -> 6160.3574 | I10: =ScenarioParameters!$G6 -> 11872.917 | J10: =ScenarioParameters!$G7 -> 6518.2561 | K10: =ScenarioParameters!$G8 -> 12977.645 | L10: =ScenarioParameters!$G9 -> 8761.3198 | M10: =ScenarioParameters!$G10 -> 15586.137 | N10: =ScenarioParameters!$G11 -> 8260.8289 | O10: =ScenarioParameters!$G12 -> 16215.662 | P10: =ScenarioParameters!$G13 -> 10767.267 | Q10: =ScenarioParameters!$G14 -> 18944.32 | R10: =ScenarioParameters!$G15 -> 10119.139 | S10: =ScenarioParameters!$G16 -> 19669.223 | T10: =ScenarioParameters!$G17 -> 12944.52 | U10: =ScenarioParameters!$G18 -> 22590.723
A11: Unit product cost | F11: =F9/F10 -> -0.11528 | G11: =G9/G10 -> -0.11528 | H11: =H9/H10 -> -0.11528 | I11: =I9/I10 -> -0.11528 | J11: =J9/J10 -> -0.11528 | K11: =K9/K10 -> -0.11528 | L11: =L9/L10 -> -0.11528 | M11: =M9/M10 -> -0.11528 | ... U11: =U9/U10 -> -0.11528
A12: Sales revenue | F12: =(ScenarioParameters!$B$4*F10)*(1/1000) -> 928.98285 | G12: =(ScenarioParameters!$B$4*G10)*(1/1000) -> 2373.4848 | H12: =(ScenarioParameters!$B$4*H10)*(1/1000) -> 1841.9469 | I12: =(ScenarioParameters!$B$4*I10)*(1/1000) -> 3550.0022 | J12: =(ScenarioParameters!$B$4*J10)*(1/1000) -> 1948.9586 | K12: =(ScenarioParameters!$B$4*K10)*(1/1000) -> 3880.3159 | L12: =(ScenarioParameters!$B$4*L10)*(1/1000) -> 2619.6346 | M12: =(ScenarioParameters!$B$4*M10)*(1/1000) -> 4660.255 | ... U12: =(ScenarioParameters!$B$4*U10)*(1/1000) -> 6754.626
A13: Forecasted Sales Volume | F13: =F$10 -> 3106.9661 | G13: =G$10 -> 7938.0762 | H13: =H$10 -> 6160.3574 | I13: =I$10 -> 11872.917 | J13: =J$10 -> 6518.2561 | K13: =K$10 -> 12977.645 | L13: =L$10 -> 8761.3198 | M13: =M$10 -> 15586.137 | ... U13: =U$10 -> 22590.723
A14: Unit price | F14: =F$12/F$13 -> 0.299 | G14: =G$12/G$13 -> 0.299 | H14: =H$12/H$13 -> 0.299 | I14: =I$12/I$13 -> 0.299 | J14: =J$12/J$13 -> 0.299 | K14: =K$12/K$13 -> 0.299 | L14: =L$12/L$13 -> 0.299 | M14: =M$12/M$13 -> 0.299 | ... U14: =U$12/U$13 -> 0.299
A16: Period Cash Flow | B16: =SUM(B6+B7+B8+B9+B12) -> -12.096 | C16: =SUM(C6+C7+C8+C9+C12) -> -12.096 | D16: =SUM(D6+D7+D8+D9+D12) -> -12.096 | E16: =SUM(E6+E7+E8+E9+E12) -> -15.12 | F16: =SUM(F6+F7+F8+F9+F12) -> 357.78781 | G16: =SUM(G6+G7+G8+G9+G12) -> 1248.3834 | H16: =SUM(H6+H7+H8+H9+H12) -> 921.78086 | I16: =SUM(I6+I7+I8+I9+I12) -> 1971.2923 | ... U16: =SUM(U6+U7+U8+U9+U12) -> 3940.3675
A17: Unit Price | B17: =B16 -> -12.096 | C17: =C16/(1+(ScenarioParameters!$B$8/100)/4)^B3 -> -11.887961 | D17: =D16/(1+(ScenarioParameters!$B$8/100)/4)^C3 -> -11.683499 | E17: =E16/(1+(ScenarioParameters!$B$8/100)/4)^D3 -> -14.353193 | F17: =F16/(1+(ScenarioParameters!$B$8/100)/4)^E3 -> 333.80118 | G17: =G16/(1+(ScenarioParameters!$B$8/100)/4)^F3 -> 1144.6584 | H17: =H16/(1+(ScenarioParameters!$B$8/100)/4)^G3 -> 830.65594 | I17: =I16/(1+(ScenarioParameters!$B$8/100)/4)^H3 -> 1745.8628 | J17: =J16/(1+(ScenarioParameters!$B$8/100)/4)^I3 -> 859.56103 | ... U17: =U16/(1+(ScenarioParameters!$B$8/100)/4)^T3 -> 2833.8887
A19: Project NVP | B19: =SUM(B17:U17) -> 25477.777
A21: Forecasted Sales Volume from Winter's forecasting method*

Sheet +20% DevCost
A1: Development Cost Analysis: | B1: 0.2
B2: Year 0, Development | F2: Year 1, Projection | J2: Year 2, Projection | N2: Year 3, Projection | R2: Year 4, Projection
A3: Period | B3: 1 | C3: =B3+1 -> 2 | D3: =C3+1 -> 3 | E3: =D3+1 -> 4 | F3: =E3+1 -> 5 | G3: =F3+1 -> 6 | H3: =G3+1 -> 7 | I3: =H3+1 -> 8 | J3: =I3+1 -> 9 | ... U3: =T3+1 -> 20
A4: ($Value in thousands) | B4: Q1 | C4: Q2 | D4: Q3 | E4: Q4 | F4: Q1 | G4: Q2 | H4: Q3 | I4: Q4 | J4: Q1 | K4: Q2 | L4: Q3 | M4: Q4 | N4: Q1 | O4: Q2 | P4: Q3 | Q4: Q4 | R4: Q1 | S4: Q2 | T4: Q3 | U4: Q4
A6: Development Cost | B6: =(-1)*ScenarioParameters!$B$3/4*(1/1000)*(1+$B$1) -> -18.144 | C6: =(-1)*ScenarioParameters!$B$3/4*(1/1000)*(1+$B$1) -> -18.144 | D6: =(-1)*ScenarioParameters!$B$3/4*(1/1000)*(1+$B$1) -> -18.144 | E6: =(-1)*ScenarioParameters!$B$3/4*(1/1000)*(1+$B$1) -> -18.144
A7: Ramp-up cost | E7: =(-1)*ScenarioParameters!$B$6/2*(1/1000) -> -3.024 | F7: =(-1)*ScenarioParameters!$B$6/2*(1/1000) -> -3.024
A8: Marketing & support cost | F8: =(-1)*ScenarioParameters!$B$7/4*(1/1000) -> -210 | G8: =(-1)*ScenarioParameters!$B$7/4*(1/1000) -> -210 | H8: =(-1)*ScenarioParameters!$B$7/4*(1/1000) -> -210 | I8: =(-1)*ScenarioParameters!$B$7/4*(1/1000) -> -210 | J8: =(-1)*ScenarioParameters!$B$7/4*(1/1000) -> -210 | K8: =(-1)*ScenarioParameters!$B$7/4*(1/1000) -> -210 | L8: =(-1)*ScenarioParameters!$B$7/4*(1/1000) -> -210 | M8: =(-1)*ScenarioParameters!$B$7/4*(1/1000) -> -210 | ... U8: =(-1)*ScenarioParameters!$B$7/4*(1/1000) -> -210
A9: Production Cost | F9: =(-1)*(ScenarioParameters!$B$5)*ScenarioParameters!$G3*(1/1000) -> -358.17105 | G9: =(-1)*(ScenarioParameters!$B$5)*ScenarioParameters!$G4*(1/1000) -> -915.10143 | H9: =(-1)*(ScenarioParameters!$B$5)*ScenarioParameters!$G5*(1/1000) -> -710.166 | I9: =(-1)*(ScenarioParameters!$B$5)*ScenarioParameters!$G6*(1/1000) -> -1368.7099 | J9: =(-1)*(ScenarioParameters!$B$5)*ScenarioParameters!$G7*(1/1000) -> -751.42456 | K9: =(-1)*(ScenarioParameters!$B$5)*ScenarioParameters!$G8*(1/1000) -> -1496.0629 | L9: =(-1)*(ScenarioParameters!$B$5)*ScenarioParameters!$G9*(1/1000) -> -1010.0049 | M9: =(-1)*(ScenarioParameters!$B$5)*ScenarioParameters!$G10*(1/1000) -> -1796.7699 | N9: =(-1)*(ScenarioParameters!$B$5)*ScenarioParameters!$G11*(1/1000) -> -952.30836 | O9: =(-1)*(ScenarioParameters!$B$5)*ScenarioParameters!$G12*(1/1000) -> -1869.3415 | P9: =(-1)*(ScenarioParameters!$B$5)*ScenarioParameters!$G13*(1/1000) -> -1241.2506 | Q9: =(-1)*(ScenarioParameters!$B$5)*ScenarioParameters!$G14*(1/1000) -> -2183.9012 | R9: =(-1)*(ScenarioParameters!$B$5)*ScenarioParameters!$G15*(1/1000) -> -1166.5343 | S9: =(-1)*(ScenarioParameters!$B$5)*ScenarioParameters!$G16*(1/1000) -> -2267.4681 | T9: =(-1)*(ScenarioParameters!$B$5)*ScenarioParameters!$G17*(1/1000) -> -1492.2443 | U9: =(-1)*(ScenarioParameters!$B$5)*ScenarioParameters!$G18*(1/1000) -> -2604.2585
A10: Production volume | F10: =ScenarioParameters!$G3 -> 3106.9661 | G10: =ScenarioParameters!$G4 -> 7938.0762 | H10: =ScenarioParameters!$G5 -> 6160.3574 | I10: =ScenarioParameters!$G6 -> 11872.917 | J10: =ScenarioParameters!$G7 -> 6518.2561 | K10: =ScenarioParameters!$G8 -> 12977.645 | L10: =ScenarioParameters!$G9 -> 8761.3198 | M10: =ScenarioParameters!$G10 -> 15586.137 | N10: =ScenarioParameters!$G11 -> 8260.8289 | O10: =ScenarioParameters!$G12 -> 16215.662 | P10: =ScenarioParameters!$G13 -> 10767.267 | Q10: =ScenarioParameters!$G14 -> 18944.32 | R10: =ScenarioParameters!$G15 -> 10119.139 | S10: =ScenarioParameters!$G16 -> 19669.223 | T10: =ScenarioParameters!$G17 -> 12944.52 | U10: =ScenarioParameters!$G18 -> 22590.723
A11: Unit product cost | F11: =F9/F10 -> -0.11528 | G11: =G9/G10 -> -0.11528 | H11: =H9/H10 -> -0.11528 | I11: =I9/I10 -> -0.11528 | J11: =J9/J10 -> -0.11528 | K11: =K9/K10 -> -0.11528 | L11: =L9/L10 -> -0.11528 | M11: =M9/M10 -> -0.11528 | ... U11: =U9/U10 -> -0.11528
A12: Sales revenue | F12: =(ScenarioParameters!$B$4*F10)*(1/1000) -> 928.98285 | G12: =(ScenarioParameters!$B$4*G10)*(1/1000) -> 2373.4848 | H12: =(ScenarioParameters!$B$4*H10)*(1/1000) -> 1841.9469 | I12: =(ScenarioParameters!$B$4*I10)*(1/1000) -> 3550.0022 | J12: =(ScenarioParameters!$B$4*J10)*(1/1000) -> 1948.9586 | K12: =(ScenarioParameters!$B$4*K10)*(1/1000) -> 3880.3159 | L12: =(ScenarioParameters!$B$4*L10)*(1/1000) -> 2619.6346 | M12: =(ScenarioParameters!$B$4*M10)*(1/1000) -> 4660.255 | ... U12: =(ScenarioParameters!$B$4*U10)*(1/1000) -> 6754.626
A13: Forecasted Sales Volume | F13: =F$10 -> 3106.9661 | G13: =G$10 -> 7938.0762 | H13: =H$10 -> 6160.3574 | I13: =I$10 -> 11872.917 | J13: =J$10 -> 6518.2561 | K13: =K$10 -> 12977.645 | L13: =L$10 -> 8761.3198 | M13: =M$10 -> 15586.137 | ... U13: =U$10 -> 22590.723
A14: Unit price | F14: =F$12/F$13 -> 0.299 | G14: =G$12/G$13 -> 0.299 | H14: =H$12/H$13 -> 0.299 | I14: =I$12/I$13 -> 0.299 | J14: =J$12/J$13 -> 0.299 | K14: =K$12/K$13 -> 0.299 | L14: =L$12/L$13 -> 0.299 | M14: =M$12/M$13 -> 0.299 | ... U14: =U$12/U$13 -> 0.299
A16: Period Cash Flow | B16: =SUM(B6+B7+B8+B9+B12) -> -18.144 | C16: =SUM(C6+C7+C8+C9+C12) -> -18.144 | D16: =SUM(D6+D7+D8+D9+D12) -> -18.144 | E16: =SUM(E6+E7+E8+E9+E12) -> -21.168 | F16: =SUM(F6+F7+F8+F9+F12) -> 357.78781 | G16: =SUM(G6+G7+G8+G9+G12) -> 1248.3834 | H16: =SUM(H6+H7+H8+H9+H12) -> 921.78086 | I16: =SUM(I6+I7+I8+I9+I12) -> 1971.2923 | ... U16: =SUM(U6+U7+U8+U9+U12) -> 3940.3675
A17: Unit Price | B17: =B16 -> -18.144 | C17: =C16/(1+(ScenarioParameters!$B$8/100)/4)^B3 -> -17.831941 | D17: =D16/(1+(ScenarioParameters!$B$8/100)/4)^C3 -> -17.525249 | E17: =E16/(1+(ScenarioParameters!$B$8/100)/4)^D3 -> -20.094471 | F17: =F16/(1+(ScenarioParameters!$B$8/100)/4)^E3 -> 333.80118 | G17: =G16/(1+(ScenarioParameters!$B$8/100)/4)^F3 -> 1144.6584 | H17: =H16/(1+(ScenarioParameters!$B$8/100)/4)^G3 -> 830.65594 | I17: =I16/(1+(ScenarioParameters!$B$8/100)/4)^H3 -> 1745.8628 | J17: =J16/(1+(ScenarioParameters!$B$8/100)/4)^I3 -> 859.56103 | ... U17: =U16/(1+(ScenarioParameters!$B$8/100)/4)^T3 -> 2833.8887
A19: Project NVP | B19: =SUM(B17:U17) -> 25454.202
A21: Forecasted Sales Volume from Winter's forecasting method*

Sheet +30% DevCost
A1: Development Cost Analysis: | B1: 0.3
B2: Year 0, Development | F2: Year 1, Projection | J2: Year 2, Projection | N2: Year 3, Projection | R2: Year 4, Projection
A3: Period | B3: 1 | C3: =B3+1 -> 2 | D3: =C3+1 -> 3 | E3: =D3+1 -> 4 | F3: =E3+1 -> 5 | G3: =F3+1 -> 6 | H3: =G3+1 -> 7 | I3: =H3+1 -> 8 | J3: =I3+1 -> 9 | ... U3: =T3+1 -> 20
A4: ($Value in thousands) | B4: Q1 | C4: Q2 | D4: Q3 | E4: Q4 | F4: Q1 | G4: Q2 | H4: Q3 | I4: Q4 | J4: Q1 | K4: Q2 | L4: Q3 | M4: Q4 | N4: Q1 | O4: Q2 | P4: Q3 | Q4: Q4 | R4: Q1 | S4: Q2 | T4: Q3 | U4: Q4
A6: Development Cost | B6: =(-1)*ScenarioParameters!$B$3/4*(1/1000)*(1+$B$1) -> -19.656 | C6: =(-1)*ScenarioParameters!$B$3/4*(1/1000)*(1+$B$1) -> -19.656 | D6: =(-1)*ScenarioParameters!$B$3/4*(1/1000)*(1+$B$1) -> -19.656 | E6: =(-1)*ScenarioParameters!$B$3/4*(1/1000)*(1+$B$1) -> -19.656
A7: Ramp-up cost | E7: =(-1)*ScenarioParameters!$B$6/2*(1/1000) -> -3.024 | F7: =(-1)*ScenarioParameters!$B$6/2*(1/1000) -> -3.024
A8: Marketing & support cost | F8: =(-1)*ScenarioParameters!$B$7/4*(1/1000) -> -210 | G8: =(-1)*ScenarioParameters!$B$7/4*(1/1000) -> -210 | H8: =(-1)*ScenarioParameters!$B$7/4*(1/1000) -> -210 | I8: =(-1)*ScenarioParameters!$B$7/4*(1/1000) -> -210 | J8: =(-1)*ScenarioParameters!$B$7/4*(1/1000) -> -210 | K8: =(-1)*ScenarioParameters!$B$7/4*(1/1000) -> -210 | L8: =(-1)*ScenarioParameters!$B$7/4*(1/1000) -> -210 | M8: =(-1)*ScenarioParameters!$B$7/4*(1/1000) -> -210 | ... U8: =(-1)*ScenarioParameters!$B$7/4*(1/1000) -> -210
A9: Production Cost | F9: =(-1)*(ScenarioParameters!$B$5)*ScenarioParameters!$G3*(1/1000) -> -358.17105 | G9: =(-1)*(ScenarioParameters!$B$5)*ScenarioParameters!$G4*(1/1000) -> -915.10143 | H9: =(-1)*(ScenarioParameters!$B$5)*ScenarioParameters!$G5*(1/1000) -> -710.166 | I9: =(-1)*(ScenarioParameters!$B$5)*ScenarioParameters!$G6*(1/1000) -> -1368.7099 | J9: =(-1)*(ScenarioParameters!$B$5)*ScenarioParameters!$G7*(1/1000) -> -751.42456 | K9: =(-1)*(ScenarioParameters!$B$5)*ScenarioParameters!$G8*(1/1000) -> -1496.0629 | L9: =(-1)*(ScenarioParameters!$B$5)*ScenarioParameters!$G9*(1/1000) -> -1010.0049 | M9: =(-1)*(ScenarioParameters!$B$5)*ScenarioParameters!$G10*(1/1000) -> -1796.7699 | N9: =(-1)*(ScenarioParameters!$B$5)*ScenarioParameters!$G11*(1/1000) -> -952.30836 | O9: =(-1)*(ScenarioParameters!$B$5)*ScenarioParameters!$G12*(1/1000) -> -1869.3415 | P9: =(-1)*(ScenarioParameters!$B$5)*ScenarioParameters!$G13*(1/1000) -> -1241.2506 | Q9: =(-1)*(ScenarioParameters!$B$5)*ScenarioParameters!$G14*(1/1000) -> -2183.9012 | R9: =(-1)*(ScenarioParameters!$B$5)*ScenarioParameters!$G15*(1/1000) -> -1166.5343 | S9: =(-1)*(ScenarioParameters!$B$5)*ScenarioParameters!$G16*(1/1000) -> -2267.4681 | T9: =(-1)*(ScenarioParameters!$B$5)*ScenarioParameters!$G17*(1/1000) -> -1492.2443 | U9: =(-1)*(ScenarioParameters!$B$5)*ScenarioParameters!$G18*(1/1000) -> -2604.2585
A10: Production volume | F10: =ScenarioParameters!$G3 -> 3106.9661 | G10: =ScenarioParameters!$G4 -> 7938.0762 | H10: =ScenarioParameters!$G5 -> 6160.3574 | I10: =ScenarioParameters!$G6 -> 11872.917 | J10: =ScenarioParameters!$G7 -> 6518.2561 | K10: =ScenarioParameters!$G8 -> 12977.645 | L10: =ScenarioParameters!$G9 -> 8761.3198 | M10: =ScenarioParameters!$G10 -> 15586.137 | N10: =ScenarioParameters!$G11 -> 8260.8289 | O10: =ScenarioParameters!$G12 -> 16215.662 | P10: =ScenarioParameters!$G13 -> 10767.267 | Q10: =ScenarioParameters!$G14 -> 18944.32 | R10: =ScenarioParameters!$G15 -> 10119.139 | S10: =ScenarioParameters!$G16 -> 19669.223 | T10: =ScenarioParameters!$G17 -> 12944.52 | U10: =ScenarioParameters!$G18 -> 22590.723
A11: Unit product cost | F11: =F9/F10 -> -0.11528 | G11: =G9/G10 -> -0.11528 | H11: =H9/H10 -> -0.11528 | I11: =I9/I10 -> -0.11528 | J11: =J9/J10 -> -0.11528 | K11: =K9/K10 -> -0.11528 | L11: =L9/L10 -> -0.11528 | M11: =M9/M10 -> -0.11528 | ... U11: =U9/U10 -> -0.11528
A12: Sales revenue | F12: =(ScenarioParameters!$B$4*F10)*(1/1000) -> 928.98285 | G12: =(ScenarioParameters!$B$4*G10)*(1/1000) -> 2373.4848 | H12: =(ScenarioParameters!$B$4*H10)*(1/1000) -> 1841.9469 | I12: =(ScenarioParameters!$B$4*I10)*(1/1000) -> 3550.0022 | J12: =(ScenarioParameters!$B$4*J10)*(1/1000) -> 1948.9586 | K12: =(ScenarioParameters!$B$4*K10)*(1/1000) -> 3880.3159 | L12: =(ScenarioParameters!$B$4*L10)*(1/1000) -> 2619.6346 | M12: =(ScenarioParameters!$B$4*M10)*(1/1000) -> 4660.255 | ... U12: =(ScenarioParameters!$B$4*U10)*(1/1000) -> 6754.626
A13: Forecasted Sales Volume | F13: =F$10 -> 3106.9661 | G13: =G$10 -> 7938.0762 | H13: =H$10 -> 6160.3574 | I13: =I$10 -> 11872.917 | J13: =J$10 -> 6518.2561 | K13: =K$10 -> 12977.645 | L13: =L$10 -> 8761.3198 | M13: =M$10 -> 15586.137 | ... U13: =U$10 -> 22590.723
A14: Unit price | F14: =F$12/F$13 -> 0.299 | G14: =G$12/G$13 -> 0.299 | H14: =H$12/H$13 -> 0.299 | I14: =I$12/I$13 -> 0.299 | J14: =J$12/J$13 -> 0.299 | K14: =K$12/K$13 -> 0.299 | L14: =L$12/L$13 -> 0.299 | M14: =M$12/M$13 -> 0.299 | ... U14: =U$12/U$13 -> 0.299
A16: Period Cash Flow | B16: =SUM(B6+B7+B8+B9+B12) -> -19.656 | C16: =SUM(C6+C7+C8+C9+C12) -> -19.656 | D16: =SUM(D6+D7+D8+D9+D12) -> -19.656 | E16: =SUM(E6+E7+E8+E9+E12) -> -22.68 | F16: =SUM(F6+F7+F8+F9+F12) -> 357.78781 | G16: =SUM(G6+G7+G8+G9+G12) -> 1248.3834 | H16: =SUM(H6+H7+H8+H9+H12) -> 921.78086 | I16: =SUM(I6+I7+I8+I9+I12) -> 1971.2923 | ... U16: =SUM(U6+U7+U8+U9+U12) -> 3940.3675
A17: Unit Price | B17: =B16 -> -19.656 | C17: =C16/(1+(ScenarioParameters!$B$8/100)/4)^B3 -> -19.317936 | D17: =D16/(1+(ScenarioParameters!$B$8/100)/4)^C3 -> -18.985687 | E17: =E16/(1+(ScenarioParameters!$B$8/100)/4)^D3 -> -21.52979 | F17: =F16/(1+(ScenarioParameters!$B$8/100)/4)^E3 -> 333.80118 | G17: =G16/(1+(ScenarioParameters!$B$8/100)/4)^F3 -> 1144.6584 | H17: =H16/(1+(ScenarioParameters!$B$8/100)/4)^G3 -> 830.65594 | I17: =I16/(1+(ScenarioParameters!$B$8/100)/4)^H3 -> 1745.8628 | J17: =J16/(1+(ScenarioParameters!$B$8/100)/4)^I3 -> 859.56103 | ... U17: =U16/(1+(ScenarioParameters!$B$8/100)/4)^T3 -> 2833.8887
A19: Project NVP | B19: =SUM(B17:U17) -> 25448.309
A21: Forecasted Sales Volume from Winter's forecasting method*

Sheet -30% DevCost
A1: Development Cost Analysis: | B1: -0.3
B2: Year 0, Development | F2: Year 1, Projection | J2: Year 2, Projection | N2: Year 3, Projection | R2: Year 4, Projection
A3: Period | B3: 1 | C3: =B3+1 -> 2 | D3: =C3+1 -> 3 | E3: =D3+1 -> 4 | F3: =E3+1 -> 5 | G3: =F3+1 -> 6 | H3: =G3+1 -> 7 | I3: =H3+1 -> 8 | J3: =I3+1 -> 9 | ... U3: =T3+1 -> 20
A4: ($Value in thousands) | B4: Q1 | C4: Q2 | D4: Q3 | E4: Q4 | F4: Q1 | G4: Q2 | H4: Q3 | I4: Q4 | J4: Q1 | K4: Q2 | L4: Q3 | M4: Q4 | N4: Q1 | O4: Q2 | P4: Q3 | Q4: Q4 | R4: Q1 | S4: Q2 | T4: Q3 | U4: Q4
A6: Development Cost | B6: =(-1)*ScenarioParameters!$B$3/4*(1/1000)*(1+$B$1) -> -10.584 | C6: =(-1)*ScenarioParameters!$B$3/4*(1/1000)*(1+$B$1) -> -10.584 | D6: =(-1)*ScenarioParameters!$B$3/4*(1/1000)*(1+$B$1) -> -10.584 | E6: =(-1)*ScenarioParameters!$B$3/4*(1/1000)*(1+$B$1) -> -10.584
A7: Ramp-up cost | E7: =(-1)*ScenarioParameters!$B$6/2*(1/1000) -> -3.024 | F7: =(-1)*ScenarioParameters!$B$6/2*(1/1000) -> -3.024
A8: Marketing & support cost | F8: =(-1)*ScenarioParameters!$B$7/4*(1/1000) -> -210 | G8: =(-1)*ScenarioParameters!$B$7/4*(1/1000) -> -210 | H8: =(-1)*ScenarioParameters!$B$7/4*(1/1000) -> -210 | I8: =(-1)*ScenarioParameters!$B$7/4*(1/1000) -> -210 | J8: =(-1)*ScenarioParameters!$B$7/4*(1/1000) -> -210 | K8: =(-1)*ScenarioParameters!$B$7/4*(1/1000) -> -210 | L8: =(-1)*ScenarioParameters!$B$7/4*(1/1000) -> -210 | M8: =(-1)*ScenarioParameters!$B$7/4*(1/1000) -> -210 | ... U8: =(-1)*ScenarioParameters!$B$7/4*(1/1000) -> -210
A9: Production Cost | F9: =(-1)*(ScenarioParameters!$B$5)*ScenarioParameters!$G3*(1/1000) -> -358.17105 | G9: =(-1)*(ScenarioParameters!$B$5)*ScenarioParameters!$G4*(1/1000) -> -915.10143 | H9: =(-1)*(ScenarioParameters!$B$5)*ScenarioParameters!$G5*(1/1000) -> -710.166 | I9: =(-1)*(ScenarioParameters!$B$5)*ScenarioParameters!$G6*(1/1000) -> -1368.7099 | J9: =(-1)*(ScenarioParameters!$B$5)*ScenarioParameters!$G7*(1/1000) -> -751.42456 | K9: =(-1)*(ScenarioParameters!$B$5)*ScenarioParameters!$G8*(1/1000) -> -1496.0629 | L9: =(-1)*(ScenarioParameters!$B$5)*ScenarioParameters!$G9*(1/1000) -> -1010.0049 | M9: =(-1)*(ScenarioParameters!$B$5)*ScenarioParameters!$G10*(1/1000) -> -1796.7699 | N9: =(-1)*(ScenarioParameters!$B$5)*ScenarioParameters!$G11*(1/1000) -> -952.30836 | O9: =(-1)*(ScenarioParameters!$B$5)*ScenarioParameters!$G12*(1/1000) -> -1869.3415 | P9: =(-1)*(ScenarioParameters!$B$5)*ScenarioParameters!$G13*(1/1000) -> -1241.2506 | Q9: =(-1)*(ScenarioParameters!$B$5)*ScenarioParameters!$G14*(1/1000) -> -2183.9012 | R9: =(-1)*(ScenarioParameters!$B$5)*ScenarioParameters!$G15*(1/1000) -> -1166.5343 | S9: =(-1)*(ScenarioParameters!$B$5)*ScenarioParameters!$G16*(1/1000) -> -2267.4681 | T9: =(-1)*(ScenarioParameters!$B$5)*ScenarioParameters!$G17*(1/1000) -> -1492.2443 | U9: =(-1)*(ScenarioParameters!$B$5)*ScenarioParameters!$G18*(1/1000) -> -2604.2585
A10: Production volume | F10: =ScenarioParameters!$G3 -> 3106.9661 | G10: =ScenarioParameters!$G4 -> 7938.0762 | H10: =ScenarioParameters!$G5 -> 6160.3574 | I10: =ScenarioParameters!$G6 -> 11872.917 | J10: =ScenarioParameters!$G7 -> 6518.2561 | K10: =ScenarioParameters!$G8 -> 12977.645 | L10: =ScenarioParameters!$G9 -> 8761.3198 | M10: =ScenarioParameters!$G10 -> 15586.137 | N10: =ScenarioParameters!$G11 -> 8260.8289 | O10: =ScenarioParameters!$G12 -> 16215.662 | P10: =ScenarioParameters!$G13 -> 10767.267 | Q10: =ScenarioParameters!$G14 -> 18944.32 | R10: =ScenarioParameters!$G15 -> 10119.139 | S10: =ScenarioParameters!$G16 -> 19669.223 | T10: =ScenarioParameters!$G17 -> 12944.52 | U10: =ScenarioParameters!$G18 -> 22590.723
A11: Unit product cost | F11: =F9/F10 -> -0.11528 | G11: =G9/G10 -> -0.11528 | H11: =H9/H10 -> -0.11528 | I11: =I9/I10 -> -0.11528 | J11: =J9/J10 -> -0.11528 | K11: =K9/K10 -> -0.11528 | L11: =L9/L10 -> -0.11528 | M11: =M9/M10 -> -0.11528 | ... U11: =U9/U10 -> -0.11528
A12: Sales revenue | F12: =(ScenarioParameters!$B$4*F10)*(1/1000) -> 928.98285 | G12: =(ScenarioParameters!$B$4*G10)*(1/1000) -> 2373.4848 | H12: =(ScenarioParameters!$B$4*H10)*(1/1000) -> 1841.9469 | I12: =(ScenarioParameters!$B$4*I10)*(1/1000) -> 3550.0022 | J12: =(ScenarioParameters!$B$4*J10)*(1/1000) -> 1948.9586 | K12: =(ScenarioParameters!$B$4*K10)*(1/1000) -> 3880.3159 | L12: =(ScenarioParameters!$B$4*L10)*(1/1000) -> 2619.6346 | M12: =(ScenarioParameters!$B$4*M10)*(1/1000) -> 4660.255 | ... U12: =(ScenarioParameters!$B$4*U10)*(1/1000) -> 6754.626
A13: Forecasted Sales Volume | F13: =F$10 -> 3106.9661 | G13: =G$10 -> 7938.0762 | H13: =H$10 -> 6160.3574 | I13: =I$10 -> 11872.917 | J13: =J$10 -> 6518.2561 | K13: =K$10 -> 12977.645 | L13: =L$10 -> 8761.3198 | M13: =M$10 -> 15586.137 | ... U13: =U$10 -> 22590.723
A14: Unit price | F14: =F$12/F$13 -> 0.299 | G14: =G$12/G$13 -> 0.299 | H14: =H$12/H$13 -> 0.299 | I14: =I$12/I$13 -> 0.299 | J14: =J$12/J$13 -> 0.299 | K14: =K$12/K$13 -> 0.299 | L14: =L$12/L$13 -> 0.299 | M14: =M$12/M$13 -> 0.299 | ... U14: =U$12/U$13 -> 0.299
A16: Period Cash Flow | B16: =SUM(B6+B7+B8+B9+B12) -> -10.584 | C16: =SUM(C6+C7+C8+C9+C12) -> -10.584 | D16: =SUM(D6+D7+D8+D9+D12) -> -10.584 | E16: =SUM(E6+E7+E8+E9+E12) -> -13.608 | F16: =SUM(F6+F7+F8+F9+F12) -> 357.78781 | G16: =SUM(G6+G7+G8+G9+G12) -> 1248.3834 | H16: =SUM(H6+H7+H8+H9+H12) -> 921.78086 | I16: =SUM(I6+I7+I8+I9+I12) -> 1971.2923 | ... U16: =SUM(U6+U7+U8+U9+U12) -> 3940.3675
A17: Unit Price | B17: =B16 -> -10.584 | C17: =C16/(1+(ScenarioParameters!$B$8/100)/4)^B3 -> -10.401966 | D17: =D16/(1+(ScenarioParameters!$B$8/100)/4)^C3 -> -10.223062 | E17: =E16/(1+(ScenarioParameters!$B$8/100)/4)^D3 -> -12.917874 | F17: =F16/(1+(ScenarioParameters!$B$8/100)/4)^E3 -> 333.80118 | G17: =G16/(1+(ScenarioParameters!$B$8/100)/4)^F3 -> 1144.6584 | H17: =H16/(1+(ScenarioParameters!$B$8/100)/4)^G3 -> 830.65594 | I17: =I16/(1+(ScenarioParameters!$B$8/100)/4)^H3 -> 1745.8628 | J17: =J16/(1+(ScenarioParameters!$B$8/100)/4)^I3 -> 859.56103 | ... U17: =U16/(1+(ScenarioParameters!$B$8/100)/4)^T3 -> 2833.8887
A19: Project NVP | B19: =SUM(B17:U17) -> 25483.671
A21: Forecasted Sales Volume from Winter's forecasting method*

Sheet -1 DevTime
A1: Dev Time
B2: Year 1 | F2: Year 2 | J2: Year 3 | N2: Year 4
A3: Period | B3: 1 | C3: =B3+1 -> 2 | D3: =C3+1 -> 3 | E3: =D3+1 -> 4 | F3: =E3+1 -> 5 | G3: =F3+1 -> 6 | H3: =G3+1 -> 7 | I3: =H3+1 -> 8 | J3: =I3+1 -> 9 | ... Q3: =P3+1 -> 16
A4: ($Value in thousands) | B4: Q1 | C4: Q2 | D4: Q3 | E4: Q4 | F4: Q1 | G4: Q2 | H4: Q3 | I4: Q4 | J4: Q1 | K4: Q2 | L4: Q3 | M4: Q4 | N4: Q1 | O4: Q2 | P4: Q3 | Q4: Q4
A6: Development Cost | B6: =(-1)*ScenarioParameters!$B$3/4*(1/1000) -> -15.12 | C6: =(-1)*ScenarioParameters!$B$3/4*(1/1000) -> -15.12 | D6: =(-1)*ScenarioParameters!$B$3/4*(1/1000) -> -15.12
A7: Ramp-up cost | D7: =(-1)*ScenarioParameters!$B$6/2*(1/1000) -> -3.024 | E7: =(-1)*ScenarioParameters!$B$6/2*(1/1000) -> -3.024
A8: Marketing & support cost | E8: =(-1)*ScenarioParameters!$B$7/4*(1/1000) -> -210 | F8: =(-1)*ScenarioParameters!$B$7/4*(1/1000) -> -210 | G8: =(-1)*ScenarioParameters!$B$7/4*(1/1000) -> -210 | H8: =(-1)*ScenarioParameters!$B$7/4*(1/1000) -> -210 | I8: =(-1)*ScenarioParameters!$B$7/4*(1/1000) -> -210 | J8: =(-1)*ScenarioParameters!$B$7/4*(1/1000) -> -210 | K8: =(-1)*ScenarioParameters!$B$7/4*(1/1000) -> -210 | L8: =(-1)*ScenarioParameters!$B$7/4*(1/1000) -> -210 | ... Q8: =(-1)*ScenarioParameters!$B$7/4*(1/1000) -> -210
A9: Production volume | F9: =(-1)*(ScenarioParameters!$B$5)*(ScenarioParameters!$B$2/4)*(1/1000) -> #VALUE! | G9: =(-1)*(ScenarioParameters!$B$5)*(ScenarioParameters!$B$2/4)*(1/1000) -> #VALUE! | H9: =(-1)*(ScenarioParameters!$B$5)*(ScenarioParameters!$B$2/4)*(1/1000) -> #VALUE! | I9: =(-1)*(ScenarioParameters!$B$5)*(ScenarioParameters!$B$2/4)*(1/1000) -> #VALUE! | J9: =(-1)*(ScenarioParameters!$B$5)*(ScenarioParameters!$B$2/4)*(1/1000) -> #VALUE! | K9: =(-1)*(ScenarioParameters!$B$5)*(ScenarioParameters!$B$2/4)*(1/1000) -> #VALUE! | L9: =(-1)*(ScenarioParameters!$B$5)*(ScenarioParameters!$B$2/4)*(1/1000) -> #VALUE! | M9: =(-1)*(ScenarioParameters!$B$5)*(ScenarioParameters!$B$2/4)*(1/1000) -> #VALUE! | ... Q9: =(-1)*(ScenarioParameters!$B$5)*(ScenarioParameters!$B$2/4)*(1/1000) -> #VALUE!
A10: Unit product cost | F10: =ScenarioParameters!$B$2/4 -> #VALUE! | G10: =ScenarioParameters!$B$2/4 -> #VALUE! | H10: =ScenarioParameters!$B$2/4 -> #VALUE! | I10: =ScenarioParameters!$B$2/4 -> #VALUE! | J10: =ScenarioParameters!$B$2/4 -> #VALUE! | K10: =ScenarioParameters!$B$2/4 -> #VALUE! | L10: =ScenarioParameters!$B$2/4 -> #VALUE! | M10: =ScenarioParameters!$B$2/4 -> #VALUE! | ... Q10: =ScenarioParameters!$B$2/4 -> #VALUE!
A11: Sales revenue | F11: =F9/F10 -> #VALUE! | G11: =G9/G10 -> #VALUE! | H11: =H9/H10 -> #VALUE! | I11: =I9/I10 -> #VALUE! | J11: =J9/J10 -> #VALUE! | K11: =K9/K10 -> #VALUE! | L11: =L9/L10 -> #VALUE! | M11: =M9/M10 -> #VALUE! | ... Q11: =Q9/Q10 -> #VALUE!
A12: sales volume | F12: =(ScenarioParameters!$B$4*ScenarioParameters!$B$2/4)*(1/1000) -> #VALUE! | G12: =(ScenarioParameters!$B$4*ScenarioParameters!$B$2/4)*(1/1000) -> #VALUE! | H12: =(ScenarioParameters!$B$4*ScenarioParameters!$B$2/4)*(1/1000) -> #VALUE! | I12: =(ScenarioParameters!$B$4*ScenarioParameters!$B$2/4)*(1/1000) -> #VALUE! | J12: =(ScenarioParameters!$B$4*ScenarioParameters!$B$2/4)*(1/1000) -> #VALUE! | K12: =(ScenarioParameters!$B$4*ScenarioParameters!$B$2/4)*(1/1000) -> #VALUE! | L12: =(ScenarioParameters!$B$4*ScenarioParameters!$B$2/4)*(1/1000) -> #VALUE! | M12: =(ScenarioParameters!$B$4*ScenarioParameters!$B$2/4)*(1/1000) -> #VALUE! | ... Q12: =(ScenarioParameters!$B$4*ScenarioParameters!$B$2/4)*(1/1000) -> #VALUE!
A13: unit price | F13: =ScenarioParameters!$B$2/4 -> #VALUE! | G13: =ScenarioParameters!$B$2/4 -> #VALUE! | H13: =ScenarioParameters!$B$2/4 -> #VALUE! | I13: =ScenarioParameters!$B$2/4 -> #VALUE! | J13: =ScenarioParameters!$B$2/4 -> #VALUE! | K13: =ScenarioParameters!$B$2/4 -> #VALUE! | L13: =ScenarioParameters!$B$2/4 -> #VALUE! | M13: =ScenarioParameters!$B$2/4 -> #VALUE! | ... Q13: =ScenarioParameters!$B$2/4 -> #VALUE!
F14: =F12/F13 -> #VALUE! | G14: =G12/G13 -> #VALUE! | H14: =H12/H13 -> #VALUE! | I14: =I12/I13 -> #VALUE! | J14: =J12/J13 -> #VALUE! | K14: =K12/K13 -> #VALUE! | L14: =L12/L13 -> #VALUE! | M14: =M12/M13 -> #VALUE! | ... Q14: =Q12/Q13 -> #VALUE!
A16: Period Cash Flow | B16: =SUM(B6+B7+B8+B9+B12) -> -15.12 | C16: =SUM(C6+C7+C8+C9+C12) -> -15.12 | D16: =SUM(D6+D7+D8+D9+D12) -> -18.144 | E16: =SUM(E6+E7+E8+E9+E12) -> -213.024 | F16: =SUM(F6+F7+F8+F9+F12) -> #VALUE! | G16: =SUM(G6+G7+G8+G9+G12) -> #VALUE! | H16: =SUM(H6+H7+H8+H9+H12) -> #VALUE! | I16: =SUM(I6+I7+I8+I9+I12) -> #VALUE! | ... Q16: =SUM(Q6+Q7+Q8+Q9+Q12) -> #VALUE!
A17: Unit Price | B17: =B16 -> -15.12 | C17: =C16/(1+(ScenarioParameters!$B$8/100)/4)^B3 -> -14.859951 | D17: =D16/(1+(ScenarioParameters!$B$8/100)/4)^C3 -> -17.525249 | E17: =E16/(1+(ScenarioParameters!$B$8/100)/4)^D3 -> -202.22055 | F17: =F16/(1+(ScenarioParameters!$B$8/100)/4)^E3 -> #VALUE! | G17: =G16/(1+(ScenarioParameters!$B$8/100)/4)^F3 -> #VALUE! | H17: =H16/(1+(ScenarioParameters!$B$8/100)/4)^G3 -> #VALUE! | I17: =I16/(1+(ScenarioParameters!$B$8/100)/4)^H3 -> #VALUE! | J17: =J16/(1+(ScenarioParameters!$B$8/100)/4)^I3 -> #VALUE! | ... Q17: =Q16/(1+(ScenarioParameters!$B$8/100)/4)^P3 -> #VALUE!
A19: Project NVP | B19: =SUM(B17:Q17) -> #VALUE!

Sheet -2 DevTime
A1: Dev Time
B2: Year 1 | F2: Year 2 | J2: Year 3 | N2: Year 4
A3: Period | B3: 1 | C3: =B3+1 -> 2 | D3: =C3+1 -> 3 | E3: =D3+1 -> 4 | F3: =E3+1 -> 5 | G3: =F3+1 -> 6 | H3: =G3+1 -> 7 | I3: =H3+1 -> 8 | J3: =I3+1 -> 9 | ... Q3: =P3+1 -> 16
A4: ($Value in thousands) | B4: Q1 | C4: Q2 | D4: Q3 | E4: Q4 | F4: Q1 | G4: Q2 | H4: Q3 | I4: Q4 | J4: Q1 | K4: Q2 | L4: Q3 | M4: Q4 | N4: Q1 | O4: Q2 | P4: Q3 | Q4: Q4
A6: Development Cost | B6: =(-1)*ScenarioParameters!$B$3/4*(1/1000) -> -15.12 | C6: =(-1)*ScenarioParameters!$B$3/4*(1/1000) -> -15.12
A7: Ramp-up cost | C7: =(-1)*ScenarioParameters!$B$6/2*(1/1000) -> -3.024 | D7: =(-1)*ScenarioParameters!$B$6/2*(1/1000) -> -3.024 | E7: =(-1)*ScenarioParameters!$B$6/2*(1/1000) -> -3.024
A8: Marketing & support cost | D8: =(-1)*ScenarioParameters!$B$7/4*(1/1000) -> -210 | E8: =(-1)*ScenarioParameters!$B$7/4*(1/1000) -> -210 | F8: =(-1)*ScenarioParameters!$B$7/4*(1/1000) -> -210 | G8: =(-1)*ScenarioParameters!$B$7/4*(1/1000) -> -210 | H8: =(-1)*ScenarioParameters!$B$7/4*(1/1000) -> -210 | I8: =(-1)*ScenarioParameters!$B$7/4*(1/1000) -> -210 | J8: =(-1)*ScenarioParameters!$B$7/4*(1/1000) -> -210 | K8: =(-1)*ScenarioParameters!$B$7/4*(1/1000) -> -210 | ... Q8: =(-1)*ScenarioParameters!$B$7/4*(1/1000) -> -210
A9: Production volume | E9: =(-1)*(ScenarioParameters!$B$5)*(ScenarioParameters!$B$2/4)*(1/1000) -> #VALUE! | F9: =(-1)*(ScenarioParameters!$B$5)*(ScenarioParameters!$B$2/4)*(1/1000) -> #VALUE! | G9: =(-1)*(ScenarioParameters!$B$5)*(ScenarioParameters!$B$2/4)*(1/1000) -> #VALUE! | H9: =(-1)*(ScenarioParameters!$B$5)*(ScenarioParameters!$B$2/4)*(1/1000) -> #VALUE! | I9: =(-1)*(ScenarioParameters!$B$5)*(ScenarioParameters!$B$2/4)*(1/1000) -> #VALUE! | J9: =(-1)*(ScenarioParameters!$B$5)*(ScenarioParameters!$B$2/4)*(1/1000) -> #VALUE! | K9: =(-1)*(ScenarioParameters!$B$5)*(ScenarioParameters!$B$2/4)*(1/1000) -> #VALUE! | L9: =(-1)*(ScenarioParameters!$B$5)*(ScenarioParameters!$B$2/4)*(1/1000) -> #VALUE! | ... Q9: =(-1)*(ScenarioParameters!$B$5)*(ScenarioParameters!$B$2/4)*(1/1000) -> #VALUE!
A10: Unit product cost | E10: =ScenarioParameters!$B$2/4 -> #VALUE! | F10: =ScenarioParameters!$B$2/4 -> #VALUE! | G10: =ScenarioParameters!$B$2/4 -> #VALUE! | H10: =ScenarioParameters!$B$2/4 -> #VALUE! | I10: =ScenarioParameters!$B$2/4 -> #VALUE! | J10: =ScenarioParameters!$B$2/4 -> #VALUE! | K10: =ScenarioParameters!$B$2/4 -> #VALUE! | L10: =ScenarioParameters!$B$2/4 -> #VALUE! | ... Q10: =ScenarioParameters!$B$2/4 -> #VALUE!
A11: Sales revenue | E11: =E9/E10 -> #VALUE! | F11: =F9/F10 -> #VALUE! | G11: =G9/G10 -> #VALUE! | H11: =H9/H10 -> #VALUE! | I11: =I9/I10 -> #VALUE! | J11: =J9/J10 -> #VALUE! | K11: =K9/K10 -> #VALUE! | L11: =L9/L10 -> #VALUE! | ... Q11: =Q9/Q10 -> #VALUE!
A12: sales volume | E12: =(ScenarioParameters!$B$4*ScenarioParameters!$B$2/4)*(1/1000) -> #VALUE! | F12: =(ScenarioParameters!$B$4*ScenarioParameters!$B$2/4)*(1/1000) -> #VALUE! | G12: =(ScenarioParameters!$B$4*ScenarioParameters!$B$2/4)*(1/1000) -> #VALUE! | H12: =(ScenarioParameters!$B$4*ScenarioParameters!$B$2/4)*(1/1000) -> #VALUE! | I12: =(ScenarioParameters!$B$4*ScenarioParameters!$B$2/4)*(1/1000) -> #VALUE! | J12: =(ScenarioParameters!$B$4*ScenarioParameters!$B$2/4)*(1/1000) -> #VALUE! | K12: =(ScenarioParameters!$B$4*ScenarioParameters!$B$2/4)*(1/1000) -> #VALUE! | L12: =(ScenarioParameters!$B$4*ScenarioParameters!$B$2/4)*(1/1000) -> #VALUE! | ... Q12: =(ScenarioParameters!$B$4*ScenarioParameters!$B$2/4)*(1/1000) -> #VALUE!
A13: unit price | E13: =ScenarioParameters!$B$2/4 -> #VALUE! | F13: =ScenarioParameters!$B$2/4 -> #VALUE! | G13: =ScenarioParameters!$B$2/4 -> #VALUE! | H13: =ScenarioParameters!$B$2/4 -> #VALUE! | I13: =ScenarioParameters!$B$2/4 -> #VALUE! | J13: =ScenarioParameters!$B$2/4 -> #VALUE! | K13: =ScenarioParameters!$B$2/4 -> #VALUE! | L13: =ScenarioParameters!$B$2/4 -> #VALUE! | ... Q13: =ScenarioParameters!$B$2/4 -> #VALUE!
E14: =E12/E13 -> #VALUE! | F14: =F12/F13 -> #VALUE! | G14: =G12/G13 -> #VALUE! | H14: =H12/H13 -> #VALUE! | I14: =I12/I13 -> #VALUE! | J14: =J12/J13 -> #VALUE! | K14: =K12/K13 -> #VALUE! | L14: =L12/L13 -> #VALUE! | ... Q14: =Q12/Q13 -> #VALUE!
A16: Period Cash Flow | B16: =SUM(B6+B7+B8+B9+B12) -> -15.12 | C16: =SUM(C6+C7+C8+C9+C12) -> -18.144 | D16: =SUM(D6+D7+D8+D9+D12) -> -213.024 | E16: =SUM(E6+E7+E8+E9+E12) -> #VALUE! | F16: =SUM(F6+F7+F8+F9+F12) -> #VALUE! | G16: =SUM(G6+G7+G8+G9+G12) -> #VALUE! | H16: =SUM(H6+H7+H8+H9+H12) -> #VALUE! | I16: =SUM(I6+I7+I8+I9+I12) -> #VALUE! | ... Q16: =SUM(Q6+Q7+Q8+Q9+Q12) -> #VALUE!
A17: Unit Price | B17: =B16 -> -15.12 | C17: =C16/(1+(ScenarioParameters!$B$8/100)/4)^B3 -> -17.831941 | D17: =D16/(1+(ScenarioParameters!$B$8/100)/4)^C3 -> -205.75941 | E17: =E16/(1+(ScenarioParameters!$B$8/100)/4)^D3 -> #VALUE! | F17: =F16/(1+(ScenarioParameters!$B$8/100)/4)^E3 -> #VALUE! | G17: =G16/(1+(ScenarioParameters!$B$8/100)/4)^F3 -> #VALUE! | H17: =H16/(1+(ScenarioParameters!$B$8/100)/4)^G3 -> #VALUE! | I17: =I16/(1+(ScenarioParameters!$B$8/100)/4)^H3 -> #VALUE! | J17: =J16/(1+(ScenarioParameters!$B$8/100)/4)^I3 -> #VALUE! | ... Q17: =Q16/(1+(ScenarioParameters!$B$8/100)/4)^P3 -> #VALUE!
A19: Project NVP | B19: =SUM(B17:Q17) -> #VALUE!

Sheet +1 DevTime
A1: Dev Time
B2: Year 1 | F2: Year 2 | J2: Year 3 | N2: Year 4
A3: Period | B3: 1 | C3: =B3+1 -> 2 | D3: =C3+1 -> 3 | E3: =D3+1 -> 4 | F3: =E3+1 -> 5 | G3: =F3+1 -> 6 | H3: =G3+1 -> 7 | I3: =H3+1 -> 8 | J3: =I3+1 -> 9 | ... Q3: =P3+1 -> 16
A4: ($Value in thousands) | B4: Q1 | C4: Q2 | D4: Q3 | E4: Q4 | F4: Q1 | G4: Q2 | H4: Q3 | I4: Q4 | J4: Q1 | K4: Q2 | L4: Q3 | M4: Q4 | N4: Q1 | O4: Q2 | P4: Q3 | Q4: Q4
A6: Development Cost | B6: =(-1)*ScenarioParameters!$B$3/4*(1/1000) -> -15.12 | C6: =(-1)*ScenarioParameters!$B$3/4*(1/1000) -> -15.12 | D6: =(-1)*ScenarioParameters!$B$3/4*(1/1000) -> -15.12 | E6: =(-1)*ScenarioParameters!$B$3/4*(1/1000) -> -15.12 | F6: =(-1)*ScenarioParameters!$B$3/4*(1/1000) -> -15.12
A7: Ramp-up cost | F7: =(-1)*ScenarioParameters!$B$6/2*(1/1000) -> -3.024 | G7: =(-1)*ScenarioParameters!$B$6/2*(1/1000) -> -3.024
A8: Marketing & support cost | G8: =(-1)*ScenarioParameters!$B$7/4*(1/1000) -> -210 | H8: =(-1)*ScenarioParameters!$B$7/4*(1/1000) -> -210 | I8: =(-1)*ScenarioParameters!$B$7/4*(1/1000) -> -210 | J8: =(-1)*ScenarioParameters!$B$7/4*(1/1000) -> -210 | K8: =(-1)*ScenarioParameters!$B$7/4*(1/1000) -> -210 | L8: =(-1)*ScenarioParameters!$B$7/4*(1/1000) -> -210 | M8: =(-1)*ScenarioParameters!$B$7/4*(1/1000) -> -210 | N8: =(-1)*ScenarioParameters!$B$7/4*(1/1000) -> -210 | ... Q8: =(-1)*ScenarioParameters!$B$7/4*(1/1000) -> -210
A9: Production volume | H9: =(-1)*(ScenarioParameters!$B$5)*(ScenarioParameters!$B$2/4)*(1/1000) -> #VALUE! | I9: =(-1)*(ScenarioParameters!$B$5)*(ScenarioParameters!$B$2/4)*(1/1000) -> #VALUE! | J9: =(-1)*(ScenarioParameters!$B$5)*(ScenarioParameters!$B$2/4)*(1/1000) -> #VALUE! | K9: =(-1)*(ScenarioParameters!$B$5)*(ScenarioParameters!$B$2/4)*(1/1000) -> #VALUE! | L9: =(-1)*(ScenarioParameters!$B$5)*(ScenarioParameters!$B$2/4)*(1/1000) -> #VALUE! | M9: =(-1)*(ScenarioParameters!$B$5)*(ScenarioParameters!$B$2/4)*(1/1000) -> #VALUE! | N9: =(-1)*(ScenarioParameters!$B$5)*(ScenarioParameters!$B$2/4)*(1/1000) -> #VALUE! | O9: =(-1)*(ScenarioParameters!$B$5)*(ScenarioParameters!$B$2/4)*(1/1000) -> #VALUE! | ... Q9: =(-1)*(ScenarioParameters!$B$5)*(ScenarioParameters!$B$2/4)*(1/1000) -> #VALUE!
A10: Unit product cost | H10: =ScenarioParameters!$B$2/4 -> #VALUE! | I10: =ScenarioParameters!$B$2/4 -> #VALUE! | J10: =ScenarioParameters!$B$2/4 -> #VALUE! | K10: =ScenarioParameters!$B$2/4 -> #VALUE! | L10: =ScenarioParameters!$B$2/4 -> #VALUE! | M10: =ScenarioParameters!$B$2/4 -> #VALUE! | N10: =ScenarioParameters!$B$2/4 -> #VALUE! | O10: =ScenarioParameters!$B$2/4 -> #VALUE! | ... Q10: =ScenarioParameters!$B$2/4 -> #VALUE!
A11: Sales revenue | H11: =H9/H10 -> #VALUE! | I11: =I9/I10 -> #VALUE! | J11: =J9/J10 -> #VALUE! | K11: =K9/K10 -> #VALUE! | L11: =L9/L10 -> #VALUE! | M11: =M9/M10 -> #VALUE! | N11: =N9/N10 -> #VALUE! | O11: =O9/O10 -> #VALUE! | ... Q11: =Q9/Q10 -> #VALUE!
A12: sales volume | H12: =(ScenarioParameters!$B$4*ScenarioParameters!$B$2/4)*(1/1000) -> #VALUE! | I12: =(ScenarioParameters!$B$4*ScenarioParameters!$B$2/4)*(1/1000) -> #VALUE! | J12: =(ScenarioParameters!$B$4*ScenarioParameters!$B$2/4)*(1/1000) -> #VALUE! | K12: =(ScenarioParameters!$B$4*ScenarioParameters!$B$2/4)*(1/1000) -> #VALUE! | L12: =(ScenarioParameters!$B$4*ScenarioParameters!$B$2/4)*(1/1000) -> #VALUE! | M12: =(ScenarioParameters!$B$4*ScenarioParameters!$B$2/4)*(1/1000) -> #VALUE! | N12: =(ScenarioParameters!$B$4*ScenarioParameters!$B$2/4)*(1/1000) -> #VALUE! | O12: =(ScenarioParameters!$B$4*ScenarioParameters!$B$2/4)*(1/1000) -> #VALUE! | ... Q12: =(ScenarioParameters!$B$4*ScenarioParameters!$B$2/4)*(1/1000) -> #VALUE!
A13: unit price | H13: =ScenarioParameters!$B$2/4 -> #VALUE! | I13: =ScenarioParameters!$B$2/4 -> #VALUE! | J13: =ScenarioParameters!$B$2/4 -> #VALUE! | K13: =ScenarioParameters!$B$2/4 -> #VALUE! | L13: =ScenarioParameters!$B$2/4 -> #VALUE! | M13: =ScenarioParameters!$B$2/4 -> #VALUE! | N13: =ScenarioParameters!$B$2/4 -> #VALUE! | O13: =ScenarioParameters!$B$2/4 -> #VALUE! | ... Q13: =ScenarioParameters!$B$2/4 -> #VALUE!
H14: =H12/H13 -> #VALUE! | I14: =I12/I13 -> #VALUE! | J14: =J12/J13 -> #VALUE! | K14: =K12/K13 -> #VALUE! | L14: =L12/L13 -> #VALUE! | M14: =M12/M13 -> #VALUE! | N14: =N12/N13 -> #VALUE! | O14: =O12/O13 -> #VALUE! | ... Q14: =Q12/Q13 -> #VALUE!
A16: Period Cash Flow | B16: =SUM(B6+B7+B8+B9+B12) -> -15.12 | C16: =SUM(C6+C7+C8+C9+C12) -> -15.12 | D16: =SUM(D6+D7+D8+D9+D12) -> -15.12 | E16: =SUM(E6+E7+E8+E9+E12) -> -15.12 | F16: =SUM(F6+F7+F8+F9+F12) -> -18.144 | G16: =SUM(G6+G7+G8+G9+G12) -> -213.024 | H16: =SUM(H6+H7+H8+H9+H12) -> #VALUE! | I16: =SUM(I6+I7+I8+I9+I12) -> #VALUE! | ... Q16: =SUM(Q6+Q7+Q8+Q9+Q12) -> #VALUE!
A17: Unit Price | B17: =B16 -> -15.12 | C17: =C16/(1+(ScenarioParameters!$B$8/100)/4)^B3 -> -14.859951 | D17: =D16/(1+(ScenarioParameters!$B$8/100)/4)^C3 -> -14.604374 | E17: =E16/(1+(ScenarioParameters!$B$8/100)/4)^D3 -> -14.353193 | F17: =F16/(1+(ScenarioParameters!$B$8/100)/4)^E3 -> -16.927599 | G17: =G16/(1+(ScenarioParameters!$B$8/100)/4)^F3 -> -195.32438 | H17: =H16/(1+(ScenarioParameters!$B$8/100)/4)^G3 -> #VALUE! | I17: =I16/(1+(ScenarioParameters!$B$8/100)/4)^H3 -> #VALUE! | J17: =J16/(1+(ScenarioParameters!$B$8/100)/4)^I3 -> #VALUE! | ... Q17: =Q16/(1+(ScenarioParameters!$B$8/100)/4)^P3 -> #VALUE!
A19: Project NVP | B19: =SUM(B17:Q17) -> #VALUE!

Sheet +2 DevTime
A1: Dev Time
B2: Year 1 | F2: Year 2 | J2: Year 3 | N2: Year 4
A3: Period | B3: 1 | C3: =B3+1 -> 2 | D3: =C3+1 -> 3 | E3: =D3+1 -> 4 | F3: =E3+1 -> 5 | G3: =F3+1 -> 6 | H3: =G3+1 -> 7 | I3: =H3+1 -> 8 | J3: =I3+1 -> 9 | ... Q3: =P3+1 -> 16
A4: ($Value in thousands) | B4: Q1 | C4: Q2 | D4: Q3 | E4: Q4 | F4: Q1 | G4: Q2 | H4: Q3 | I4: Q4 | J4: Q1 | K4: Q2 | L4: Q3 | M4: Q4 | N4: Q1 | O4: Q2 | P4: Q3 | Q4: Q4
A6: Development Cost | B6: =(-1)*ScenarioParameters!$B$3/4*(1/1000) -> -15.12 | C6: =(-1)*ScenarioParameters!$B$3/4*(1/1000) -> -15.12 | D6: =(-1)*ScenarioParameters!$B$3/4*(1/1000) -> -15.12 | E6: =(-1)*ScenarioParameters!$B$3/4*(1/1000) -> -15.12 | F6: =(-1)*ScenarioParameters!$B$3/4*(1/1000) -> -15.12 | G6: =(-1)*ScenarioParameters!$B$3/4*(1/1000) -> -15.12
A7: Ramp-up cost | G7: =(-1)*ScenarioParameters!$B$6/2*(1/1000) -> -3.024 | H7: =(-1)*ScenarioParameters!$B$6/2*(1/1000) -> -3.024
A8: Marketing & support cost | H8: =(-1)*ScenarioParameters!$B$7/4*(1/1000) -> -210 | I8: =(-1)*ScenarioParameters!$B$7/4*(1/1000) -> -210 | J8: =(-1)*ScenarioParameters!$B$7/4*(1/1000) -> -210 | K8: =(-1)*ScenarioParameters!$B$7/4*(1/1000) -> -210 | L8: =(-1)*ScenarioParameters!$B$7/4*(1/1000) -> -210 | M8: =(-1)*ScenarioParameters!$B$7/4*(1/1000) -> -210 | N8: =(-1)*ScenarioParameters!$B$7/4*(1/1000) -> -210 | O8: =(-1)*ScenarioParameters!$B$7/4*(1/1000) -> -210 | ... Q8: =(-1)*ScenarioParameters!$B$7/4*(1/1000) -> -210
A9: Production volume | I9: =(-1)*(ScenarioParameters!$B$5)*(ScenarioParameters!$B$2/4)*(1/1000) -> #VALUE! | J9: =(-1)*(ScenarioParameters!$B$5)*(ScenarioParameters!$B$2/4)*(1/1000) -> #VALUE! | K9: =(-1)*(ScenarioParameters!$B$5)*(ScenarioParameters!$B$2/4)*(1/1000) -> #VALUE! | L9: =(-1)*(ScenarioParameters!$B$5)*(ScenarioParameters!$B$2/4)*(1/1000) -> #VALUE! | M9: =(-1)*(ScenarioParameters!$B$5)*(ScenarioParameters!$B$2/4)*(1/1000) -> #VALUE! | N9: =(-1)*(ScenarioParameters!$B$5)*(ScenarioParameters!$B$2/4)*(1/1000) -> #VALUE! | O9: =(-1)*(ScenarioParameters!$B$5)*(ScenarioParameters!$B$2/4)*(1/1000) -> #VALUE! | P9: =(-1)*(ScenarioParameters!$B$5)*(ScenarioParameters!$B$2/4)*(1/1000) -> #VALUE! | Q9: =(-1)*(ScenarioParameters!$B$5)*(ScenarioParameters!$B$2/4)*(1/1000) -> #VALUE!
A10: Unit product cost | I10: =ScenarioParameters!$B$2/4 -> #VALUE! | J10: =ScenarioParameters!$B$2/4 -> #VALUE! | K10: =ScenarioParameters!$B$2/4 -> #VALUE! | L10: =ScenarioParameters!$B$2/4 -> #VALUE! | M10: =ScenarioParameters!$B$2/4 -> #VALUE! | N10: =ScenarioParameters!$B$2/4 -> #VALUE! | O10: =ScenarioParameters!$B$2/4 -> #VALUE! | P10: =ScenarioParameters!$B$2/4 -> #VALUE! | Q10: =ScenarioParameters!$B$2/4 -> #VALUE!
A11: Sales revenue | I11: =I9/I10 -> #VALUE! | J11: =J9/J10 -> #VALUE! | K11: =K9/K10 -> #VALUE! | L11: =L9/L10 -> #VALUE! | M11: =M9/M10 -> #VALUE! | N11: =N9/N10 -> #VALUE! | O11: =O9/O10 -> #VALUE! | P11: =P9/P10 -> #VALUE! | Q11: =Q9/Q10 -> #VALUE!
A12: sales volume | I12: =(ScenarioParameters!$B$4*ScenarioParameters!$B$2/4)*(1/1000) -> #VALUE! | J12: =(ScenarioParameters!$B$4*ScenarioParameters!$B$2/4)*(1/1000) -> #VALUE! | K12: =(ScenarioParameters!$B$4*ScenarioParameters!$B$2/4)*(1/1000) -> #VALUE! | L12: =(ScenarioParameters!$B$4*ScenarioParameters!$B$2/4)*(1/1000) -> #VALUE! | M12: =(ScenarioParameters!$B$4*ScenarioParameters!$B$2/4)*(1/1000) -> #VALUE! | N12: =(ScenarioParameters!$B$4*ScenarioParameters!$B$2/4)*(1/1000) -> #VALUE! | O12: =(ScenarioParameters!$B$4*ScenarioParameters!$B$2/4)*(1/1000) -> #VALUE! | P12: =(ScenarioParameters!$B$4*ScenarioParameters!$B$2/4)*(1/1000) -> #VALUE! | Q12: =(ScenarioParameters!$B$4*ScenarioParameters!$B$2/4)*(1/1000) -> #VALUE!
A13: unit price | I13: =ScenarioParameters!$B$2/4 -> #VALUE! | J13: =ScenarioParameters!$B$2/4 -> #VALUE! | K13: =ScenarioParameters!$B$2/4 -> #VALUE! | L13: =ScenarioParameters!$B$2/4 -> #VALUE! | M13: =ScenarioParameters!$B$2/4 -> #VALUE! | N13: =ScenarioParameters!$B$2/4 -> #VALUE! | O13: =ScenarioParameters!$B$2/4 -> #VALUE! | P13: =ScenarioParameters!$B$2/4 -> #VALUE! | Q13: =ScenarioParameters!$B$2/4 -> #VALUE!
I14: =I12/I13 -> #VALUE! | J14: =J12/J13 -> #VALUE! | K14: =K12/K13 -> #VALUE! | L14: =L12/L13 -> #VALUE! | M14: =M12/M13 -> #VALUE! | N14: =N12/N13 -> #VALUE! | O14: =O12/O13 -> #VALUE! | P14: =P12/P13 -> #VALUE! | Q14: =Q12/Q13 -> #VALUE!
A16: Period Cash Flow | B16: =SUM(B6+B7+B8+B9+B12) -> -15.12 | C16: =SUM(C6+C7+C8+C9+C12) -> -15.12 | D16: =SUM(D6+D7+D8+D9+D12) -> -15.12 | E16: =SUM(E6+E7+E8+E9+E12) -> -15.12 | F16: =SUM(F6+F7+F8+F9+F12) -> -15.12 | G16: =SUM(G6+G7+G8+G9+G12) -> -18.144 | H16: =SUM(H6+H7+H8+H9+H12) -> -213.024 | I16: =SUM(I6+I7+I8+I9+I12) -> #VALUE! | ... Q16: =SUM(Q6+Q7+Q8+Q9+Q12) -> #VALUE!
A17: Unit Price | B17: =B16 -> -15.12 | C17: =C16/(1+(ScenarioParameters!$B$8/100)/4)^B3 -> -14.859951 | D17: =D16/(1+(ScenarioParameters!$B$8/100)/4)^C3 -> -14.604374 | E17: =E16/(1+(ScenarioParameters!$B$8/100)/4)^D3 -> -14.353193 | F17: =F16/(1+(ScenarioParameters!$B$8/100)/4)^E3 -> -14.106333 | G17: =G16/(1+(ScenarioParameters!$B$8/100)/4)^F3 -> -16.636461 | H17: =H16/(1+(ScenarioParameters!$B$8/100)/4)^G3 -> -191.96499 | I17: =I16/(1+(ScenarioParameters!$B$8/100)/4)^H3 -> #VALUE! | J17: =J16/(1+(ScenarioParameters!$B$8/100)/4)^I3 -> #VALUE! | ... Q17: =Q16/(1+(ScenarioParameters!$B$8/100)/4)^P3 -> #VALUE!
A19: Project NVP | B19: =SUM(B17:Q17) -> #VALUE!

Sheet +3 DevTime
A1: Dev Time
B2: Year 1 | F2: Year 2 | J2: Year 3 | N2: Year 4
A3: Period | B3: 1 | C3: =B3+1 -> 2 | D3: =C3+1 -> 3 | E3: =D3+1 -> 4 | F3: =E3+1 -> 5 | G3: =F3+1 -> 6 | H3: =G3+1 -> 7 | I3: =H3+1 -> 8 | J3: =I3+1 -> 9 | ... Q3: =P3+1 -> 16
A4: ($Value in thousands) | B4: Q1 | C4: Q2 | D4: Q3 | E4: Q4 | F4: Q1 | G4: Q2 | H4: Q3 | I4: Q4 | J4: Q1 | K4: Q2 | L4: Q3 | M4: Q4 | N4: Q1 | O4: Q2 | P4: Q3 | Q4: Q4
A6: Development Cost | B6: =(-1)*ScenarioParameters!$B$3/4*(1/1000) -> -15.12 | C6: =(-1)*ScenarioParameters!$B$3/4*(1/1000) -> -15.12 | D6: =(-1)*ScenarioParameters!$B$3/4*(1/1000) -> -15.12 | E6: =(-1)*ScenarioParameters!$B$3/4*(1/1000) -> -15.12 | F6: =(-1)*ScenarioParameters!$B$3/4*(1/1000) -> -15.12 | G6: =(-1)*ScenarioParameters!$B$3/4*(1/1000) -> -15.12 | H6: =(-1)*ScenarioParameters!$B$3/4*(1/1000) -> -15.12
A7: Ramp-up cost | H7: =(-1)*ScenarioParameters!$B$6/2*(1/1000) -> -3.024 | I7: =(-1)*ScenarioParameters!$B$6/2*(1/1000) -> -3.024
A8: Marketing & support cost | I8: =(-1)*ScenarioParameters!$B$7/4*(1/1000) -> -210 | J8: =(-1)*ScenarioParameters!$B$7/4*(1/1000) -> -210 | K8: =(-1)*ScenarioParameters!$B$7/4*(1/1000) -> -210 | L8: =(-1)*ScenarioParameters!$B$7/4*(1/1000) -> -210 | M8: =(-1)*ScenarioParameters!$B$7/4*(1/1000) -> -210 | N8: =(-1)*ScenarioParameters!$B$7/4*(1/1000) -> -210 | O8: =(-1)*ScenarioParameters!$B$7/4*(1/1000) -> -210 | P8: =(-1)*ScenarioParameters!$B$7/4*(1/1000) -> -210 | Q8: =(-1)*ScenarioParameters!$B$7/4*(1/1000) -> -210
A9: Production volume | J9: =(-1)*(ScenarioParameters!$B$5)*(ScenarioParameters!$B$2/4)*(1/1000) -> #VALUE! | K9: =(-1)*(ScenarioParameters!$B$5)*(ScenarioParameters!$B$2/4)*(1/1000) -> #VALUE! | L9: =(-1)*(ScenarioParameters!$B$5)*(ScenarioParameters!$B$2/4)*(1/1000) -> #VALUE! | M9: =(-1)*(ScenarioParameters!$B$5)*(ScenarioParameters!$B$2/4)*(1/1000) -> #VALUE! | N9: =(-1)*(ScenarioParameters!$B$5)*(ScenarioParameters!$B$2/4)*(1/1000) -> #VALUE! | O9: =(-1)*(ScenarioParameters!$B$5)*(ScenarioParameters!$B$2/4)*(1/1000) -> #VALUE! | P9: =(-1)*(ScenarioParameters!$B$5)*(ScenarioParameters!$B$2/4)*(1/1000) -> #VALUE! | Q9: =(-1)*(ScenarioParameters!$B$5)*(ScenarioParameters!$B$2/4)*(1/1000) -> #VALUE!
A10: Unit product cost | J10: =ScenarioParameters!$B$2/4 -> #VALUE! | K10: =ScenarioParameters!$B$2/4 -> #VALUE! | L10: =ScenarioParameters!$B$2/4 -> #VALUE! | M10: =ScenarioParameters!$B$2/4 -> #VALUE! | N10: =ScenarioParameters!$B$2/4 -> #VALUE! | O10: =ScenarioParameters!$B$2/4 -> #VALUE! | P10: =ScenarioParameters!$B$2/4 -> #VALUE! | Q10: =ScenarioParameters!$B$2/4 -> #VALUE!
A11: Sales revenue | J11: =J9/J10 -> #VALUE! | K11: =K9/K10 -> #VALUE! | L11: =L9/L10 -> #VALUE! | M11: =M9/M10 -> #VALUE! | N11: =N9/N10 -> #VALUE! | O11: =O9/O10 -> #VALUE! | P11: =P9/P10 -> #VALUE! | Q11: =Q9/Q10 -> #VALUE!
A12: sales volume | J12: =(ScenarioParameters!$B$4*ScenarioParameters!$B$2/4)*(1/1000) -> #VALUE! | K12: =(ScenarioParameters!$B$4*ScenarioParameters!$B$2/4)*(1/1000) -> #VALUE! | L12: =(ScenarioParameters!$B$4*ScenarioParameters!$B$2/4)*(1/1000) -> #VALUE! | M12: =(ScenarioParameters!$B$4*ScenarioParameters!$B$2/4)*(1/1000) -> #VALUE! | N12: =(ScenarioParameters!$B$4*ScenarioParameters!$B$2/4)*(1/1000) -> #VALUE! | O12: =(ScenarioParameters!$B$4*ScenarioParameters!$B$2/4)*(1/1000) -> #VALUE! | P12: =(ScenarioParameters!$B$4*ScenarioParameters!$B$2/4)*(1/1000) -> #VALUE! | Q12: =(ScenarioParameters!$B$4*ScenarioParameters!$B$2/4)*(1/1000) -> #VALUE!
A13: unit price | J13: =ScenarioParameters!$B$2/4 -> #VALUE! | K13: =ScenarioParameters!$B$2/4 -> #VALUE! | L13: =ScenarioParameters!$B$2/4 -> #VALUE! | M13: =ScenarioParameters!$B$2/4 -> #VALUE! | N13: =ScenarioParameters!$B$2/4 -> #VALUE! | O13: =ScenarioParameters!$B$2/4 -> #VALUE! | P13: =ScenarioParameters!$B$2/4 -> #VALUE! | Q13: =ScenarioParameters!$B$2/4 -> #VALUE!
J14: =J12/J13 -> #VALUE! | K14: =K12/K13 -> #VALUE! | L14: =L12/L13 -> #VALUE! | M14: =M12/M13 -> #VALUE! | N14: =N12/N13 -> #VALUE! | O14: =O12/O13 -> #VALUE! | P14: =P12/P13 -> #VALUE! | Q14: =Q12/Q13 -> #VALUE!
A16: Period Cash Flow | B16: =SUM(B6+B7+B8+B9+B12) -> -15.12 | C16: =SUM(C6+C7+C8+C9+C12) -> -15.12 | D16: =SUM(D6+D7+D8+D9+D12) -> -15.12 | E16: =SUM(E6+E7+E8+E9+E12) -> -15.12 | F16: =SUM(F6+F7+F8+F9+F12) -> -15.12 | G16: =SUM(G6+G7+G8+G9+G12) -> -15.12 | H16: =SUM(H6+H7+H8+H9+H12) -> -18.144 | I16: =SUM(I6+I7+I8+I9+I12) -> -213.024 | ... Q16: =SUM(Q6+Q7+Q8+Q9+Q12) -> #VALUE!
A17: Unit Price | B17: =B16 -> -15.12 | C17: =C16/(1+(ScenarioParameters!$B$8/100)/4)^B3 -> -14.859951 | D17: =D16/(1+(ScenarioParameters!$B$8/100)/4)^C3 -> -14.604374 | E17: =E16/(1+(ScenarioParameters!$B$8/100)/4)^D3 -> -14.353193 | F17: =F16/(1+(ScenarioParameters!$B$8/100)/4)^E3 -> -14.106333 | G17: =G16/(1+(ScenarioParameters!$B$8/100)/4)^F3 -> -13.863718 | H17: =H16/(1+(ScenarioParameters!$B$8/100)/4)^G3 -> -16.35033 | I17: =I16/(1+(ScenarioParameters!$B$8/100)/4)^H3 -> -188.66338 | J17: =J16/(1+(ScenarioParameters!$B$8/100)/4)^I3 -> #VALUE! | ... Q17: =Q16/(1+(ScenarioParameters!$B$8/100)/4)^P3 -> #VALUE!
A19: Project NVP | B19: =SUM(B17:Q17) -> #VALUE!

Sheet DevTime_Sensitivity
A1: Base Dev Cost, $ | B1: Change in DevTime, # of Qrts | C1: Development Cost, $ Thounsands | D1: Change in Development Cost, $ Thousands | E1: NPV, $ Thousands | F1: Change in NPV, % | G1: Change in NPV, $ Thousands
A2: =ScenarioParameters!$B$3/1000 -> 60.48 | B2: 3 | C2: =SUM('+3 DevTime'!$B$6:$Q$6)*-1 -> 105.84 | D2: =C2-A2 -> 45.36 | E2: ='+3 DevTime'!$B$19 -> #VALUE! | F2: =(E2-$E$5)/$E$5 -> #VALUE! | G2: =E2-$E$5 -> #VALUE!
A3: =ScenarioParameters!$B$3/1000 -> 60.48 | B3: 2 | C3: =SUM('+2 DevTime'!$B$6:$Q$6)*-1 -> 90.72 | D3: =C3-A3 -> 30.24 | E3: ='+2 DevTime'!$B$19 -> #VALUE! | F3: =(E3-$E$5)/$E$5 -> #VALUE! | G3: =E3-$E$5 -> #VALUE!
A4: =ScenarioParameters!$B$3/1000 -> 60.48 | B4: 1 | C4: =SUM('+1 DevTime'!$B$6:$Q$6)*-1 -> 75.6 | D4: =C4-A4 -> 15.12 | E4: ='+1 DevTime'!$B$19 -> #VALUE! | F4: =(E4-$E$5)/$E$5 -> #VALUE! | G4: =E4-$E$5 -> #VALUE!
A5: 25000 | B5: 0 | C5: =-25000*-1 -> 25000 | D5: =C5-A5 -> 0 | E5: =BaseCase!B19 -> 25465.99 | F5: =(E5-$E$5)/$E$5 -> 0 | G5: =E5-$E$5 -> 0
A6: 25000 | B6: -1 | C6: =SUM('-1 DevTime'!$B$6:$Q$6)*-1 -> 45.36 | D6: =C6-A6 -> -24954.64 | E6: ='-1 DevTime'!$B$19 -> #VALUE! | F6: =(E6-$E$5)/$E$5 -> #VALUE! | G6: =E6-$E$5 -> #VALUE!
A7: 25000 | B7: -2 | C7: =SUM('-2 DevTime'!$B$6:$Q$6)*-1 -> 30.24 | D7: =C7-A7 -> -24969.76 | E7: ='-2 DevTime'!$B$19 -> #VALUE! | F7: =(E7-$E$5)/$E$5 -> #VALUE! | G7: =E7-$E$5 -> #VALUE!

Sheet UnitCost_Sensitivity
A1: Base Unit Cost, $ | B1: Change in Unit Production Cost, % | C1: New Unit Cost | D1: Unit Volume | E1: Total Cost Product Cost | F1: Change in Total Product Cost, $ Thousands | G1: NPV, $ Thousands | H1: Change in NPV, % | I1: Change in NPV, $ Thousands
A2: =ScenarioParameters!B5 -> 115.28 | B2: 0.3 | C2: =A2+A2*B2 -> 149.864 | D2: =SUM('+30 UnitCost'!F10:AB10) -> 192433.36 | E2: =SUM('+30 UnitCost'!F9:AB9) -> -29846.624 | F2: =E2+ABS($E$5) -> -7662.9061 | G2: ='+30 UnitCost'!$B$19 -> 19402.792 | H2: =(G2-$G$5)/$G$5 -> -0.23809001 | I2: =G2-$G$5 -> -6063.1977
A3: =A2 -> 115.28 | B3: 0.2 | C3: =A3+A3*B3 -> 138.336 | D3: =SUM('+20 UnitCost'!F10:AB10) -> 192433.36 | E3: =SUM('+20 UnitCost'!F9:AB9) -> -27550.73 | F3: =E3+ABS($E$5) -> -5367.012 | G3: ='+20 UnitCost'!$B$19 -> 21234.76 | H3: =(G3-$G$5)/$G$5 -> -0.16615217 | I3: =G3-$G$5 -> -4231.2295
A4: =A3 -> 115.28 | B4: 0.1 | C4: =A4+A4*B4 -> 126.808 | D4: =SUM('+10 UnitCost'!F10:AB10) -> 192433.36 | E4: =SUM('+10 UnitCost'!F9:AB9) -> -25254.835 | F4: =E4+ABS($E$5) -> -3071.1179 | G4: ='+10 UnitCost'!$B$19 -> 23066.729 | H4: =(G4-$G$5)/$G$5 -> -0.094214337 | I4: =G4-$G$5 -> -2399.2614
A5: =A4 -> 115.28 | B5: 0 | C5: =A5+A5*B5 -> 115.28 | D5: =SUM(BaseCase!F10:AB10) -> 192433.36 | E5: =SUM(BaseCase!F9:AB9) -> -22183.717 | F5: =E5+ABS($E$5) -> 0 | G5: =BaseCase!B19 -> 25465.99 | H5: =(G5-$G$5)/$G$5 -> 0 | I5: =G5-$G$5 -> 0
A6: =A5 -> 115.28 | B6: -0.1 | C6: =A6+A6*B6 -> 103.752 | D6: =SUM('-10 UnitCost'!F10:AB10) -> 192433.36 | E6: =SUM('-10 UnitCost'!F9:AB9) -> -20663.047 | F6: =E6+ABS($E$5) -> 1520.6704 | G6: ='-10 UnitCost'!$B$19 -> 26730.665 | H6: =(G6-$G$5)/$G$5 -> 0.049661334 | I6: =G6-$G$5 -> 1264.675
A7: =A6 -> 115.28 | B7: -0.2 | C7: =A7+A7*B7 -> 92.224 | D7: =SUM('-20 UnitCost'!F10:AB10) -> 192433.36 | E7: =SUM('-20 UnitCost'!F9:AB9) -> -18367.153 | F7: =E7+ABS($E$5) -> 3816.5645 | G7: ='-20 UnitCost'!$B$19 -> 28562.633 | H7: =(G7-$G$5)/$G$5 -> 0.12159917 | I7: =G7-$G$5 -> 3096.6432
A8: =A7 -> 115.28 | B8: -0.3 | C8: =A8+A8*B8 -> 80.696 | D8: =SUM('-30 UnitCost'!F10:AB10) -> 192433.36 | E8: =SUM('-30 UnitCost'!F9:AB9) -> -16071.259 | F8: =E8+ABS($E$5) -> 6112.4586 | G8: ='-30 UnitCost'!$B$19 -> 30394.601 | H8: =(G8-$G$5)/$G$5 -> 0.193537 | I8: =G8-$G$5 -> 4928.6114
